Workbook

Sheet Связи
A2: Маркеры | B2: Направление - direction (spr_partners)
B3: Менеджер - Ответсвенный для прогноза (b_crm_deal)
B4: План - Потенциал сумма (b_crm_deal)
B5: Факт - Amount (doc_Sales)
B6: Даты - Date (doc_Sales)
A9: Связи | B9: b_crm_deal - ID
B10: b_uts_crm_deal - VALUE
B12: b_uts_crm_deal - № ЗК
B13: doc_OrderSales- Number
B15: doc_OrderSales- id 1c
B16: doc_Sales - Zakaz_id_1c
B18: doc_OrderSales- Partner id
B19: spr_partners - id_1c

Sheet b_crm_deal
A1: ID | B1: TITLE | C1: ASSIGNED_BY_ID | D1: DATE_CREATE | E1: Группа стадий | F1: Стадия крупно | G1: b_crm_deal_category.NAME.1 | H1: b_crm_status.NAME | I1: Потенциал дата | J1: b_crm_company.TITLE | K1: b_crm_company.Ответственный за клиента | L1: b_crm_deal_category.NAME | M1: LAST_ACTIVITY_TIME | N1: MOVED_TIME | O1: Для проверки | P1: Ответственный | Q1: Потенциал с конверсией | R1: Потенциал сумма | S1: b_crm_company.ID | T1: COMPANY_ID | U1: Прогноз март 2026 | V1: Прогноз апрель 2026 | W1: Сумма с согласовании заказа | X1: Сумма в производстве | Y1: Сумма отгружено | Z1: Сумма в КП | AA1: Срок перехода | AB1: Просрочка | AC1: Ссылка | AD1: Год | AE1: Стандарт/Проект | AF1: Ответсвенный для прогноза
A2: 57250 | B2: Жилой комплекс "Курский" | C2: 110 | D2: 45734.458 | E2: Активные продажи | F2: Лидогенерация | G2: Строительство | H2: Новая сделка | I2: 45991 | J2: null | K2: null | L2: Строительство | M2: 45734.458 | N2: 45734.458 | O2: OK | P2: Алексеева М.И. | Q2: 500000 | R2: 4000000 | S2: null | T2: null | U2: null | V2: null | W2: null | X2: null | Y2: null | Z2: null | AA2: 3 | AB2: Не просрочена | AC2: https://crm.example.com/deal/57250 | AD2: 2025 | AE2: Проект | AF2: Алексеева М.И.
A3: 57249 | B3: Сибур, Анапа (дозаказ) | C3: 101 | D3: 45734.448 | E3: Активные продажи | F3: Технический | G3: Строительство | H3: Запуск в производство | I3: 45777 | J3: Фасад-Строй | K3: Васильева К.А. | L3: Строительство | M3: 45734.451 | N3: 45734.449 | O3: В производстве | P3: Сергеева Н.В. | Q3: 1200000 | R3: 1200000 | S3: 10001 | T3: 10001 | U3: null | V3: null | W3: null | X3: 1200000 | Y3: null | Z3: null | AA3: 15 | AB3: Не просрочена | AC3: https://crm.example.com/deal/57249 | AD3: 2025 | AE3: Проект | AF3: Сергеева Н.В.
A4: 57248 | B4: Артек (дозаказ) | C4: 101 | D4: 45734.431 | E4: Активные продажи | F4: Технический | G4: Строительство | H4: Запуск в производство | I4: 45779 | J4: СтройКомплект | K4: Каримова Д.Р. | L4: Строительство | M4: 45734.431 | N4: 45734.431 | O4: В производстве | P4: Сергеева Н.В. | Q4: 700000 | R4: 700000 | S4: 10002 | T4: 10002 | U4: null | V4: null | W4: null | X4: 1500000 | Y4: null | Z4: null | AA4: 15 | AB4: Не просрочена | AC4: https://crm.example.com/deal/57248 | AD4: 2025 | AE4: Проект | AF4: Сергеева Н.В.
A5: 57247 | B5: Сибур, Анапа (двери) | C5: 101 | D5: 45734.427 | E5: Активные продажи | F5: Технический | G5: Строительство | H5: Запуск в производство | I5: 45780 | J5: Виртус | K5: Сергеева Н.В. | L5: Строительство | M5: 45734.427 | N5: 45734.428 | O5: В производстве | P5: Сергеева Н.В. | Q5: 650000 | R5: 650000 | S5: 10003 | T5: 10003 | U5: null | V5: null | W5: null | X5: 1300000 | Y5: null | Z5: null | AA5: 15 | AB5: Не просрочена | AC5: https://crm.example.com/deal/57247 | AD5: 2025 | AE5: Проект | AF5: Сергеева Н.В.
A6: 57246 | B6: Стандартные отгрузки "РесторанСервис" | C6: 107 | D6: 45734.417 | E6: Активные продажи | F6: Технический | G6: Строительство | H6: Запуск в производство | I6: 45807 | J6: РесторанСервис | K6: Родина Т.В. | L6: Строительство | M6: 45734.417 | N6: 45734.417 | O6: В производстве | P6: Новикова А.В. | Q6: 3500000 | R6: 3500000 | S6: 10004 | T6: 10004 | U6: null | V6: null | W6: null | X6: 600000 | Y6: null | Z6: null | AA6: 15 | AB6: Не просрочена | AC6: https://crm.example.com/deal/57246 | AD6: 2025 | AE6: Стандарт | AF6: Новикова А.В.
A7: 57245 | B7: HPL панели, г. Москва | C7: 102 | D7: 45734.406 | E7: Активные продажи | F7: Лидогенерация | G7: Строительство | H7: Сбор информации | I7: 45867 | J7: null | K7: null | L7: Строительство | M7: 45734.458 | N7: 45734.41 | O7: OK | P7: Петрова Е.В. | Q7: 0 | R7: 0 | S7: null | T7: null | U7: null | V7: null | W7: null | X7: null | Y7: null | Z7: null | AA7: 3 | AB7: Не просрочена | AC7: https://crm.example.com/deal/57245 | AD7: 2025 | AE7: Проект | AF7: Петрова Е.В.
A8: 57244 | B8: Бизнес-центр "Вперед" | C8: 110 | D8: 45734.396 | E8: Активные продажи | F8: Лидогенерация | G8: Строительство | H8: Проверка объекта | I8: 45838 | J8: Фасад-Строй | K8: Васильева К.А. | L8: Строительство | M8: 45734.458 | N8: 45734.427 | O8: OK | P8: Алексеева М.И. | Q8: 2000000 | R8: 2000000 | S8: 10001 | T8: 10001 | U8: null | V8: null | W8: null | X8: null | Y8: null | Z8: null | AA8: null | AB8: Нет | AC8: https://crm.example.com/deal/57244 | AD8: 2025 | AE8: Проект | AF8: Алексеева М.И.
A9: 57243 | B9: Входящий звонок (дилер) | C9: 112 | D9: 45734.375 | E9: Успешно | F9: Передан дилеру | G9: Передан дилеру | H9: Передан дилеру | I9: null | J9: null | K9: null | L9: Передан дилеру | M9: 45734.375 | N9: 45734.376 | O9: OK | P9: Орлова Т.В. | Q9: 0 | R9: 0 | S9: null | T9: null | U9: null | V9: null | W9: null | X9: null | Y9: null | Z9: null | AA9: null | AB9: Нет | AC9: https://crm.example.com/deal/57243 | AD9: 2025 | AE9: Проект | AF9: null
A10: 57242 | B10: Частный дом, Казахстан | C10: 107 | D10: 45734.354 | E10: Активные продажи | F10: Квалификация | G10: Инжиниринг | H10: В очереди | I10: 45899 | J10: ТОО "Еврофасад" | K10: Новикова А.В. | L10: Инжиниринг | M10: 45734.354 | N10: 45734.358 | O10: OK | P10: Новикова А.В. | Q10: 0 | R10: 0 | S10: 10005 | T10: 10005 | U10: null | V10: null | W10: null | X10: null | Y10: null | Z10: null | AA10: null | AB10: Нет | AC10: https://crm.example.com/deal/57242 | AD10: 2025 | AE10: Проект | AF10: Новикова А.В.
A11: 57241 | B11: РБС Групп (двери) | C11: 104 | D11: 45734.344 | E11: Активные продажи | F11: Технический | G11: Строительство | H11: Выставление счета | I11: 45747 | J11: РБС Групп | K11: Алексеева М.И. | L11: Строительство | M11: 45734.344 | N11: 45734.347 | O11: Подтвержден | P11: Сидоров В.В. | Q11: 500000 | R11: 500000 | S11: 10006 | T11: 10006 | U11: null | V11: null | W11: null | X11: 500000 | Y11: null | Z11: 500000 | AA11: 5 | AB11: Не просрочена | AC11: https://crm.example.com/deal/57241 | AD11: 2025 | AE11: Проект | AF11: Сидоров В.В.
A12: 57240 | B12: Спа-центр "Коприно" | C12: 110 | D12: 45734.333 | E12: Активные продажи | F12: Лидогенерация | G12: Строительство | H12: Проверка объекта | I12: 45870 | J12: СтройКомплект | K12: Сергеева Н.В. | L12: Строительство | M12: 45734.333 | N12: 45734.396 | O12: OK | P12: Алексеева М.И. | Q12: 2000000 | R12: 2000000 | S12: 10007 | T12: 10007 | U12: null | V12: null | W12: null | X12: null | Y12: null | Z12: null | AA12: null | AB12: Нет | AC12: https://crm.example.com/deal/57240 | AD12: 2025 | AE12: Проект | AF12: Алексеева М.И.
A13: 57239 | B13: Стандартные отгрузки "Веста-Краснодар" | C13: 113 | D13: 45734.333 | E13: Активные продажи | F13: Технический | G13: Строительство | H13: Запуск в производство | I13: 45747 | J13: Веста-Краснодар | K13: Сергеева Н.В. | L13: Строительство | M13: 45734.5 | N13: 45734.333 | O13: В производстве | P13: Горин А.Н. | Q13: 50000 | R13: 50000 | S13: 10008 | T13: 10008 | U13: null | V13: null | W13: null | X13: 50000 | Y13: null | Z13: 40000 | AA13: 15 | AB13: Не просрочена | AC13: https://crm.example.com/deal/57239 | AD13: 2025 | AE13: Стандарт | AF13: Горин А.Н.
A14: 57238 | B14: Рентгенозащитные двери | C14: 110 | D14: 45734.323 | E14: Активные продажи | F14: Технический | G14: Строительство | H14: Запуск в производство | I14: 45747 | J14: СтройДизайн | K14: Алексеева М.И. | L14: Строительство | M14: 45734.5 | N14: 45734.326 | O14: В производстве | P14: Алексеева М.И. | Q14: 150000 | R14: 150000 | S14: 10009 | T14: 10009 | U14: null | V14: null | W14: null | X14: 150000 | Y14: null | Z14: null | AA14: 15 | AB14: Не просрочена | AC14: https://crm.example.com/deal/57238 | AD14: 2025 | AE14: Проект | AF14: Алексеева М.И.
A15: 57237 | B15: Откосы для КПП больниц | C15: 108 | D15: 45734.312 | E15: Активные продажи | F15: Технический | G15: Строительство | H15: Согласование отгрузки | I15: 45746 | J15: Алексвит | K15: Васильева К.А. | L15: Строительство | M15: 45734.521 | N15: 45734.319 | O15: Отгружено | P15: Васильева К.А. | Q15: 400000 | R15: 400000 | S15: 10010 | T15: 10010 | U15: null | V15: null | W15: null | X15: 400000 | Y15: null | Z15: 500000 | AA15: 5 | AB15: Не просрочена | AC15: https://crm.example.com/deal/57237 | AD15: 2025 | AE15: Проект | AF15: Васильева К.А.
A16: 57236 | B16: Центр детской онкологии, Беларусь | C16: 107 | D16: 45734.302 | E16: Активные продажи | F16: Технический | G16: Строительство СНГ | H16: Выставление счета | I16: 45807 | J16: Тисса | K16: Родина Т.В. | L16: Строительство СНГ | M16: 45734.302 | N16: 45734.312 | O16: Подтвержден | P16: Новикова А.В. | Q16: 800000 | R16: 800000 | S16: 10011 | T16: 10011 | U16: null | V16: null | W16: 800000 | X16: null | Y16: null | Z16: null | AA16: 5 | AB16: Не просрочена | AC16: https://crm.example.com/deal/57236 | AD16: 2025 | AE16: Проект | AF16: Новикова А.В.
A17: 57235 | B17: Мебель для библиотеки Орска | C17: 104 | D17: 45734.285 | E17: Активные продажи | F17: Лидогенерация | G17: Строительство | H17: Сбор информации | I17: null | J17: ЦБС Орска | K17: Козлов Д.Д. | L17: Строительство | M17: 45734.288 | N17: 45734.292 | O17: OK | P17: Сидоров В.В. | Q17: 0 | R17: 0 | S17: 10012 | T17: 10012 | U17: null | V17: null | W17: null | X17: null | Y17: null | Z17: null | AA17: 3 | AB17: Не просрочена | AC17: https://crm.example.com/deal/57235 | AD17: 2025 | AE17: Проект | AF17: Сидоров В.В.
A18: 57234 | B18: Аналитприбор, заказ 882 | C18: 106 | D18: 45733.688 | E18: Активные продажи | F18: Технический | G18: Логистика | H18: Выставление счета | I18: 45784 | J18: Аналитприбор | K18: Соколова И.М. | L18: Логистика | M18: 45734.333 | N18: 45733.688 | O18: Подтвержден | P18: Соколова И.М. | Q18: 1500000 | R18: 2000000 | S18: 10013 | T18: 10013 | U18: null | V18: null | W18: 2000000 | X18: null | Y18: null | Z18: null | AA18: 5 | AB18: Не просрочена | AC18: https://crm.example.com/deal/57234 | AD18: 2025 | AE18: Проект | AF18: Соколова И.М.
A19: 57233 | B19: ВДС, дозаказ | C19: 107 | D19: 45733.681 | E19: Активные продажи | F19: Технический | G19: Строительство СНГ | H19: Частичная оплата | I19: 45747 | J19: ТД ВДС | K19: Сергеева Н.В. | L19: Строительство СНГ | M19: 45733.681 | N19: 45733.684 | O19: Подтвержден | P19: Новикова А.В. | Q19: 100000 | R19: 110000 | S19: 10014 | T19: 10014 | U19: null | V19: null | W19: null | X19: 110000 | Y19: null | Z19: null | AA19: 3 | AB19: Не просрочена | AC19: https://crm.example.com/deal/57233 | AD19: 2025 | AE19: Проект | AF19: Новикова А.В.
A20: 57232 | B20: Лабораторная мебель для Апатит | C20: 102 | D20: 45733.677 | E20: Активные продажи | F20: Лидогенерация | G20: Строительство | H20: Сбор информации | I20: 45867 | J20: null | K20: null | L20: Строительство | M20: 45733.681 | N20: 45733.681 | O20: OK | P20: Петрова Е.В. | Q20: 0 | R20: 0 | S20: null | T20: null | U20: null | V20: null | W20: null | X20: null | Y20: null | Z20: null | AA20: 3 | AB20: Не просрочена | AC20: https://crm.example.com/deal/57232 | AD20: 2025 | AE20: Проект | AF20: Петрова Е.В.
A21: 57231 | B21: Двери/откосы для КПП (успешно) | C21: 102 | D21: 45733.667 | E21: Успешно | F21: Успешно | G21: Строительство | H21: Успешно | I21: 45777 | J21: Алексвит | K21: Васильева К.А. | L21: Строительство | M21: 45733.667 | N21: 45734.271 | O21: OK | P21: Петрова Е.В. | Q21: 80000 | R21: 80000 | S21: 10010 | T21: 10010 | U21: null | V21: null | W21: null | X21: null | Y21: 80000 | Z21: 70000 | AA21: null | AB21: Нет | AC21: https://crm.example.com/deal/57231 | AD21: 2025 | AE21: Проект | AF21: Петрова Е.В.
A22: 57230 | B22: Заявка (Офис СБЕР) | C22: 101 | D22: 45733.646 | E22: Активные продажи | F22: Квалификация | G22: Дизайн-интерьеры | H22: Формирование КП | I22: 46163 | J22: Велесстрой | K22: Ормонбеков А. | L22: Дизайн-интерьеры | M22: 45733.417 | N22: 45733.188 | O22: OK | P22: Иванов П.С. | Q22: 0 | R22: 8000000 | S22: 10015 | T22: 10015 | U22: null | V22: null | W22: null | X22: null | Y22: null | Z22: null | AA22: null | AB22: Нет | AC22: https://crm.example.com/deal/57230 | AD22: 2025 | AE22: Проект | AF22: Ормонбеков А.
A23: 57229 | B23: КПП для ГКБ Ерамишанцева (дозаказ) | C23: 102 | D23: 45733.639 | E23: Активные продажи | F23: Проектирование | G23: Строительство | H23: КП сформировано | I23: 45819 | J23: Алексвит | K23: Васильева К.А. | L23: Строительство | M23: 45734.521 | N23: 45733.417 | O23: Есть КП | P23: Петрова Е.В. | Q23: 900000 | R23: 900000 | S23: 10010 | T23: 10010 | U23: null | V23: null | W23: null | X23: null | Y23: null | Z23: 900000 | AA23: 2 | AB23: Не просрочена | AC23: https://crm.example.com/deal/57229 | AD23: 2025 | AE23: Проект | AF23: Петрова Е.В.
A24: 57228 | B24: Офис СБЕР | C24: 110 | D24: 45733.604 | E24: Активные продажи | F24: Проектирование | G24: Строительство | H24: Передан в ДИ | I24: 46163 | J24: Велесстрой | K24: Ормонбеков А. | L24: Строительство | M24: 45733.417 | N24: 45733.646 | O24: OK | P24: Алексеева М.И. | Q24: 2000000 | R24: 8000000 | S24: 10015 | T24: 10015 | U24: null | V24: null | W24: null | X24: null | Y24: null | Z24: null | AA24: null | AB24: Нет | AC24: https://crm.example.com/deal/57228 | AD24: 2025 | AE24: Проект | AF24: Алексеева М.И.
A25: 57227 | B25: Стандартные отгрузки "Премьер Групп" | C25: 101 | D25: 45733.59 | E25: Активные продажи | F25: Технический | G25: Строительство | H25: Запуск в производство | I25: 45736 | J25: Премьер Групп | K25: Сергеева Н.В. | L25: Строительство | M25: 45734.521 | N25: 45733.59 | O25: В производстве | P25: Сергеева Н.В. | Q25: 80000 | R25: 80000 | S25: 10016 | T25: 10016 | U25: null | V25: null | W25: null | X25: 80000 | Y25: null | Z25: null | AA25: 15 | AB25: Не просрочена | AC25: https://crm.example.com/deal/57227 | AD25: 2025 | AE25: Стандарт | AF25: Сергеева Н.В.
A26: 57226 | B26: Мебель для вагона 4460 | C26: 114 | D26: 45733.583 | E26: Активные продажи | F26: Квалификация | G26: Транспорт | H26: Передан в КТО | I26: 45799 | J26: КСК МК | K26: Соколова И.М. | L26: Транспорт | M26: 45734.499 | N26: 45733.583 | O26: OK | P26: Попкова А.С. | Q26: 0 | R26: 0 | S26: 10017 | T26: 10017 | U26: null | V26: null | W26: null | X26: null | Y26: null | Z26: null | AA26: null | AB26: Нет | AC26: https://crm.example.com/deal/57226 | AD26: 2025 | AE26: Проект | AF26: Соколова И.М.
A27: 57225 | B27: Столешницы (ЛитТрансСервис) | C27: 114 | D27: 45733.58 | E27: Активные продажи | F27: Квалификация | G27: Отгрузка в кредит | H27: Ожидание оплаты | I27: 45747 | J27: ЛитТрансСервис | K27: Орлова Т.В. | L27: Отгрузка в кредит | M27: 45733.58 | N27: 45734.607 | O27: OK | P27: Попкова А.С. | Q27: 0 | R27: 50000 | S27: 10018 | T27: 10018 | U27: null | V27: null | W27: null | X27: null | Y27: null | Z27: null | AA27: null | AB27: Нет | AC27: https://crm.example.com/deal/57225 | AD27: 2025 | AE27: Проект | AF27: Орлова Т.В.
A28: 57224 | B28: Панели (Тверской экспресс) | C28: 114 | D28: 45733.576 | E28: Активные продажи | F28: Технический | G28: Транспорт | H28: Запуск в производство | I28: 45747 | J28: КСК МК | K28: Соколова И.М. | L28: Транспорт | M28: 45734.499 | N28: 45733.578 | O28: В производстве | P28: Попкова А.С. | Q28: 1200000 | R28: 1200000 | S28: 10017 | T28: 10017 | U28: null | V28: null | W28: null | X28: null | Y28: null | Z28: null | AA28: null | AB28: Нет | AC28: https://crm.example.com/deal/57224 | AD28: 2025 | AE28: Проект | AF28: Соколова И.М.
A29: 57223 | B29: КСК МК (столешницы из наличия) | C29: 114 | D29: 45733.573 | E29: Активные продажи | F29: Квалификация | G29: Отгрузка в кредит | H29: Ожидание оплаты | I29: 45722 | J29: КСК МК | K29: Соколова И.М. | L29: Отгрузка в кредит | M29: 45734.499 | N29: 45733.573 | O29: OK | P29: Попкова А.С. | Q29: 0 | R29: 80000 | S29: 10017 | T29: 10017 | U29: null | V29: null | W29: null | X29: null | Y29: null | Z29: null | AA29: null | AB29: Нет | AC29: https://crm.example.com/deal/57223 | AD29: 2025 | AE29: Проект | AF29: Соколова И.М.

Sheet b_uts_crm_deal
A1: VALUE_ID | C1: UF_CRM_1770214651 | D1: Прогноз продаж март 2026 | E1: Прогноз продаж апрель 2026 | F1: НомерЗК | G1: № ЗК | H1: № КП | I1: doc_OrderSales (в производстве для сделок).Сумма | J1: doc_OrderSales (в производстве для сделок).Ожидаемая дата производства | K1: doc_Sales (отгружено для сделок).Сумма | L1: doc_Sales (отгружено для сделок).Дата отгрузки | M1: doc_Comm_offer (для сделок).Сумма КП
A2: 57250 | B2: =VLOOKUP(A2,b_crm_deal!A:M,2,0) -> Жилой комплекс "Курский" | C2: Жилой комплекс "Курский" | D2: null | E2: null | F2: null | G2: null | H2: null | I2: null | J2: null | K2: null | L2: null | M2: null
A3: 57249 | B3: =VLOOKUP(A3,b_crm_deal!A:M,2,0) -> Сибур, Анапа (дозаказ) | C3: Сибур, Анапа (дозаказ) | D3: null | E3: null | F3: null | G3: ЗСУП-000768 | H3: ЗСУП-000768 | I3: null | J3: 1250000 | K3: 45785 | L3: null | M3: null | N3: null
A4: 57248 | B4: =VLOOKUP(A4,b_crm_deal!A:M,2,0) -> Артек (дозаказ) | C4: Артек (дозаказ) | D4: null | E4: null | F4: null | G4: ЗСУП-000715 | H4: ЗСУП-000707 | I4: null | J4: 900000 | K4: 45787 | L4: null | M4: null | N4: null
A5: 57248 | B5: =VLOOKUP(A5,b_crm_deal!A:M,2,0) -> Артек (дозаказ) | C5: Артек (дозаказ) | D5: null | E5: null | F5: null | G5: ЗСУП-000770 | H5: ЗСУП-000707 | I5: null | J5: 450000 | K5: 45789 | L5: null | M5: null | N5: null
A6: 57248 | B6: =VLOOKUP(A6,b_crm_deal!A:M,2,0) -> Артек (дозаказ) | C6: Артек (дозаказ) | D6: null | E6: null | F6: null | G6: ЗСУП-000716 | H6: ЗСУП-000707 | I6: null | J6: 140000 | K6: 45789 | L6: null | M6: null | N6: null
A7: 57248 | B7: =VLOOKUP(A7,b_crm_deal!A:M,2,0) -> Артек (дозаказ) | C7: Артек (дозаказ) | D7: null | E7: null | F7: null | G7: ЗСУП-000707 | H7: ЗСУП-000707 | I7: null | J7: 45000 | K7: 45787 | L7: null | M7: null | N7: null
A8: 57247 | B8: =VLOOKUP(A8,b_crm_deal!A:M,2,0) -> Сибур, Анапа (двери) | C8: Сибур, Анапа (двери) | D8: null | E8: null | F8: null | G8: ЗСУП-000851 | H8: ЗСУП-000851 | I8: null | J8: 1300000 | K8: 45792 | L8: null | M8: null | N8: null
A9: 57246 | B9: =VLOOKUP(A9,b_crm_deal!A:M,2,0) -> Стандартные отгрузки "РесторанСервис" | C9: Стандартные отгрузки "РесторанСервис" | D9: null | E9: null | F9: null | G9: ЗСУП-000936 | H9: null | I9: 90000 | J9: null | K9: null | L9: null | M9: null | N9: null
A10: 57245 | B10: =VLOOKUP(A10,b_crm_deal!A:M,2,0) -> HPL панели, г. Москва | C10: HPL панели, г. Москва | D10: null | E10: null | F10: null | G10: ЗСУП-000918 | H10: null | I10: null | J10: null | K10: null | L10: null | M10: null | N10: null
A11: 57244 | B11: =VLOOKUP(A11,b_crm_deal!A:M,2,0) -> Бизнес-центр "Вперед" | C11: Бизнес-центр "Вперед" | D11: null | E11: null | F11: null | G11: null | H11: null | I11: null | J11: null | K11: null | L11: null | M11: null | N11: null
A12: 57243 | B12: =VLOOKUP(A12,b_crm_deal!A:M,2,0) -> Входящий звонок (дилер) | C12: Входящий звонок (дилер) | D12: null | E12: null | F12: null | G12: null | H12: null | I12: null | J12: null | K12: null | L12: null | M12: null | N12: null
A13: 57242 | B13: =VLOOKUP(A13,b_crm_deal!A:M,2,0) -> Частный дом, Казахстан | C13: Частный дом, Казахстан | D13: null | E13: null | F13: null | G13: null | H13: null | I13: null | J13: null | K13: null | L13: null | M13: null | N13: null
A14: 57241 | B14: =VLOOKUP(A14,b_crm_deal!A:M,2,0) -> РБС Групп (двери) | C14: РБС Групп (двери) | D14: null | E14: null | F14: null | G14: null | H14: null | I14: null | J14: 500000 | K14: 45794 | L14: null | M14: null | N14: 500000
A15: 57240 | B15: =VLOOKUP(A15,b_crm_deal!A:M,2,0) -> Спа-центр "Коприно" | C15: Спа-центр "Коприно" | D15: null | E15: null | F15: null | G15: ЗСУП-000869 | H15: ЗСУП-000664 | I15: null | J15: null | K15: null | L15: null | M15: null | N15: null
A16: 57239 | B16: =VLOOKUP(A16,b_crm_deal!A:M,2,0) -> Стандартные отгрузки "Веста-Краснодар" | C16: Стандартные отгрузки "Веста-Краснодар" | D16: null | E16: null | F16: null | G16: null | H16: null | I16: null | J16: 50000 | K16: 45792 | L16: null | M16: null | N16: 40000
A17: 57238 | B17: =VLOOKUP(A17,b_crm_deal!A:M,2,0) -> Рентгенозащитные двери | C17: Рентгенозащитные двери | D17: null | E17: null | F17: null | G17: ЗСУП-000824 | H17: ЗСУП-000263 | I17: null | J17: 150000 | K17: 45792 | L17: null | M17: null | N17: null
A18: 57237 | B18: =VLOOKUP(A18,b_crm_deal!A:M,2,0) -> Откосы для КПП больниц | C18: Откосы для КПП больниц | D18: null | E18: null | F18: null | G18: ЗСУП-000812 | H18: ЗСУП-00 | I18: null | J18: 400000 | K18: 45788 | L18: null | M18: null | N18: 500000
A19: 57236 | B19: =VLOOKUP(A19,b_crm_deal!A:M,2,0) -> Центр детской онкологии, Беларусь | C19: Центр детской онкологии, Беларусь | D19: null | E19: null | F19: null | G19: ЗСУП-000564 | H19: ЗСУП-000410 | I19: null | J19: null | K19: null | L19: null | M19: null | N19: null
A20: 57235 | B20: =VLOOKUP(A20,b_crm_deal!A:M,2,0) -> Мебель для библиотеки Орска | C20: Мебель для библиотеки Орска | D20: null | E20: null | F20: null | G20: ЗСУП-000911 | H20: ЗСУП-000660 | I20: null | J20: null | K20: null | L20: null | M20: null | N20: null
A21: 57234 | B21: =VLOOKUP(A21,b_crm_deal!A:M,2,0) -> Аналитприбор, заказ 882 | C21: Аналитприбор, заказ 882 | D21: null | E21: null | F21: null | G21: null | H21: null | I21: 2000000 | J21: null | K21: null | L21: null | M21: null | N21: null
A22: 57233 | B22: =VLOOKUP(A22,b_crm_deal!A:M,2,0) -> ВДС, дозаказ | C22: ВДС, дозаказ | D22: null | E22: null | F22: null | G22: ЗСУП-000882 | H22: null | I22: null | J22: 110000 | K22: 45745 | L22: null | M22: null | N22: null
A23: 57232 | B23: =VLOOKUP(A23,b_crm_deal!A:M,2,0) -> Лабораторная мебель для Апатит | C23: Лабораторная мебель для Апатит | D23: null | E23: null | F23: null | G23: ЗСУП-000249 | H23: ЗСУП-000657 | I23: null | J23: null | K23: null | L23: null | M23: null | N23: null
A24: 57231 | B24: =VLOOKUP(A24,b_crm_deal!A:M,2,0) -> Двери/откосы для КПП (успешно) | C24: Двери/откосы для КПП (успешно) | D24: null | E24: null | F24: null | G24: null | H24: null | I24: null | J24: null | K24: null | L24: 80000 | M24: 45734.417 | N24: 70000
A25: 57230 | B25: =VLOOKUP(A25,b_crm_deal!A:M,2,0) -> Заявка (Офис СБЕР) | C25: Заявка (Офис СБЕР) | D25: null | E25: null | F25: null | G25: ЗСУП-000523 | H25: ЗСУП-000355 | I25: null | J25: null | K25: null | L25: null | M25: null | N25: null
A26: 57229 | B26: =VLOOKUP(A26,b_crm_deal!A:M,2,0) -> КПП для ГКБ Ерамишанцева (дозаказ) | C26: КПП для ГКБ Ерамишанцева (дозаказ) | D26: null | E26: null | F26: null | G26: null | H26: null | I26: null | J26: null | K26: null | L26: null | M26: null | N26: 900000
A27: 57228 | B27: =VLOOKUP(A27,b_crm_deal!A:M,2,0) -> Офис СБЕР | C27: Офис СБЕР | D27: null | E27: null | F27: null | I27: null | J27: null | K27: null | L27: null | M27: null | N27: null
A28: 57227 | B28: =VLOOKUP(A28,b_crm_deal!A:M,2,0) -> Стандартные отгрузки "Премьер Групп" | C28: Стандартные отгрузки "Премьер Групп" | D28: null | E28: null | F28: null | G28: null | H28: ЗСУП-000649 | I28: null | J28: 80000 | K28: 45756 | L28: null | M28: null | N28: null
A29: 57226 | B29: =VLOOKUP(A29,b_crm_deal!A:M,2,0) -> Мебель для вагона 4460 | C29: Мебель для вагона 4460 | D29: null | E29: null | F29: null | G29: null | H29: null | I29: null | J29: null | K29: null | L29: null | M29: null | N29: null
A30: 57225 | B30: =VLOOKUP(A30,b_crm_deal!A:M,2,0) -> Столешницы (ЛитТрансСервис) | C30: Столешницы (ЛитТрансСервис) | D30: null | E30: null | F30: null | I30: null | J30: null | K30: null | L30: null | M30: null | N30: null
A31: 57224 | B31: =VLOOKUP(A31,b_crm_deal!A:M,2,0) -> Панели (Тверской экспресс) | C31: Панели (Тверской экспресс) | D31: null | E31: null | F31: null | G31: ЗСУП-000609 | H31: null | I31: null | J31: null | K31: null | L31: null | M31: null | N31: null
A32: 57223 | B32: =VLOOKUP(A32,b_crm_deal!A:M,2,0) -> КСК МК (столешницы из наличия) | C32: КСК МК (столешницы из наличия) | D32: null | E32: null | F32: null | G32: null | H32: null | I32: null | J32: null | K32: null | L32: null | M32: null | N32: null

Sheet doc_OrderSales
A1: id_1c | B1: Name | C1: Number | D1: NumberExt | E1: Date | F1: Posted | G1: IsDelete | H1: vid_oper | I1: Priority | J1: organisation_id_1с | K1: status | L1: phersons_id_1с | M1: phersons_name | N1: author_id_1c | O1: author_name | P1: Partner_id | Q1: contractor_id_1с | R1: agreement_id_1с | S1: covenant_id_1c | T1: department_id_1с | U1: condition | V1: Nomenclature_id_1с | W1: UnitStore | X1: UnitReport | Y1: store_id_1с | Z1: store_name | AA1: Quantity | AB1: Amount | AC1: QuantityUnitReport | AD1: QuantityWeight | AE1: VidNomenclature | AF1: Date_shipment | AG1: SecurityOption | AH1: pos_cancelled | AI1: Price_plan | AJ1: Amount_plan | AK1: Price_Dop | AL1: percent_Action | AM1: Amount_Action | AN1: percent_Dop | AO1: vid_price | AP1: Price | AQ1: direction | AR1: Ref_1C | AS1: reason_cancelled | AT1: id_1c_doc_Comm_offer | AU1: spr_nomenclature.Name | AV1: spr_nomenclature.Группы ном | AW1: Копия Date | AX1: Сведение
A2: f38645b5-1d2d-11f1-99bb-00155dde6a00 | B2: Заказ клиента ЗСУП-000768 от 06.03.2026 14:49:05 | C2: ЗСУП-000768 | D2: ЗСУП-000768_2026 | E2: 46087.617 | F2: 0 | G2: 0 | H2: Реализация | I2: Средний | J2: 9e38a44e-b7d0-11e7-a547-f6d178db6df1 | K2: На согласовании | L2: 05f2ed7a-4034-11ef-8110-00155d000d00 | M2: Сорокина Инга Викторовна | N2: 7ada799d-7cef-11f0-a009-00155d81c805 | O2: Ипатова Анна Юрьевна | P2: 0b990115-2b95-11e9-ab3f-0cc47af964e9 | Q2: bed902e8-43aa-11ec-ab50-0cc47af964e9 | R2: 44587403-d89a-11ef-ab69-0cc47af964e9 | S2: 54206bf8-fefd-11ea-ab46-0cc47af964e9 | T2: 55c87efc-b566-11e7-a547-f6d178db6df1 | U2: Ожидается согласование | V2: 1030044b-4135-11f0-ab6b-0cc47af964e9 | W2: лист | X2: м2 | Y2: fa6fadf3-b578-11e7-a547-f6d178db6df1 | Z2: Склад упаковки готовой продукции (ЗСП) | AA2: 2 | AB2: 50 790,00 | AC2: 8.065 | AD2: 70.536 | AE2: Слопласт | AF2: null | AG2: К обеспечению | AH2: 0 | AI2: 10 920,05 | AJ2: 21 840,10 | AK2: 0 | AL2: 0 | AM2: 0 | AN2: 0 | AP2: 25 395,00 | AQ2: Стройка | AR2: e1cib/data/Документ.ЗаказКлиента?ref=99bb00155dde6a0011f11d2df38645b5 | AT2: 00000000-0000-0000-0000-000000000000 | AU2: Слопласт ТГ (/1320 х 3050 х 8,0/2/BITM/МТ//9736/9736//Н) | AV2: узкий/BITM/ТГ/МТ/(8.0) | AW2: 2025 | AX2: ЗСУП-003412_2 025
A3: 80941762-16e0-11f1-99b9-00155dde6a00 | B3: Заказ клиента ЗСУП-000715 от 03.03.2026 11:36:22 | C3: ЗСУП-000715 | D3: ЗСУП-000715_2026 | E3: 46084.483 | F3: 1 | G3: 0 | H3: Реализация | I3: Средний | J3: 9e38a44e-b7d0-11e7-a547-f6d178db6df1 | K3: К выполнению / В резерве | L3: 2a671c75-1d9b-11e2-a65b-0015171241a4 | M3: Макаренко Мария Борисовна | N3: d51dce26-0c67-11ef-810e-00155d000d00 | O3: Лебедева Елена Николаевна | P3: 0b990115-2b95-11e9-ab3f-0cc47af964e9 | Q3: bed902e8-43aa-11ec-ab50-0cc47af964e9 | R3: 00000000-0000-0000-0000-000000000000 | S3: 54206bf8-fefd-11ea-ab46-0cc47af964e9 | T3: 55c87efc-b566-11e7-a547-f6d178db6df1 | U3: Ожидается обеспечение | V3: 1030044b-4135-11f0-ab6b-0cc47af964e9 | W3: лист | X3: м2 | Y3: f027a6ed-b812-11e7-a547-f6d178db6df1 | Z3: Склад МО (Мытищи) | AA3: 6 | AB3: 188 988,00 | AC3: 24.194 | AD3: 211.608 | AE3: Слопласт | AF3: null | AG3: К обеспечению | AH3: 0 | AI3: 19 875,29 | AJ3: 119 251,74 | AK3: 0 | AL3: 0 | AM3: 0 | AN3: 0 | AP3: 31 498,00 | AQ3: Стройка | AR3: e1cib/data/Документ.ЗаказКлиента?ref=99b900155dde6a0011f116e080941762 | AT3: 00000000-0000-0000-0000-000000000000 | AU3: Слопласт Ф (/1320 х 3050 х 10,0/2/BITM/МТ/УФ/2754/1113Т//Н) | AV3: узкий/BITM/Ф/МТ/(9.0-11.0) | AW3: 2025 | AX3: ЗСУП-003776_2 025
A4: 653048a2-1955-11f1-99bb-00155dde6a00 | B4: Заказ клиента ЗСУП-000770 от 06.03.2026 15:00:47 | C4: ЗСУП-000770 | D4: ЗСУП-000770_2026 | E4: 46087.625 | F4: 1 | G4: 0 | H4: Реализация | I4: Средний | J4: 9e38a44e-b7d0-11e7-a547-f6d178db6df1 | K4: К выполнению / В резерве | L4: 05f2ed7a-4034-11ef-8110-00155d000d00 | M4: Сорокина Инга Викторовна | N4: 7ada799d-7cef-11f0-a009-00155d81c805 | O4: Ипатова Анна Юрьевна | P4: 0b990115-2b95-11e9-ab3f-0cc47af964e9 | Q4: bed902e8-43aa-11ec-ab50-0cc47af964e9 | R4: 3cd61b03-e097-11f0-99b9-00155dde6a00 | S4: 54206bf8-fefd-11ea-ab46-0cc47af964e9 | T4: 55c87efc-b566-11e7-a547-f6d178db6df1 | U4: Ожидается обеспечение | V4: 1030044b-4135-11f0-ab6b-0cc47af964e9 | W4: лист | X4: м2 | Y4: fa6fadf3-b578-11e7-a547-f6d178db6df1 | Z4: Склад упаковки готовой продукции (ЗСП) | AA4: 6 | AB4: 152 370,00 | AC4: 24.194 | AD4: 211.608 | AE4: Слопласт | AF4: null | AG4: К обеспечению | AH4: 0 | AI4: 16 866,75 | AJ4: 101 200,50 | AK4: 0 | AL4: 0 | AM4: 0 | AN4: 0 | AP4: 25 395,00 | AQ4: Стройка | AR4: e1cib/data/Документ.ЗаказКлиента?ref=99bb00155dde6a0011f11955653048a2 | AT4: 00000000-0000-0000-0000-000000000000 | AU4: Слопласт ТГ (/1320 х 3050 х 8,0/2/BITM/МТ//9736/9736//Н) | AV4: узкий/BITM/ТГ/МТ/(8.0) | AW4: 2026 | AX4: ЗСУП-000370_2 026
A5: bbe8240f-16e1-11f1-99b9-00155dde6a00 | B5: Заказ клиента ЗСУП-000716 от 03.03.2026 12:17:01 | C5: ЗСУП-000716 | D5: ЗСУП-000716_2026 | E5: 46084.512 | F5: 1 | G5: 0 | H5: Реализация | I5: Средний | J5: 9e38a44e-b7d0-11e7-a547-f6d178db6df1 | K5: К выполнению / В резерве | L5: 8870b4a7-f73b-11e6-80de-00155d000d00 | M5: Козлова Мария Николаевна | N5: c2b02347-0c63-11ef-ab64-0cc47af964e9 | O5: Касимова Карина Ринатовна | P5: c64f81c5-f924-11ed-ab5f-0cc47af964e9 | Q5: c64f81fe-f924-11ed-ab5f-0cc47af964e9 | R5: 5538e8d6-e24e-11f0-99b9-00155dde6a00 | S5: 54206bf8-fefd-11ea-ab46-0cc47af964e9 | T5: 55c87efc-b566-11e7-a547-f6d178db6df1 | U5: Ожидается обеспечение | V5: 05f12735-b32c-11eb-ab4d-0cc47af964e9 | W5: лист | X5: м2 | Y5: fa6fadf3-b578-11e7-a547-f6d178db6df1 | Z5: Склад упаковки готовой продукции (ЗСП) | AA5: 1 | AB5: 12 700,80 | AC5: 4.032 | AD5: 23.512 | AE5: Слопласт | AF5: null | AG5: К обеспечению | AH5: 0 | AI5: 8 059,24 | AJ5: 8 059,24 | AK5: 0 | AL5: 0 | AM5: 0 | AN5: 0 | AP5: 12 700,80 | AQ5: Стройка | AR5: e1cib/data/Документ.ЗаказКлиента?ref=99b900155dde6a0011f116e1bbe8240f | AT5: 00000000-0000-0000-0000-000000000000 | AU5: Слопласт ТГ (12/1320 х 3050 х 4,0/2/BITM/МТ//847/847//Н) | AV5: узкий/BITM/ТГ/МТ/(4.0) | AW5: 2026 | AX5: ЗСУП-000643_2 026
A6: b418c3b9-1636-11f1-99b9-00155dde6a00 | B6: Заказ клиента ЗСУП-000707 от 02.03.2026 15:52:50 | C6: ЗСУП-000707 | D6: ЗСУП-000707_2026 | E6: 46083.661 | F6: 1 | G6: 0 | H6: Реализация | I6: Средний | J6: 9e38a44e-b7d0-11e7-a547-f6d178db6df1 | K6: К выполнению / В резерве | L6: 2a671c75-1d9b-11e2-a65b-0015171241a4 | M6: Макаренко Мария Борисовна | N6: c2b02347-0c63-11ef-ab64-0cc47af964e9 | O6: Касимова Карина Ринатовна | P6: c64f81c5-f924-11ed-ab5f-0cc47af964e9 | Q6: c64f81fe-f924-11ed-ab5f-0cc47af964e9 | R6: 320acb99-1637-11f1-99b9-00155dde6a00 | S6: 258beace-a26f-11eb-ab4c-0cc47af964e9 | T6: 55c87efc-b566-11e7-a547-f6d178db6df1 | U6: Ожидается обеспечение | V6: 1033fcfb-f348-11ef-ab6a-0cc47af964e9 | W6: лист | X6: м2 | Y6: fa6fadf3-b578-11e7-a547-f6d178db6df1 | Z6: Склад упаковки готовой продукции (ЗСП) | AA6: 60 | AB6: 209 349,60 | AC6: 241.935 | AD6: 282.12 | AE6: Слопласт | AF6: null | AG6: К обеспечению | AH6: 0 | AI6: 1 621,21 | AJ6: 97 272,60 | AK6: 0 | AL6: 0 | AM6: 0 | AN6: 0 | AP6: 3 489,16 | AQ6: Стройка | AR6: e1cib/data/Документ.ЗаказКлиента?ref=99b900155dde6a0011f11636b418c3b9 | AT6: 00000000-0000-0000-0000-000000000000 | AU6: Слопласт ТГ (/1320 х 3050 х 0,8/1/BITM/СД//9733//Ш) | AV6: узкий/BITM/ТГ/СД/(0.5-1.0) | AW6: 2026 | AX6: ЗСУП-000270_2 026
A7: c236b5ca-1e1d-11f1-99bb-00155dde6a00 | B7: Заказ клиента ЗСУП-000851 от 12.03.2026 17:08:18 | C7: ЗСУП-000851 | D7: ЗСУП-000851_2026 | E7: 46093.714 | F7: 1 | G7: 0 | H7: Реализация | I7: Средний | J7: 9e38a44e-b7d0-11e7-a547-f6d178db6df1 | K7: К выполнению / В резерве | L7: 59599dd2-c972-11ed-8109-00155d000d00 | M7: Стальберг Елена Александровна | N7: 59599dd2-c972-11ed-8109-00155d000d00 | O7: Стальберг Елена Александровна | P7: 1b556bc5-f368-11e8-9fe3-d000e1470f5d | Q7: 1b556bc6-f368-11e8-9fe3-d000e1470f5d | R7: 3081c846-2107-11f1-99bb-00155dde6a00 | S7: c42f193e-01ce-11e9-ab3f-0cc47af964e9 | T7: 55c87efc-b566-11e7-a547-f6d178db6df1 | U7: Ожидается обеспечение | V7: 03ed5797-640e-11e8-ab3e-0cc47af964e9 | W7: лист | X7: м2 | Y7: fa6fadf3-b578-11e7-a547-f6d178db6df1 | Z7: Склад упаковки готовой продукции (ЗСП) | AA7: 4 | AB7: 204 224,00 | AC7: 19.139 | AD7: 391.508 | AE7: Слопласт | AF7: null | AG7: К обеспечению | AH7: 0 | AI7: 33 164,09 | AJ7: 132 656,36 | AK7: 0 | AL7: 0 | AM7: 0 | AN7: 0 | AO7: С2 | AP7: 51 056,00 | AQ7: Транспорт | AR7: e1cib/data/Документ.ЗаказКлиента?ref=99bb00155dde6a0011f11e1dc236b5ca | AT7: 00000000-0000-0000-0000-000000000000 | AU7: Слопласт ТГ (/1570 х 3050 х 14,0/2/BITM/Т//2762/2762//Н) | AV7: широкий/BITM/ТГ/Т/(13.0-25.0) | AW7: 2025 | AX7: ЗСУП-001865_2 025
A8: c6d95ff4-2269-11f1-99bb-00155dde6a00 | B8: Заказ клиента ЗСУП-000936 от 18.03.2026 17:46:46 | C8: ЗСУП-000936 | D8: ЗСУП-000936_2026 | E8: 46099.74 | F8: 0 | G8: 0 | H8: Реализация | I8: Средний | J8: 9e38a44e-b7d0-11e7-a547-f6d178db6df1 | K8: На согласовании | L8: 59599dd2-c972-11ed-8109-00155d000d00 | M8: Стальберг Елена Александровна | N8: 7fc9daa0-066f-11f1-a014-00155d81c802 | O8: Кулагина Анна Александровна | P8: 1b556bc5-f368-11e8-9fe3-d000e1470f5d | Q8: 1b556bc6-f368-11e8-9fe3-d000e1470f5d | R8: 3081c846-2107-11f1-99bb-00155dde6a00 | S8: c42f193e-01ce-11e9-ab3f-0cc47af964e9 | T8: 55c87efc-b566-11e7-a547-f6d178db6df1 | V8: 03ed5797-640e-11e8-ab3e-0cc47af964e9 | W8: лист | X8: м2 | Y8: fa6fadf3-b578-11e7-a547-f6d178db6df1 | Z8: Склад упаковки готовой продукции (ЗСП) | AA8: 8 | AB8: 417 600,00 | AC8: 38.278 | AD8: 783.016 | AE8: Слопласт | AF8: null | AG8: К обеспечению | AH8: 0 | AI8: 31 988,29 | AJ8: 255 906,32 | AK8: 0 | AL8: 0 | AM8: 0 | AN8: 0 | AO8: С2 | AP8: 52 200,00 | AQ8: Транспорт | AR8: e1cib/data/Документ.ЗаказКлиента?ref=99bb00155dde6a0011f12269c6d95ff4 | AT8: 00000000-0000-0000-0000-000000000000 | AU8: Слопласт ТГ (/1570 х 3050 х 14,0/2/BITM/Т//2762/2762//Н) | AV8: широкий/BITM/ТГ/Т/(13.0-25.0) | AW8: 2025 | AX8: ЗСУП-003811_2 025
A9: d0bbdb8d-1fe5-11f1-99bb-00155dde6a00 | B9: Заказ клиента ЗСУП-000918 от 15.03.2026 17:49:55 | C9: ЗСУП-000918 | D9: ЗСУП-000918_2026 | E9: 46096.742 | F9: 0 | G9: 0 | H9: Реализация | I9: Средний | J9: 9e38a44e-b7d0-11e7-a547-f6d178db6df1 | K9: На согласовании | L9: 59599dd2-c972-11ed-8109-00155d000d00 | M9: Стальберг Елена Александровна | N9: 7fc9daa0-066f-11f1-a014-00155d81c802 | O9: Кулагина Анна Александровна | P9: 7a9e79e3-22c5-11ed-ab55-0cc47af964e9 | Q9: dbbed476-bb09-11ec-ab50-0cc47af964e9 | R9: d532e74f-22e8-11ed-ab55-0cc47af964e9 | S9: d4764638-87cb-11f0-99b7-00155dde6a00 | T9: 609d494f-b566-11e7-a547-f6d178db6df1 | V9: 1862f4f7-8a28-11f0-99b7-00155dde6a00 | W9: лист | X9: м2 | Y9: fa6fadf3-b578-11e7-a547-f6d178db6df1 | Z9: Склад упаковки готовой продукции (ЗСП) | AA9: 3 | AB9: 23 523,00 | AC9: 14.354 | AD9: 62.922 | AE9: Слопласт | AF9: null | AG9: К обеспечению | AH9: 0 | AI9: 5 840,75 | AJ9: 17 522,25 | AK9: 0 | AL9: 0 | AM9: 0 | AN9: 0 | AP9: 7 841,00 | AQ9: Транспорт | AR9: e1cib/data/Документ.ЗаказКлиента?ref=99bb00155dde6a0011f11fe5d0bbdb8d | AT9: 00000000-0000-0000-0000-000000000000 | AU9: Слопласт ТГ (/1570 х 3050 х 3,0/1/BITM/Т//688//Ш) | AV9: широкий/BITM/ТГ/Т/(2.5-3.0) | AW9: 2025 | AX9: ЗСУП-004450_2 025
A10: 3a7e6a32-1f4f-11f1-99bb-00155dde6a00 | B10: Заказ клиента ЗСУП-000869 от 15.03.2026 11:47:47 | C10: ЗСУП-000869 | D10: ЗСУП-000869_2026 | E10: 46096.491 | F10: 0 | G10: 0 | H10: Реализация | I10: Средний | J10: 9e38a44e-b7d0-11e7-a547-f6d178db6df1 | K10: На согласовании | L10: 05f2ed7a-4034-11ef-8110-00155d000d00 | M10: Сорокина Инга Викторовна | N10: 7ada799d-7cef-11f0-a009-00155d81c805 | O10: Ипатова Анна Юрьевна | P10: 3fa69b08-b7a5-11e2-ae63-0015171241a4 | Q10: 35ad1025-f36b-11e8-9fe3-d000e1470f5d | R10: f8e09145-5001-11ef-ab64-0cc47af964e9 | S10: 52094fa9-769a-11eb-ab4c-0cc47af964e9 | T10: 55c87efc-b566-11e7-a547-f6d178db6df1 | V10: 037f533d-013b-11ef-ab64-0cc47af964e9 | W10: лист | X10: м2 | Y10: fa6fadf3-b578-11e7-a547-f6d178db6df1 | Z10: Склад упаковки готовой продукции (ЗСП) | AA10: 600 | AB10: 759 600,00 | AC10: 2419.355 | AD10: 1763.4 | AE10: Слопласт | AF10: null | AG10: К обеспечению | AH10: 0 | AI10: 1 025,10 | AJ10: 615 060,00 | AK10: 0 | AL10: 0 | AM10: 0 | AN10: 0 | AP10: 1 266,00 | AQ10: Мебель | AR10: e1cib/data/Документ.ЗаказКлиента?ref=99bb00155dde6a0011f11f4f3a7e6a32 | AT10: 00000000-0000-0000-0000-000000000000 | AU10: Слопласт П (/1320 х 3050 х 0,5/BIPA/Г//711//Ш) | AV10: узкий/BIPA/П/Г/(0.5-1.0) | AW10: 2025 | AX10: ЗСУП-001729_2 025
A11: 14fdc30b-1d31-11f1-99bb-00155dde6a00 | B11: Заказ клиента ЗСУП-000824 от 11.03.2026 14:30:03 | C11: ЗСУП-000824 | D11: ЗСУП-000824_2026 | E11: 46092.604 | F11: 1 | G11: 0 | H11: Реализация | I11: Средний | J11: 9e38a44e-b7d0-11e7-a547-f6d178db6df1 | K11: К выполнению / В резерве | L11: 01d4de8c-6aaf-11ef-8110-00155d000d00 | M11: Рожкова Софья Алексеевна | N11: deb389e3-b3c8-11ef-8111-00155d000d00 | O11: Троицкая Мария Николаевна | P11: 31844b91-355e-11de-8227-0015171241a4 | Q11: 107108ee-f367-11e8-9fe3-d000e1470f5d | R11: 09095034-f078-11f0-99b9-00155dde6a00 | S11: 2f3364f4-226a-11ea-ab44-0cc47af964e9 | T11: 609d494f-b566-11e7-a547-f6d178db6df1 | U11: Ожидается обеспечение | V11: 194970a4-6577-11ed-ab59-0cc47af964e9 | W11: лист | X11: м2 | Y11: fa6fadf3-b578-11e7-a547-f6d178db6df1 | Z11: Склад упаковки готовой продукции (ЗСП) | AA11: 12 | AB11: 19 440,00 | AC11: 48.387 | AD11: 35.268 | AE11: Слопласт | AF11: null | AG11: К обеспечению | AH11: 0 | AI11: 958.46 | AJ11: 11 501,52 | AK11: 0 | AL11: 0 | AM11: 0 | AN11: 0 | AO11: С4 | AP11: 1 620,00 | AQ11: Мебель | AR11: e1cib/data/Документ.ЗаказКлиента?ref=99bb00155dde6a0011f11d3114fdc30b | AT11: 00000000-0000-0000-0000-000000000000 | AU11: Слопласт П (/1320 х 3050 х 0,5/BIPA/ТС//707//Ш) | AV11: узкий/BIPA/П/ТС/(0.5-1.0) | AW11: 2026 | AX11: ЗСУП-000004_2 026
A12: d30b1e43-164d-11f1-99b9-00155dde6a00 | B12: Заказ клиента ЗСУП-000812 от 27.02.2026 0:00:00 | C12: ЗСУП-000812 | D12: ЗСУП-000812_2026 | E12: 46080 | F12: 0 | G12: 0 | H12: Реализация | I12: Средний | J12: 9e38a44e-b7d0-11e7-a547-f6d178db6df1 | K12: На согласовании | L12: 05f2ed7a-4034-11ef-8110-00155d000d00 | M12: Сорокина Инга Викторовна | N12: 7ada799d-7cef-11f0-a009-00155d81c805 | O12: Ипатова Анна Юрьевна | P12: 043fe15a-a8fe-11e3-a2e4-0015171241a4 | Q12: 04e19795-f36b-11e8-9fe3-d000e1470f5d | R12: f8e09145-5001-11ef-ab64-0cc47af964e9 | S12: 0d1dd908-1fa2-11ed-ab55-0cc47af964e9 | T12: 55c87efc-b566-11e7-a547-f6d178db6df1 | V12: 037f533d-013b-11ef-ab64-0cc47af964e9 | W12: лист | X12: м2 | Y12: fa6fadf3-b578-11e7-a547-f6d178db6df1 | Z12: Склад упаковки готовой продукции (ЗСП) | AA12: 600 | AB12: 759 600,00 | AC12: 2419.355 | AD12: 1763.4 | AE12: Слопласт | AF12: null | AG12: К обеспечению | AH12: 0 | AI12: 1 025,10 | AJ12: 615 060,00 | AK12: 0 | AL12: 0 | AM12: 0 | AN12: 0 | AP12: 1 266,00 | AQ12: Мебель | AR12: e1cib/data/Документ.ЗаказКлиента?ref=99b900155dde6a0011f1164dd30b1e43 | AT12: 00000000-0000-0000-0000-000000000000 | AU12: Слопласт П (/1320 х 3050 х 0,5/BIPA/Г//711//Ш) | AV12: узкий/BIPA/П/Г/(0.5-1.0) | AW12: 2025 | AX12: ЗСУП-004450_2 025
A13: e2e7dc1d-0bbd-11f1-99b9-00155dde6a00 | B13: Заказ клиента ЗСУП-000564 от 16.02.2026 17:02:45 | C13: ЗСУП-000564 | D13: ЗСУП-000564_2026 | E13: 46069.71 | F13: 1 | G13: 0 | H13: Реализация | I13: Средний | J13: 9e38a44e-b7d0-11e7-a547-f6d178db6df1 | K13: К выполнению / В резерве | L13: 59599dd2-c972-11ed-8109-00155d000d00 | M13: Стальберг Елена Александровна | N13: 59599dd2-c972-11ed-8109-00155d000d00 | O13: Стальберг Елена Александровна | P13: 7c3ca0c6-c6ed-11e3-8894-0015171241a5 | Q13: 6c972905-f36a-11e8-9fe3-d000e1470f5d | R13: bf6910b9-e175-11ef-ab6a-0cc47af964e9 | S13: b716f4dd-1588-11e9-ab3f-0cc47af964e9 | T13: 609d494f-b566-11e7-a547-f6d178db6df1 | U13: Ожидается обеспечение | V13: 020a0fd1-ae0e-11e9-ab3f-0cc47af964e9 | W13: лист | X13: м2 | Y13: fa6fadf3-b578-11e7-a547-f6d178db6df1 | Z13: Склад упаковки готовой продукции (ЗСП) | AA13: 1 | AB13: 22 149,00 | AC13: 4.032 | AD13: 58.78 | AE13: Слопласт | AF13: null | AG13: К обеспечению | AH13: 0 | AI13: 18 182,41 | AJ13: 18 182,41 | AK13: 0 | AL13: 0 | AM13: 0 | AN13: 0 | AP13: 22 149,00 | AQ13: ГК | AR13: e1cib/data/Документ.ЗаказКлиента?ref=99b900155dde6a0011f10bbde2e7dc1d | AT13: 00000000-0000-0000-0000-000000000000 | AU13: Слопласт Д (/1320 х 3050 х 12,0/2/BIFM/Т//2760/2760//Н) | AV13: узкий/BIFM/Д/Т/(12.0) | AW13: 2025 | AX13: ЗСУП-004450_2 025
A14: ed25a087-212c-11f1-99bb-00155dde6a00 | B14: Заказ клиента ЗСУП-000911 от 16.03.2026 14:29:36 | C14: ЗСУП-000911 | D14: ЗСУП-000911_2026 | E14: 46097.603 | F14: 1 | G14: 0 | H14: Реализация | I14: Средний | J14: 9e38a44e-b7d0-11e7-a547-f6d178db6df1 | K14: К выполнению / В резерве | L14: 05f2ed7a-4034-11ef-8110-00155d000d00 | M14: Сорокина Инга Викторовна | N14: 7ada799d-7cef-11f0-a009-00155d81c805 | O14: Ипатова Анна Юрьевна | P14: 043fe15a-a8fe-11e3-a2e4-0015171241a4 | Q14: 04e19795-f36b-11e8-9fe3-d000e1470f5d | R14: f8e09145-5001-11ef-ab64-0cc47af964e9 | S14: 0d1dd908-1fa2-11ed-ab55-0cc47af964e9 | T14: 55c87efc-b566-11e7-a547-f6d178db6df1 | U14: Ожидается обеспечение | V14: 0893a63f-048c-11ef-ab64-0cc47af964e9 | W14: лист | X14: м2 | Y14: fa6fadf3-b578-11e7-a547-f6d178db6df1 | Z14: Склад упаковки готовой продукции (ЗСП) | AA14: 36 | AB14: 54 000,00 | AC14: 145.161 | AD14: 105.804 | AE14: Слопласт | AF14: null | AG14: К обеспечению | AH14: 0 | AI14: 1 025,10 | AJ14: 36 903,60 | AK14: 0 | AL14: 0 | AM14: 0 | AN14: 0 | AP14: 1 500,00 | AQ14: Мебель | AR14: e1cib/data/Документ.ЗаказКлиента?ref=99bb00155dde6a0011f1212ced25a087 | AT14: 00000000-0000-0000-0000-000000000000 | AU14: Слопласт П (/1320 х 3050 х 0,5/BIPA/Г//711//Ш) | AV14: узкий/BIPA/П/Г/(0.5-1.0) | AW14: 2025 | AX14: ЗСУП-004450_2 025
A15: cc3a40a9-1ee5-11f1-99bb-00155dde6a00 | B15: Заказ клиента ЗСУП-000882 от 13.03.2026 17:06:15 | C15: ЗСУП-000882 | D15: ЗСУП-000882_2026 | E15: 46094.713 | F15: 0 | G15: 0 | H15: Реализация | I15: Средний | J15: 9e38a44e-b7d0-11e7-a547-f6d178db6df1 | K15: На согласовании | L15: 59599dd2-c972-11ed-8109-00155d000d00 | M15: Стальберг Елена Александровна | N15: 7fc9daa0-066f-11f1-a014-00155d81c802 | O15: Кулагина Анна Александровна | P15: 1b556bc5-f368-11e8-9fe3-d000e1470f5d | Q15: 1b556bc6-f368-11e8-9fe3-d000e1470f5d | R15: 3081c846-2107-11f1-99bb-00155dde6a00 | S15: c42f193e-01ce-11e9-ab3f-0cc47af964e9 | T15: 55c87efc-b566-11e7-a547-f6d178db6df1 | V15: 03ed5797-640e-11e8-ab3e-0cc47af964e9 | W15: лист | X15: м2 | Y15: fa6fadf3-b578-11e7-a547-f6d178db6df1 | Z15: Склад упаковки готовой продукции (ЗСП) | AA15: 8 | AB15: 417 600,00 | AC15: 38.278 | AD15: 783.016 | AE15: Слопласт | AF15: null | AG15: К обеспечению | AH15: 0 | AI15: 31 988,29 | AJ15: 255 906,32 | AK15: 0 | AL15: 0 | AM15: 0 | AN15: 0 | AO15: С2 | AP15: 52 200,00 | AQ15: Транспорт | AR15: e1cib/data/Документ.ЗаказКлиента?ref=99bb00155dde6a0011f11ee5cc3a40a9 | AT15: 00000000-0000-0000-0000-000000000000 | AU15: Слопласт ТГ (/1570 х 3050 х 14,0/2/BITM/Т//2762/2762//Н) | AV15: широкий/BITM/ТГ/Т/(13.0-25.0) | AW15: 2026 | AX15: ЗСУП-000321_2 026
A16: 45b6d95f-fc4c-11f0-99b9-00155dde6a00 | B16: Заказ клиента ЗСУП-000249 от 28.01.2026 16:06:42 | C16: ЗСУП-000249 | D16: ЗСУП-000249_2026 | E16: 46050.671 | F16: 1 | G16: 0 | H16: Реализация | I16: Средний | J16: 9e38a44e-b7d0-11e7-a547-f6d178db6df1 | K16: Закрыт | L16: 05f2ed7a-4034-11ef-8110-00155d000d00 | M16: Сорокина Инга Викторовна | N16: bafef812-be80-11ee-ab64-0cc47af964e9 | O16: Сидоренко Юлия Сергеевна | P16: 043fe15a-a8fe-11e3-a2e4-0015171241a4 | Q16: 04e19795-f36b-11e8-9fe3-d000e1470f5d | R16: f8e09145-5001-11ef-ab64-0cc47af964e9 | S16: 0d1dd908-1fa2-11ed-ab55-0cc47af964e9 | T16: 609d494f-b566-11e7-a547-f6d178db6df1 | U16: Закрыт | V16: 037f533d-013b-11ef-ab64-0cc47af964e9 | W16: лист | X16: м2 | Y16: fa6fadf3-b578-11e7-a547-f6d178db6df1 | Z16: Склад упаковки готовой продукции (ЗСП) | AA16: 12 | AB16: 15 192,00 | AC16: 48.387 | AD16: 35.268 | AE16: Слопласт | AF16: 46066 | AG16: Отгрузить | AH16: 0 | AI16: 919.22 | AJ16: 11 030,64 | AK16: 0 | AL16: 0 | AM16: 0 | AN16: 0 | AP16: 1 266,00 | AQ16: Мебель | AR16: e1cib/data/Документ.ЗаказКлиента?ref=99b900155dde6a0011f0fc4c45b6d95f | AT16: 00000000-0000-0000-0000-000000000000 | AU16: Слопласт П (/1320 х 3050 х 0,5/BIPA/Г//711//Ш) | AV16: узкий/BIPA/П/Г/(0.5-1.0) | AW16: 2025 | AX16: ЗСУП-001594_2 025
A17: 886a2158-0bd4-11f1-99b9-00155dde6a00 | B17: Заказ клиента ЗСУП-000524 от 12.03.2026 0:00:00 | C17: ЗСУП-000524 | D17: ЗСУП-000524_2026 | E17: 46093 | F17: 1 | G17: 0 | H17: Реализация | I17: Средний | J17: 9e38a44e-b7d0-11e7-a547-f6d178db6df1 | K17: На согласовании | L17: 8870b4a7-f73b-11e6-80de-00155d000d00 | M17: Козлова Мария Николаевна | N17: c2b02347-0c63-11ef-ab64-0cc47af964e9 | O17: Касимова Карина Ринатовна | P17: 0600068e-2127-45ca-91ca-271aa52dfc58 | Q17: 48591ce1-a540-448b-9f0c-5fef704a3eba | R17: 6b74db2f-0bd4-11f1-99b9-00155dde6a00 | S17: 54206bf8-fefd-11ea-ab46-0cc47af964e9 | T17: 55c87efc-b566-11e7-a547-f6d178db6df1 | U17: Ожидается согласование | V17: 030917fe-1900-11eb-ab48-0cc47af964e9 | W17: лист | X17: м2 | Y17: fa6fadf3-b578-11e7-a547-f6d178db6df1 | Z17: Склад упаковки готовой продукции (ЗСП) | AA17: 32 | AB17: 828 928,00 | AC17: 129.032 | AD17: 1504.768 | AE17: Слопласт | AF17: null | AG17: К обеспечению | AH17: 0 | AI17: 0 | AJ17: 0 | AK17: 0 | AL17: 0 | AM17: 0 | AN17: 0 | AP17: 25 904,00 | AQ17: Стройка | AR17: e1cib/data/Документ.ЗаказКлиента?ref=99b900155dde6a0011f10bd4886a2158 | AT17: c66f8b60-0b1c-11f1-99b9-00155dde6a00 | AU17: Слопласт ТГ (/1320 х 3050 х 8,0/2/BITM/Т//2756/2756//Н) | AV17: узкий/BITM/ТГ/Т/(8.0) | AW17: 2026 | AX17: ЗСУП-000700_2 026
A18: 882b5916-116f-11f1-99b9-00155dde6a00 | B18: Заказ клиента ЗСУП-000609 от 24.02.2026 13:56:36 | C18: ЗСУП-000609 | D18: ЗСУП-000609_2026 | E18: 46077.581 | F18: 1 | G18: 0 | H18: Реализация | I18: Высокий | J18: 9e38a44e-b7d0-11e7-a547-f6d178db6df1 | K18: Закрыт | L18: 5b3155c0-23a7-11e5-80ca-00155d000d00 | M18: Новинская Светлана Анатольевна | N18: 7ada799d-7cef-11f0-a009-00155d81c805 | O18: Ипатова Анна Юрьевна | P18: bed902e8-43aa-11ec-ab50-0cc47af964e9 | Q18: 275aab44-f368-11e8-9fe3-d000e1470f5d | R18: 695f4407-2bab-11ee-ab62-0cc47af964e9 | S18: 54206bf8-fefd-11ea-ab46-0cc47af964e9 | T18: 55c87efc-b566-11e7-a547-f6d178db6df1 | U18: Закрыт | V18: 13ca80d0-c09b-11e7-80e3-00155d000d00 | W18: лист | X18: м2 | Y18: f027a6ed-b812-11e7-a547-f6d178db6df1 | Z18: Склад МО (Мытищи) | AA18: 8 | AB18: 49 536,00 | AC18: 38.278 | AD18: 111.856 | AE18: Слопласт | AF18: 46108 | AG18: Отгрузить | AH18: 0 | AI18: 3 950,61 | AJ18: 31 604,88 | AK18: 0 | AL18: 0 | AM18: 0 | AN18: 0 | AO18: С4 | AP18: 6 192,00 | AQ18: Транспорт | AR18: e1cib/data/Документ.ЗаказКлиента?ref=99b900155dde6a0011f1116f882b5916 | AT18: 00000000-0000-0000-0000-000000000000 | AU18: Слопласт ТГ (/1570 х 3050 х 2,0/1/BITM/М//2760//Ш) | AV18: широкий/BITM/ТГ/М/(2.0) | AW18: 2025 | AX18: ЗСУП-001743_2 025

Sheet doc_Sales
A1: base | B1: dt | C1: id_1c | D1: Name | E1: Number | F1: Date | G1: Posted | H1: IsDelete | I1: vid_oper | J1: Priority | K1: organisation_id_1с | L1: status | M1: phersons_id_1с | N1: Partner_id | O1: contractor_id_1с | P1: agreement_id_1с | Q1: covenant_id_1c | R1: department_id_1c | S1: Nomenclature_id_1c | T1: UnitStore | U1: UnitReport | V1: store_id_1c | W1: store_name | X1: Quantity | Y1: Amount | Z1: QuantityUnitReport | AA1: QuantityWeight | AB1: VidNomenclature | AC1: vid_price | AD1: AmountNDS | AE1: Price | AF1: direction | AG1: Zakaz_id_1c | AH1: Ref_1c | AI1: Сведено | AJ1: spr_nomenclature.code1С
A2: ERP | B2: 46000.557 | C2: e5b05548-d4e2-11f0-99b9-00155dde6a00 | D2: Реализация товаров и услуг ЗСУП-004953 от 09.12.2025 12:39:10 | E2: ЗСУП-004953 | F2: 46000.527 | G2: 1 | H2: 0 | I2: Реализация | J2: null | K2: 9e38a44e-b7d0-11e7-a547-f6d178db6df1 | L2: Реализовано | M2: 59599dd2-c972-11ed-8109-00155d000d00 | N2: 7c3ca0c6-c6ed-11e3-8894-0015171241a5 | O2: 6c972905-f36a-11e8-9fe3-d000e1470f5d | P2: bf6910b9-e175-11ef-ab6a-0cc47af964e9 | Q2: d5bcc2ca-e174-11ef-ab6a-0cc47af964e9 | R2: 609d494f-b566-11e7-a547-f6d178db6df1 | S2: 008da890-d0f0-11f0-99b9-00155dde6a00 | T2: лист | U2: м2 | V2: fa6fadf3-b578-11e7-a547-f6d178db6df1 | W2: Склад упаковки готовой продукции (ЗСП) | X2: 2 | Y2: 32 116,00 | Z2: 9.569 | AA2: 0.072 | AB2: Слопласт | AD2: 5 352,67 | AE2: 16 058,00 | AF2: ГК | AG2: f38645b5-1d2d-11f1-99bb-00155dde6a00 | AH2: e1cib/data/Документ.РеализацияТоваровУслуг?ref=99b900155dde6a0011f0d4e2e5b05548 | AI2: e53ee5f8-d0f0-11f0-99b9-00155dde6a00008da890-d0f0-11f0-99b9-00155dde6a00 | AJ2: УП-00114496
A3: ERP | B3: 46015.413 | C3: 4dbe3103-e096-11f0-99b9-00155dde6a00 | D3: Реализация товаров и услуг ЗСУП-005234 от 24.12.2025 10:01:09 | E3: ЗСУП-005234 | F3: 46015.417 | G3: 1 | H3: 0 | I3: Реализация | J3: null | K3: 9e38a44e-b7d0-11e7-a547-f6d178db6df1 | L3: Реализовано | M3: 59599dd2-c972-11ed-8109-00155d000d00 | N3: 7c3ca0c6-c6ed-11e3-8894-0015171241a5 | O3: 6c972905-f36a-11e8-9fe3-d000e1470f5d | P3: bf6910b9-e175-11ef-ab6a-0cc47af964e9 | Q3: d5bcc2ca-e174-11ef-ab6a-0cc47af964e9 | R3: 609d494f-b566-11e7-a547-f6d178db6df1 | S3: 008da890-d0f0-11f0-99b9-00155dde6a00 | T3: лист | U3: м2 | V3: fa6fadf3-b578-11e7-a547-f6d178db6df1 | W3: Склад упаковки готовой продукции (ЗСП) | X3: 6 | Y3: 96 348,00 | Z3: 28.708 | AA3: 0.215 | AB3: Слопласт | AD3: 16 058,00 | AE3: 16 058,00 | AF3: ГК | AG3: 80941762-16e0-11f1-99b9-00155dde6a00 | AH3: e1cib/data/Документ.РеализацияТоваровУслуг?ref=99b900155dde6a0011f0e0964dbe3103 | AI3: 7ec0f5a3-dbf2-11f0-99b9-00155dde6a00008da890-d0f0-11f0-99b9-00155dde6a00 | AJ3: УП-00114496
A4: ERP | B4: 46001.532 | C4: ad716318-d5a6-11f0-99b9-00155dde6a00 | D4: Реализация товаров и услуг ЗСУП-004988 от 10.12.2025 12:00:30 | E4: ЗСУП-004988 | F4: 46001.5 | G4: 1 | H4: 0 | I4: Реализация | J4: null | K4: 9e38a44e-b7d0-11e7-a547-f6d178db6df1 | L4: Реализовано | M4: 59599dd2-c972-11ed-8109-00155d000d00 | N4: 7c3ca0c6-c6ed-11e3-8894-0015171241a5 | O4: 6c972905-f36a-11e8-9fe3-d000e1470f5d | P4: bf6910b9-e175-11ef-ab6a-0cc47af964e9 | Q4: d5bcc2ca-e174-11ef-ab6a-0cc47af964e9 | R4: 609d494f-b566-11e7-a547-f6d178db6df1 | S4: 008da890-d0f0-11f0-99b9-00155dde6a00 | T4: лист | U4: м2 | V4: fa6fadf3-b578-11e7-a547-f6d178db6df1 | W4: Склад упаковки готовой продукции (ЗСП) | X4: 1 | Y4: 16 058,00 | Z4: 4.785 | AA4: 0.036 | AB4: Слопласт | AD4: 2 676,33 | AE4: 16 058,00 | AF4: ГК | AG4: 80941762-16e0-11f1-99b9-00155dde6a00 | AH4: e1cib/data/Документ.РеализацияТоваровУслуг?ref=99b900155dde6a0011f0d5a6ad716318 | AI4: e53ee5f8-d0f0-11f0-99b9-00155dde6a00008da890-d0f0-11f0-99b9-00155dde6a00 | AJ4: УП-00114496
A5: ERP | B5: 45999.843 | C5: 03186bd9-114e-11f0-ab6a-0cc47af964e9 | D5: Реализация товаров и услуг ЗСУП-001468 от 04.04.2025 15:12:01 | E5: ЗСУП-001468 | F5: 45751.633 | G5: 1 | H5: 0 | I5: Реализация | J5: null | K5: 9e38a44e-b7d0-11e7-a547-f6d178db6df1 | L5: Реализовано | M5: 59599dd2-c972-11ed-8109-00155d000d00 | N5: fb9d6cbe-e968-11e7-80e4-00155d000d00 | O5: f6cbecfd-f367-11e8-9fe3-d000e1470f5d | P5: 6abd010e-f3bc-11e8-9fe3-d000e1470f5d | Q5: c42f193e-01ce-11e9-ab3f-0cc47af964e9 | R5: 609d494f-b566-11e7-a547-f6d178db6df1 | S5: 000386a5-cb7d-11e7-80e3-00155d000d00 | T5: лист | U5: м2 | V5: f027a6ed-b812-11e7-a547-f6d178db6df1 | W5: Склад Москва | X5: 20 | Y5: 171 700,00 | Z5: 95.694 | AA5: 0.954 | AB5: Слопласт | AD5: 28 616,67 | AE5: 8 585,00 | AF5: Транспорт | AG5: 80941762-16e0-11f1-99b9-00155dde6a00 | AH5: e1cib/data/Документ.РеализацияТоваровУслуг?ref=ab6a0cc47af964e911f0114e03186bd9 | AI5: 6782ea25-0a2e-11f0-ab6a-0cc47af964e9000386a5-cb7d-11e7-80e3-00155d000d00 | AJ5: 00-00006192
A6: ERP | B6: 45999.843 | C6: 40e2e0e1-b4b7-11f0-99b8-00155dde6a00 | D6: Реализация товаров и услуг ЗСУП-004205 от 29.10.2025 14:06:02 | E6: ЗСУП-004205 | F6: 45959.588 | G6: 1 | H6: 0 | I6: Реализация | J6: null | K6: 9e38a44e-b7d0-11e7-a547-f6d178db6df1 | L6: Реализовано | M6: 59599dd2-c972-11ed-8109-00155d000d00 | N6: fb9d6cbe-e968-11e7-80e4-00155d000d00 | O6: f6cbecfd-f367-11e8-9fe3-d000e1470f5d | P6: 6abd010e-f3bc-11e8-9fe3-d000e1470f5d | Q6: 54206bf8-fefd-11ea-ab46-0cc47af964e9 | R6: 55c87efc-b566-11e7-a547-f6d178db6df1 | S6: 000386a5-cb7d-11e7-80e3-00155d000d00 | T6: лист | U6: м2 | V6: f027a6ed-b812-11e7-a547-f6d178db6df1 | W6: Склад Москва | X6: 12 | Y6: 103 020,00 | Z6: 57.416 | AA6: 0.572 | AB6: Слопласт | AC6: С4 | AD6: 17 170,00 | AE6: 8 585,00 | AF6: Транспорт | AG6: 80941762-16e0-11f1-99b9-00155dde6a00 | AH6: e1cib/data/Документ.РеализацияТоваровУслуг?ref=99b800155dde6a0011f0b4b740e2e0e1 | AI6: 327923bd-a060-11f0-99b7-00155dde6a00000386a5-cb7d-11e7-80e3-00155d000d00 | AJ6: 00-00006192
A7: ERP | B7: 46001.49 | C7: cc6c14e9-cc3a-11f0-99b9-00155dde6a00 | D7: Реализация товаров и услуг ЗСУП-004801 от 28.11.2025 12:15:43 | E7: ЗСУП-004801 | F7: 45989.511 | G7: 1 | H7: 0 | I7: Реализация | J7: null | K7: 9e38a44e-b7d0-11e7-a547-f6d178db6df1 | L7: Реализовано | M7: ca842095-b338-11e8-80e7-00155d000d00 | N7: f3ef402d-ff15-11ef-ab6a-0cc47af964e9 | O7: f3ef4054-ff15-11ef-ab6a-0cc47af964e9 | P7: 26361b55-9e9f-11f0-99b7-00155dde6a00 | Q7: 254335bb-a292-11f0-99b7-00155dde6a00 | R7: 609d494f-b566-11e7-a547-f6d178db6df1 | S7: 0a210693-8e39-11f0-99b7-00155dde6a00 | T7: лист | U7: м2 | V7: fa6fadf3-b578-11e7-a547-f6d178db6df1 | W7: Склад упаковки готовой продукции (ЗСП) | X7: 81 | Y7: 2 788 155,27 | Z7: 326.613 | AA7: 1.378 | AB7: Слопласт | AD7: 464 692,55 | AE7: 34 421,67 | AF7: Стройка | AG7: f38645b5-1d2d-11f1-99bb-00155dde6a00 | AH7: e1cib/data/Документ.РеализацияТоваровУслуг?ref=99b900155dde6a0011f0cc3acc6c14e9 | AI7: ed4df888-9e9f-11f0-99b7-00155dde6a000a210693-8e39-11f0-99b7-00155dde6a00 | AJ7: УП-00112269
A8: ERP | B8: 46001.448 | C8: 187f0979-cc37-11f0-99b9-00155dde6a00 | D8: Реализация товаров и услуг ЗСУП-004799 от 28.11.2025 11:49:10 | E8: ЗСУП-004799 | F8: 45989.492 | G8: 1 | H8: 0 | I8: Реализация | J8: null | K8: 9e38a44e-b7d0-11e7-a547-f6d178db6df1 | L8: Реализовано | M8: ca842095-b338-11e8-80e7-00155d000d00 | N8: f3ef402d-ff15-11ef-ab6a-0cc47af964e9 | O8: f3ef4054-ff15-11ef-ab6a-0cc47af964e9 | P8: 26361b55-9e9f-11f0-99b7-00155dde6a00 | Q8: 254335bb-a292-11f0-99b7-00155dde6a00 | R8: 609d494f-b566-11e7-a547-f6d178db6df1 | S8: 0a210693-8e39-11f0-99b7-00155dde6a00 | T8: лист | U8: м2 | V8: fa6fadf3-b578-11e7-a547-f6d178db6df1 | W8: Склад упаковки готовой продукции (ЗСП) | X8: 240 | Y8: 8 261 200,80 | Z8: 967.742 | AA8: 4.083 | AB8: Слопласт | AD8: 1 376 866,80 | AE8: 34 421,67 | AF8: Стройка | AG8: f38645b5-1d2d-11f1-99bb-00155dde6a00 | AH8: e1cib/data/Документ.РеализацияТоваровУслуг?ref=99b900155dde6a0011f0cc37187f0979 | AI8: ed4df888-9e9f-11f0-99b7-00155dde6a000a210693-8e39-11f0-99b7-00155dde6a00 | AJ8: УП-00112269
A9: ERP | B9: 46001.49 | C9: cc6c14e9-cc3a-11f0-99b9-00155dde6a00 | D9: Реализация товаров и услуг ЗСУП-004801 от 28.11.2025 12:15:43 | E9: ЗСУП-004801 | F9: 45989.511 | G9: 1 | H9: 0 | I9: Реализация | J9: null | K9: 9e38a44e-b7d0-11e7-a547-f6d178db6df1 | L9: Реализовано | M9: ca842095-b338-11e8-80e7-00155d000d00 | N9: f3ef402d-ff15-11ef-ab6a-0cc47af964e9 | O9: f3ef4054-ff15-11ef-ab6a-0cc47af964e9 | P9: 26361b55-9e9f-11f0-99b7-00155dde6a00 | Q9: 254335bb-a292-11f0-99b7-00155dde6a00 | R9: 609d494f-b566-11e7-a547-f6d178db6df1 | S9: 0a210693-8e39-11f0-99b7-00155dde6a00 | T9: лист | U9: м2 | V9: fa6fadf3-b578-11e7-a547-f6d178db6df1 | W9: Склад упаковки готовой продукции (ЗСП) | X9: 16 | Y9: 550 746,72 | Z9: 64.516 | AA9: 0.272 | AB9: Слопласт | AD9: 91 791,12 | AE9: 34 421,67 | AF9: Стройка | AG9: f38645b5-1d2d-11f1-99bb-00155dde6a00 | AH9: e1cib/data/Документ.РеализацияТоваровУслуг?ref=99b900155dde6a0011f0cc3acc6c14e9 | AI9: ed4df888-9e9f-11f0-99b7-00155dde6a000a210693-8e39-11f0-99b7-00155dde6a00 | AJ9: УП-00112269
A10: ERP | B10: 45999.843 | C10: ac6b068d-cf38-11ef-ab69-0cc47af964e9 | D10: Реализация товаров и услуг ЗСУП-000019 от 10.01.2025 12:52:59 | E10: ЗСУП-000019 | F10: 45667.537 | G10: 1 | H10: 0 | I10: Реализация | J10: null | K10: 9e38a44e-b7d0-11e7-a547-f6d178db6df1 | L10: Реализовано | M10: c500dad6-819e-11e7-80e2-00155d000d00 | N10: 78d73f12-f36a-11e8-9fe3-d000e1470f5d | O10: 78d73f13-f36a-11e8-9fe3-d000e1470f5d | P10: 132ad76f-5aaa-11ed-ab58-0cc47af964e9 | Q10: 8c0ae592-d13a-11ec-ab51-0cc47af964e9 | R10: 609d494f-b566-11e7-a547-f6d178db6df1 | S10: 194970a4-6577-11ed-ab59-0cc47af964e9 | T10: лист | U10: м2 | V10: fa6fadf3-b578-11e7-a547-f6d178db6df1 | W10: Склад упаковки готовой продукции (ЗСП) | X10: 139 | Y10: 205 859,00 | Z10: 560.484 | AA10: 47.295 | AB10: Слопласт | AD10: 34 309,83 | AE10: 1 481,00 | AF10: Мебель | AG10: 653048a2-1955-11f1-99bb-00155dde6a00 | AH10: e1cib/data/Документ.РеализацияТоваровУслуг?ref=ab690cc47af964e911efcf38ac6b068d | AI10: 9ed26bb3-9dca-11ef-ab68-0cc47af964e9194970a4-6577-11ed-ab59-0cc47af964e9 | AJ10: УП-00080436
A11: ERP | B11: 45999.843 | C11: d6f2c30f-d317-11ef-ab69-0cc47af964e9 | D11: Реализация товаров и услуг ЗСУП-000092 от 15.01.2025 11:08:05 | E11: ЗСУП-000092 | F11: 45672.464 | G11: 1 | H11: 0 | I11: Реализация | J11: null | K11: 9e38a44e-b7d0-11e7-a547-f6d178db6df1 | L11: Реализовано | M11: c500dad6-819e-11e7-80e2-00155d000d00 | N11: 78d73f12-f36a-11e8-9fe3-d000e1470f5d | O11: 78d73f13-f36a-11e8-9fe3-d000e1470f5d | P11: 132ad76f-5aaa-11ed-ab58-0cc47af964e9 | Q11: 8c0ae592-d13a-11ec-ab51-0cc47af964e9 | R11: 609d494f-b566-11e7-a547-f6d178db6df1 | S11: 194970a4-6577-11ed-ab59-0cc47af964e9 | T11: лист | U11: м2 | V11: fa6fadf3-b578-11e7-a547-f6d178db6df1 | W11: Склад упаковки готовой продукции (ЗСП) | X11: 47 | Y11: 69 607,00 | Z11: 189.516 | AA11: 15.992 | AB11: Слопласт | AD11: 11 601,17 | AE11: 1 481,00 | AF11: Мебель | AG11: 653048a2-1955-11f1-99bb-00155dde6a00 | AH11: e1cib/data/Документ.РеализацияТоваровУслуг?ref=ab690cc47af964e911efd317d6f2c30f | AI11: f2d22a58-bded-11ef-ab69-0cc47af964e9194970a4-6577-11ed-ab59-0cc47af964e9 | AJ11: УП-00080436
A12: ERP | B12: 45999.843 | C12: 5528c09f-da2f-11ef-ab69-0cc47af964e9 | D12: Реализация товаров и услуг ЗСУП-000322 от 24.01.2025 11:43:52 | E12: ЗСУП-000322 | F12: 45681.489 | G12: 1 | H12: 0 | I12: Реализация | J12: null | K12: 9e38a44e-b7d0-11e7-a547-f6d178db6df1 | L12: Реализовано | M12: bafef812-be80-11ee-ab64-0cc47af964e9 | N12: 3fa69b08-b7a5-11e2-ae63-0015171241a4 | O12: 35ad1025-f36b-11e8-9fe3-d000e1470f5d | P12: 98eb8223-4986-11ef-ab64-0cc47af964e9 | Q12: 52094fa9-769a-11eb-ab4c-0cc47af964e9 | R12: 609d494f-b566-11e7-a547-f6d178db6df1 | S12: 194970a4-6577-11ed-ab59-0cc47af964e9 | T12: лист | U12: м2 | V12: fa6fadf3-b578-11e7-a547-f6d178db6df1 | W12: Склад упаковки готовой продукции (ЗСП) | X12: 108 | Y12: 159 948,00 | Z12: 435.484 | AA12: 36.747 | AB12: Слопласт | AD12: 26 658,00 | AE12: 1 481,00 | AF12: Мебель | AG12: 653048a2-1955-11f1-99bb-00155dde6a00 | AH12: e1cib/data/Документ.РеализацияТоваровУслуг?ref=ab690cc47af964e911efda2f5528c09f | AI12: aa40444f-b08f-11ef-ab69-0cc47af964e9194970a4-6577-11ed-ab59-0cc47af964e9 | AJ12: УП-00080436
A13: ERP | B13: 45999.843 | C13: dee532e0-ded5-11ef-ab6a-0cc47af964e9 | D13: Реализация товаров и услуг ЗСУП-000399 от 30.01.2025 9:46:02 | E13: ЗСУП-000399 | F13: 45687.407 | G13: 1 | H13: 0 | I13: Реализация | J13: null | K13: 9e38a44e-b7d0-11e7-a547-f6d178db6df1 | L13: Реализовано | M13: c500dad6-819e-11e7-80e2-00155d000d00 | N13: 78d73f12-f36a-11e8-9fe3-d000e1470f5d | O13: 78d73f13-f36a-11e8-9fe3-d000e1470f5d | P13: 132ad76f-5aaa-11ed-ab58-0cc47af964e9 | Q13: 8c0ae592-d13a-11ec-ab51-0cc47af964e9 | R13: 609d494f-b566-11e7-a547-f6d178db6df1 | S13: 194970a4-6577-11ed-ab59-0cc47af964e9 | T13: лист | U13: м2 | V13: fa6fadf3-b578-11e7-a547-f6d178db6df1 | W13: Склад упаковки готовой продукции (ЗСП) | X13: 71 | Y13: 105 151,00 | Z13: 286.29 | AA13: 24.158 | AB13: Слопласт | AD13: 17 525,17 | AE13: 1 481,00 | AF13: Мебель | AG13: 653048a2-1955-11f1-99bb-00155dde6a00 | AH13: e1cib/data/Документ.РеализацияТоваровУслуг?ref=ab6a0cc47af964e911efded5dee532e0 | AI13: 89fbe6b2-c50e-11ef-ab69-0cc47af964e9194970a4-6577-11ed-ab59-0cc47af964e9 | AJ13: УП-00080436
A14: ERP | B14: 45999.843 | C14: d4109a15-dfc4-11ef-ab6a-0cc47af964e9 | D14: Реализация товаров и услуг ЗСУП-000459 от 31.01.2025 14:16:40 | E14: ЗСУП-000459 | F14: 45688.595 | G14: 1 | H14: 0 | I14: Реализация | J14: null | K14: 9e38a44e-b7d0-11e7-a547-f6d178db6df1 | L14: Реализовано | M14: c500dad6-819e-11e7-80e2-00155d000d00 | N14: fedaf6c0-f36a-11e8-9fe3-d000e1470f5d | O14: fedaf6c1-f36a-11e8-9fe3-d000e1470f5d | P14: e7ca0348-1978-11ed-ab55-0cc47af964e9 | Q14: 54206bf8-fefd-11ea-ab46-0cc47af964e9 | R14: 609d494f-b566-11e7-a547-f6d178db6df1 | S14: 194970a4-6577-11ed-ab59-0cc47af964e9 | T14: лист | U14: м2 | V14: f027a6ed-b812-11e7-a547-f6d178db6df1 | W14: Склад Москва | X14: 12 | Y14: 17 772,00 | Z14: 48.387 | AA14: 4.083 | AB14: Слопласт | AD14: 2 962,00 | AE14: 1 481,00 | AF14: Мебель | AG14: 653048a2-1955-11f1-99bb-00155dde6a00 | AH14: e1cib/data/Документ.РеализацияТоваровУслуг?ref=ab6a0cc47af964e911efdfc4d4109a15 | AI14: c1aff4d3-c1cd-11ef-ab69-0cc47af964e9194970a4-6577-11ed-ab59-0cc47af964e9 | AJ14: УП-00080436
A15: ERP | B15: 45999.843 | C15: 15535da1-dfe3-11ef-ab6a-0cc47af964e9 | D15: Реализация товаров и услуг ЗСУП-000481 от 31.01.2025 17:53:09 | E15: ЗСУП-000481 | F15: 45688.745 | G15: 1 | H15: 0 | I15: Реализация | J15: null | K15: 9e38a44e-b7d0-11e7-a547-f6d178db6df1 | L15: Реализовано | M15: bd5b30ac-573c-11eb-ab4b-0cc47af964e9 | N15: e534587a-e964-11e7-80e4-00155d000d00 | O15: ada5d5f6-f367-11e8-9fe3-d000e1470f5d | P15: d79896b0-11a7-11ed-ab55-0cc47af964e9 | Q15: 4bba30ca-29d6-11ed-ab55-0cc47af964e9 | R15: 609d494f-b566-11e7-a547-f6d178db6df1 | S15: 194970a4-6577-11ed-ab59-0cc47af964e9 | T15: лист | U15: м2 | V15: fa6fadf3-b578-11e7-a547-f6d178db6df1 | W15: Склад упаковки готовой продукции (ЗСП) | X15: 12 | Y15: 16 884,00 | Z15: 48.387 | AA15: 4.083 | AB15: Слопласт | AD15: 2 814,00 | AE15: 1 407,00 | AF15: Мебель | AG15: 653048a2-1955-11f1-99bb-00155dde6a00 | AH15: e1cib/data/Документ.РеализацияТоваровУслуг?ref=ab6a0cc47af964e911efdfe315535da1 | AI15: e0ef67b0-bbbd-11ef-ab69-0cc47af964e9194970a4-6577-11ed-ab59-0cc47af964e9 | AJ15: УП-00080436
A16: ERP | B16: 45999.843 | C16: 82fb607f-ead0-11ef-ab6a-0cc47af964e9 | D16: Реализация товаров и услуг ЗСУП-000668 от 14.02.2025 15:37:55 | E16: ЗСУП-000668 | F16: 45702.651 | G16: 1 | H16: 0 | I16: Реализация | J16: null | K16: 9e38a44e-b7d0-11e7-a547-f6d178db6df1 | L16: Реализовано | M16: bd5b30ac-573c-11eb-ab4b-0cc47af964e9 | N16: e534587a-e964-11e7-80e4-00155d000d00 | O16: ada5d5f6-f367-11e8-9fe3-d000e1470f5d | P16: d79896b0-11a7-11ed-ab55-0cc47af964e9 | Q16: 4bba30ca-29d6-11ed-ab55-0cc47af964e9 | R16: 609d494f-b566-11e7-a547-f6d178db6df1 | S16: 194970a4-6577-11ed-ab59-0cc47af964e9 | T16: лист | U16: м2 | V16: fa6fadf3-b578-11e7-a547-f6d178db6df1 | W16: Склад упаковки готовой продукции (ЗСП) | X16: 46 | Y16: 64 722,00 | Z16: 185.484 | AA16: 15.652 | AB16: Слопласт | AD16: 10 787,00 | AE16: 1 407,00 | AF16: Мебель | AG16: bbe8240f-16e1-11f1-99b9-00155dde6a00 | AH16: e1cib/data/Документ.РеализацияТоваровУслуг?ref=ab6a0cc47af964e911efead082fb607f | AI16: cf773fa8-d7cf-11ef-ab69-0cc47af964e9194970a4-6577-11ed-ab59-0cc47af964e9 | AJ16: УП-00080436
A17: ERP | B17: 45999.843 | C17: 0b526d38-ed21-11ef-ab6a-0cc47af964e9 | D17: Реализация товаров и услуг ЗСУП-000702 от 17.02.2025 14:19:30 | E17: ЗСУП-000702 | F17: 45705.597 | G17: 1 | H17: 0 | I17: Реализация | J17: null | K17: 9e38a44e-b7d0-11e7-a547-f6d178db6df1 | L17: Реализовано | M17: c500dad6-819e-11e7-80e2-00155d000d00 | N17: fc4ae344-ad9b-11eb-ab4c-0cc47af964e9 | O17: fc4ae347-ad9b-11eb-ab4c-0cc47af964e9 | P17: 79948e91-e4f5-11ee-ab64-0cc47af964e9 | Q17: 061dcbcf-02e8-11eb-ab46-0cc47af964e9 | R17: 609d494f-b566-11e7-a547-f6d178db6df1 | S17: 194970a4-6577-11ed-ab59-0cc47af964e9 | T17: лист | U17: м2 | V17: fa6fadf3-b578-11e7-a547-f6d178db6df1 | W17: Склад упаковки готовой продукции (ЗСП) | X17: 12 | Y17: 14 820,00 | Z17: 48.387 | AA17: 4.083 | AB17: Слопласт | AD17: 0 | AE17: 1 235,00 | AF17: Мебель | AG17: bbe8240f-16e1-11f1-99b9-00155dde6a00 | AH17: e1cib/data/Документ.РеализацияТоваровУслуг?ref=ab6a0cc47af964e911efed210b526d38 | AI17: 4f01dc00-d70e-11ef-ab69-0cc47af964e9194970a4-6577-11ed-ab59-0cc47af964e9 | AJ17: УП-00080436
A18: ERP | B18: 45999.843 | C18: a14f1b7e-f5ca-11ef-ab6a-0cc47af964e9 | D18: Реализация товаров и услуг ЗСУП-000919 от 28.02.2025 14:53:34 | E18: ЗСУП-000919 | F18: 45716.621 | G18: 1 | H18: 0 | I18: Реализация | J18: null | K18: 9e38a44e-b7d0-11e7-a547-f6d178db6df1 | L18: Реализовано | M18: bd5b30ac-573c-11eb-ab4b-0cc47af964e9 | N18: e534587a-e964-11e7-80e4-00155d000d00 | O18: ada5d5f6-f367-11e8-9fe3-d000e1470f5d | P18: d79896b0-11a7-11ed-ab55-0cc47af964e9 | Q18: 4bba30ca-29d6-11ed-ab55-0cc47af964e9 | R18: 609d494f-b566-11e7-a547-f6d178db6df1 | S18: 194970a4-6577-11ed-ab59-0cc47af964e9 | T18: лист | U18: м2 | V18: fa6fadf3-b578-11e7-a547-f6d178db6df1 | W18: Склад упаковки готовой продукции (ЗСП) | X18: 35 | Y18: 49 245,00 | Z18: 141.129 | AA18: 11.909 | AB18: Слопласт | AD18: 8 207,50 | AE18: 1 407,00 | AF18: Мебель | AG18: bbe8240f-16e1-11f1-99b9-00155dde6a00 | AH18: e1cib/data/Документ.РеализацияТоваровУслуг?ref=ab6a0cc47af964e911eff5caa14f1b7e | AI18: df87f30d-e3c8-11ef-ab6a-0cc47af964e9194970a4-6577-11ed-ab59-0cc47af964e9 | AJ18: УП-00080436
A19: ERP | B19: 45999.843 | C19: d4d33e6e-f5d9-11ef-ab6a-0cc47af964e9 | D19: Реализация товаров и услуг ЗСУП-000929 от 28.02.2025 16:42:20 | E19: ЗСУП-000929 | F19: 45716.696 | G19: 1 | H19: 0 | I19: Реализация | J19: null | K19: 9e38a44e-b7d0-11e7-a547-f6d178db6df1 | L19: Реализовано | M19: f422c0a3-be06-11e6-80dc-00155d000d00 | N19: 043fe15a-a8fe-11e3-a2e4-0015171241a4 | O19: 04e19795-f36b-11e8-9fe3-d000e1470f5d | P19: f8e09145-5001-11ef-ab64-0cc47af964e9 | Q19: 0d1dd908-1fa2-11ed-ab55-0cc47af964e9 | R19: 609d494f-b566-11e7-a547-f6d178db6df1 | S19: 194970a4-6577-11ed-ab59-0cc47af964e9 | T19: лист | U19: м2 | V19: fa6fadf3-b578-11e7-a547-f6d178db6df1 | W19: Склад упаковки готовой продукции (ЗСП) | X19: 107 | Y19: 158 467,00 | Z19: 431.452 | AA19: 36.407 | AB19: Слопласт | AD19: 26 411,17 | AE19: 1 481,00 | AF19: Мебель | AG19: bbe8240f-16e1-11f1-99b9-00155dde6a00 | AH19: e1cib/data/Документ.РеализацияТоваровУслуг?ref=ab6a0cc47af964e911eff5d9d4d33e6e | AI19: 5f5ac4cb-ed33-11ef-ab6a-0cc47af964e9194970a4-6577-11ed-ab59-0cc47af964e9 | AJ19: УП-00080436
A20: ERP | B20: 45999.843 | C20: 67a91eb0-f5db-11ef-ab6a-0cc47af964e9 | D20: Реализация товаров и услуг ЗСУП-000936 от 28.02.2025 16:53:41 | E20: ЗСУП-000936 | F20: 45716.704 | G20: 1 | H20: 0 | I20: Реализация | J20: null | K20: 9e38a44e-b7d0-11e7-a547-f6d178db6df1 | L20: Реализовано | M20: bd5b30ac-573c-11eb-ab4b-0cc47af964e9 | N20: e534587a-e964-11e7-80e4-00155d000d00 | O20: ada5d5f6-f367-11e8-9fe3-d000e1470f5d | P20: d79896b0-11a7-11ed-ab55-0cc47af964e9 | Q20: 4bba30ca-29d6-11ed-ab55-0cc47af964e9 | R20: 609d494f-b566-11e7-a547-f6d178db6df1 | S20: 194970a4-6577-11ed-ab59-0cc47af964e9 | T20: лист | U20: м2 | V20: fa6fadf3-b578-11e7-a547-f6d178db6df1 | W20: Склад упаковки готовой продукции (ЗСП) | X20: 45 | Y20: 63 315,00 | Z20: 181.452 | AA20: 15.311 | AB20: Слопласт | AD20: 10 552,50 | AE20: 1 407,00 | AF20: Мебель | AG20: bbe8240f-16e1-11f1-99b9-00155dde6a00 | AH20: e1cib/data/Документ.РеализацияТоваровУслуг?ref=ab6a0cc47af964e911eff5db67a91eb0 | AI20: 056ea087-eab7-11ef-ab6a-0cc47af964e9194970a4-6577-11ed-ab59-0cc47af964e9 | AJ20: УП-00080436
A21: ERP | B21: 45999.843 | C21: 0b298748-03d8-11f0-ab6a-0cc47af964e9 | D21: Реализация товаров и услуг ЗСУП-001170 от 18.03.2025 12:04:53 | E21: ЗСУП-001170 | F21: 45734.503 | G21: 1 | H21: 0 | I21: Реализация | J21: null | K21: 9e38a44e-b7d0-11e7-a547-f6d178db6df1 | L21: Реализовано | M21: 05f2ed7a-4034-11ef-8110-00155d000d00 | N21: 31844b91-355e-11de-8227-0015171241a4 | O21: 107108ee-f367-11e8-9fe3-d000e1470f5d | P21: 43488cf5-8bcf-11ef-ab68-0cc47af964e9 | Q21: 2f3364f4-226a-11ea-ab44-0cc47af964e9 | R21: 609d494f-b566-11e7-a547-f6d178db6df1 | S21: 194970a4-6577-11ed-ab59-0cc47af964e9 | T21: лист | U21: м2 | V21: fa6fadf3-b578-11e7-a547-f6d178db6df1 | W21: Склад упаковки готовой продукции (ЗСП) | X21: 12 | Y21: 17 772,00 | Z21: 48.387 | AA21: 4.083 | AB21: Слопласт | AD21: 2 962,00 | AE21: 1 481,00 | AF21: Мебель | AG21: b418c3b9-1636-11f1-99b9-00155dde6a00 | AH21: e1cib/data/Документ.РеализацияТоваровУслуг?ref=ab6a0cc47af964e911f003d80b298748 | AI21: 7fcbdc1a-f836-11ef-ab6a-0cc47af964e9194970a4-6577-11ed-ab59-0cc47af964e9 | AJ21: УП-00080436
A22: ERP | B22: 45999.843 | C22: aa7c881e-03f6-11f0-ab6a-0cc47af964e9 | D22: Реализация товаров и услуг ЗСУП-001175 от 18.03.2025 15:44:03 | E22: ЗСУП-001175 | F22: 45734.656 | G22: 1 | H22: 0 | I22: Реализация | J22: null | K22: 9e38a44e-b7d0-11e7-a547-f6d178db6df1 | L22: Реализовано | M22: bafef812-be80-11ee-ab64-0cc47af964e9 | N22: fc4ae344-ad9b-11eb-ab4c-0cc47af964e9 | O22: fc4ae347-ad9b-11eb-ab4c-0cc47af964e9 | P22: aee0dded-e7be-11ef-ab6a-0cc47af964e9 | Q22: 061dcbcf-02e8-11eb-ab46-0cc47af964e9 | R22: 55c87efc-b566-11e7-a547-f6d178db6df1 | S22: 194970a4-6577-11ed-ab59-0cc47af964e9 | T22: лист | U22: м2 | V22: fa6fadf3-b578-11e7-a547-f6d178db6df1 | W22: Склад упаковки готовой продукции (ЗСП) | X22: 12 | Y22: 14 820,00 | Z22: 48.387 | AA22: 4.083 | AB22: Слопласт | AD22: 0 | AE22: 1 235,00 | AF22: Мебель | AG22: b418c3b9-1636-11f1-99b9-00155dde6a00 | AH22: e1cib/data/Документ.РеализацияТоваровУслуг?ref=ab6a0cc47af964e911f003f6aa7c881e | AI22: 1812af48-f4d3-11ef-ab6a-0cc47af964e9194970a4-6577-11ed-ab59-0cc47af964e9 | AJ22: УП-00080436
A23: ERP | B23: 45999.843 | C23: 4135be23-0e3f-11f0-ab6a-0cc47af964e9 | D23: Реализация товаров и услуг ЗСУП-001430 от 31.03.2025 17:48:49 | E23: ЗСУП-001430 | F23: 45747.742 | G23: 1 | H23: 0 | I23: Реализация | J23: null | K23: 9e38a44e-b7d0-11e7-a547-f6d178db6df1 | L23: Реализовано | M23: 05f2ed7a-4034-11ef-8110-00155d000d00 | N23: e534587a-e964-11e7-80e4-00155d000d00 | O23: ada5d5f6-f367-11e8-9fe3-d000e1470f5d | P23: d79896b0-11a7-11ed-ab55-0cc47af964e9 | Q23: 4bba30ca-29d6-11ed-ab55-0cc47af964e9 | R23: 609d494f-b566-11e7-a547-f6d178db6df1 | S23: 194970a4-6577-11ed-ab59-0cc47af964e9 | T23: лист | U23: м2 | V23: fa6fadf3-b578-11e7-a547-f6d178db6df1 | W23: Склад упаковки готовой продукции (ЗСП) | X23: 12 | Y23: 16 884,00 | Z23: 48.387 | AA23: 4.083 | AB23: Слопласт | AD23: 2 814,00 | AE23: 1 407,00 | AF23: Мебель | AG23: b418c3b9-1636-11f1-99b9-00155dde6a00 | AH23: e1cib/data/Документ.РеализацияТоваровУслуг?ref=ab6a0cc47af964e911f00e3f4135be23 | AI23: 70556176-0659-11f0-ab6a-0cc47af964e9194970a4-6577-11ed-ab59-0cc47af964e9 | AJ23: УП-00080436
A24: ERP | B24: 45999.843 | C24: 5e84b4c7-1161-11f0-ab6a-0cc47af964e9 | D24: Реализация товаров и услуг ЗСУП-001475 от 04.04.2025 17:30:39 | E24: ЗСУП-001475 | F24: 45751.73 | G24: 1 | H24: 0 | I24: Реализация | J24: null | K24: 9e38a44e-b7d0-11e7-a547-f6d178db6df1 | L24: Реализовано | M24: 05f2ed7a-4034-11ef-8110-00155d000d00 | N24: 043fe15a-a8fe-11e3-a2e4-0015171241a4 | O24: 04e19795-f36b-11e8-9fe3-d000e1470f5d | P24: 144db961-4be7-11ef-ab64-0cc47af964e9 | Q24: 0d1dd908-1fa2-11ed-ab55-0cc47af964e9 | R24: 55c87efc-b566-11e7-a547-f6d178db6df1 | S24: 194970a4-6577-11ed-ab59-0cc47af964e9 | T24: лист | U24: м2 | V24: fa6fadf3-b578-11e7-a547-f6d178db6df1 | W24: Склад упаковки готовой продукции (ЗСП) | X24: 149 | Y24: 220 669,00 | Z24: 600.806 | AA24: 50.698 | AB24: Слопласт | AD24: 36 778,17 | AE24: 1 481,00 | AF24: Мебель | AG24: b418c3b9-1636-11f1-99b9-00155dde6a00 | AH24: e1cib/data/Документ.РеализацияТоваровУслуг?ref=ab6a0cc47af964e911f011615e84b4c7 | AI24: 6ea6aedf-04cb-11f0-ab6a-0cc47af964e9194970a4-6577-11ed-ab59-0cc47af964e9 | AJ24: УП-00080436
A25: ERP | B25: 45999.843 | C25: 0c6f661c-16a3-11f0-ab6a-0cc47af964e9 | D25: Реализация товаров и услуг ЗСУП-001536 от 11.04.2025 10:03:26 | E25: ЗСУП-001536 | F25: 45758.419 | G25: 1 | H25: 0 | I25: Реализация | J25: null | K25: 9e38a44e-b7d0-11e7-a547-f6d178db6df1 | L25: Реализовано | M25: 05f2ed7a-4034-11ef-8110-00155d000d00 | N25: 31844b91-355e-11de-8227-0015171241a4 | O25: 107108ee-f367-11e8-9fe3-d000e1470f5d | P25: 43488cf5-8bcf-11ef-ab68-0cc47af964e9 | Q25: 2f3364f4-226a-11ea-ab44-0cc47af964e9 | R25: 609d494f-b566-11e7-a547-f6d178db6df1 | S25: 194970a4-6577-11ed-ab59-0cc47af964e9 | T25: лист | U25: м2 | V25: fa6fadf3-b578-11e7-a547-f6d178db6df1 | W25: Склад упаковки готовой продукции (ЗСП) | X25: 12 | Y25: 17 772,00 | Z25: 48.387 | AA25: 4.083 | AB25: Слопласт | AD25: 2 962,00 | AE25: 1 481,00 | AF25: Мебель | AG25: b418c3b9-1636-11f1-99b9-00155dde6a00 | AH25: e1cib/data/Документ.РеализацияТоваровУслуг?ref=ab6a0cc47af964e911f016a30c6f661c | AI25: 44842685-08bd-11f0-ab6a-0cc47af964e9194970a4-6577-11ed-ab59-0cc47af964e9 | AJ25: УП-00080436
A26: ERP | B26: 45999.843 | C26: e50a4438-25c0-11f0-ab6a-0cc47af964e9 | D26: Реализация товаров и услуг ЗСУП-001819 от 30.04.2025 15:44:47 | E26: ЗСУП-001819 | F26: 45777.656 | G26: 1 | H26: 0 | I26: Реализация | J26: null | K26: 9e38a44e-b7d0-11e7-a547-f6d178db6df1 | L26: Реализовано | M26: 05f2ed7a-4034-11ef-8110-00155d000d00 | N26: 043fe15a-a8fe-11e3-a2e4-0015171241a4 | O26: 04e19795-f36b-11e8-9fe3-d000e1470f5d | P26: 144db961-4be7-11ef-ab64-0cc47af964e9 | Q26: 0d1dd908-1fa2-11ed-ab55-0cc47af964e9 | R26: 609d494f-b566-11e7-a547-f6d178db6df1 | S26: 194970a4-6577-11ed-ab59-0cc47af964e9 | T26: лист | U26: м2 | V26: fa6fadf3-b578-11e7-a547-f6d178db6df1 | W26: Склад упаковки готовой продукции (ЗСП) | X26: 137 | Y26: 177 415,00 | Z26: 552.419 | AA26: 46.614 | AB26: Слопласт | AD26: 29 569,17 | AE26: 1 295,00 | AF26: Мебель | AG26: c236b5ca-1e1d-11f1-99bb-00155dde6a00 | AH26: e1cib/data/Документ.РеализацияТоваровУслуг?ref=ab6a0cc47af964e911f025c0e50a4438 | AI26: 60ae1415-1b61-11f0-ab6a-0cc47af964e9194970a4-6577-11ed-ab59-0cc47af964e9 | AJ26: УП-00080436
A27: ERP | B27: 45999.843 | C27: faff8f37-25cd-11f0-ab6a-0cc47af964e9 | D27: Реализация товаров и услуг ЗСУП-001830 от 30.04.2025 17:18:30 | E27: ЗСУП-001830 | F27: 45777.721 | G27: 1 | H27: 0 | I27: Реализация | J27: null | K27: 9e38a44e-b7d0-11e7-a547-f6d178db6df1 | L27: Реализовано | M27: 05f2ed7a-4034-11ef-8110-00155d000d00 | N27: 3fa69b08-b7a5-11e2-ae63-0015171241a4 | O27: 35ad1025-f36b-11e8-9fe3-d000e1470f5d | P27: 98eb8223-4986-11ef-ab64-0cc47af964e9 | Q27: 52094fa9-769a-11eb-ab4c-0cc47af964e9 | R27: 55c87efc-b566-11e7-a547-f6d178db6df1 | S27: 194970a4-6577-11ed-ab59-0cc47af964e9 | T27: лист | U27: м2 | V27: fa6fadf3-b578-11e7-a547-f6d178db6df1 | W27: Склад упаковки готовой продукции (ЗСП) | X27: 200 | Y27: 296 200,00 | Z27: 806.452 | AA27: 68.05 | AB27: Слопласт | AD27: 49 366,67 | AE27: 1 481,00 | AF27: Мебель | AG27: c236b5ca-1e1d-11f1-99bb-00155dde6a00 | AH27: e1cib/data/Документ.РеализацияТоваровУслуг?ref=ab6a0cc47af964e911f025cdfaff8f37 | AI27: 3ee47088-25a1-11f0-ab6a-0cc47af964e9194970a4-6577-11ed-ab59-0cc47af964e9 | AJ27: УП-00080436
A28: ERP | B28: 45999.843 | C28: f9d45f73-308b-11f0-ab6b-0cc47af964e9 | D28: Реализация товаров и услуг ЗСУП-001920 от 14.05.2025 9:23:41 | E28: ЗСУП-001920 | F28: 45791.391 | G28: 1 | H28: 0 | I28: Реализация | J28: null | K28: 9e38a44e-b7d0-11e7-a547-f6d178db6df1 | L28: Реализовано | M28: 01d4de8c-6aaf-11ef-8110-00155d000d00 | N28: 31844b91-355e-11de-8227-0015171241a4 | O28: 107108ee-f367-11e8-9fe3-d000e1470f5d | P28: 43488cf5-8bcf-11ef-ab68-0cc47af964e9 | Q28: 2f3364f4-226a-11ea-ab44-0cc47af964e9 | R28: 609d494f-b566-11e7-a547-f6d178db6df1 | S28: 194970a4-6577-11ed-ab59-0cc47af964e9 | T28: лист | U28: м2 | V28: fa6fadf3-b578-11e7-a547-f6d178db6df1 | W28: Склад упаковки готовой продукции (ЗСП) | X28: 12 | Y28: 17 772,00 | Z28: 48.387 | AA28: 4.083 | AB28: Слопласт | AD28: 2 962,00 | AE28: 1 481,00 | AF28: Мебель | AG28: c236b5ca-1e1d-11f1-99bb-00155dde6a00 | AH28: e1cib/data/Документ.РеализацияТоваровУслуг?ref=ab6b0cc47af964e911f0308bf9d45f73 | AI28: 2459a82a-13a1-11f0-ab6a-0cc47af964e9194970a4-6577-11ed-ab59-0cc47af964e9 | AJ28: УП-00080436
A29: ERP | B29: 45999.843 | C29: 25a69a2d-3618-11f0-ab6b-0cc47af964e9 | D29: Реализация товаров и услуг ЗСУП-001975 от 21.05.2025 10:49:39 | E29: ЗСУП-001975 | F29: 45798.451 | G29: 1 | H29: 0 | I29: Реализация | J29: null | K29: 9e38a44e-b7d0-11e7-a547-f6d178db6df1 | L29: Реализовано | M29: 01d4de8c-6aaf-11ef-8110-00155d000d00 | N29: 31844b91-355e-11de-8227-0015171241a4 | O29: 107108ee-f367-11e8-9fe3-d000e1470f5d | P29: 43488cf5-8bcf-11ef-ab68-0cc47af964e9 | Q29: 2f3364f4-226a-11ea-ab44-0cc47af964e9 | R29: 609d494f-b566-11e7-a547-f6d178db6df1 | S29: 194970a4-6577-11ed-ab59-0cc47af964e9 | T29: лист | U29: м2 | V29: fa6fadf3-b578-11e7-a547-f6d178db6df1 | W29: Склад упаковки готовой продукции (ЗСП) | X29: 12 | Y29: 17 772,00 | Z29: 48.387 | AA29: 4.083 | AB29: Слопласт | AD29: 2 962,00 | AE29: 1 481,00 | AF29: Мебель | AG29: c236b5ca-1e1d-11f1-99bb-00155dde6a00 | AH29: e1cib/data/Документ.РеализацияТоваровУслуг?ref=ab6b0cc47af964e911f0361825a69a2d | AI29: b2084320-1543-11f0-ab6a-0cc47af964e9194970a4-6577-11ed-ab59-0cc47af964e9 | AJ29: УП-00080436
A30: ERP | B30: 45999.843 | C30: 57a3f573-36ee-11f0-ab6b-0cc47af964e9 | D30: Реализация товаров и услуг ЗСУП-001988 от 22.05.2025 12:22:58 | E30: ЗСУП-001988 | F30: 45799.516 | G30: 1 | H30: 0 | I30: Реализация | J30: null | K30: 9e38a44e-b7d0-11e7-a547-f6d178db6df1 | L30: Реализовано | M30: 01d4de8c-6aaf-11ef-8110-00155d000d00 | N30: e534587a-e964-11e7-80e4-00155d000d00 | O30: ada5d5f6-f367-11e8-9fe3-d000e1470f5d | P30: d79896b0-11a7-11ed-ab55-0cc47af964e9 | Q30: 4bba30ca-29d6-11ed-ab55-0cc47af964e9 | R30: 609d494f-b566-11e7-a547-f6d178db6df1 | S30: 194970a4-6577-11ed-ab59-0cc47af964e9 | T30: лист | U30: м2 | V30: fa6fadf3-b578-11e7-a547-f6d178db6df1 | W30: Склад упаковки готовой продукции (ЗСП) | X30: 24 | Y30: 33 768,00 | Z30: 96.774 | AA30: 8.166 | AB30: Слопласт | AD30: 5 628,00 | AE30: 1 407,00 | AF30: Мебель | AG30: c236b5ca-1e1d-11f1-99bb-00155dde6a00 | AH30: e1cib/data/Документ.РеализацияТоваровУслуг?ref=ab6b0cc47af964e911f036ee57a3f573 | AI30: 8ece1929-1f72-11f0-ab6a-0cc47af964e9194970a4-6577-11ed-ab59-0cc47af964e9 | AJ30: УП-00080436
A31: ERP | B31: 45999.843 | C31: beb54391-3d2b-11f0-ab6b-0cc47af964e9 | D31: Реализация товаров и услуг ЗСУП-002108 от 30.05.2025 10:57:34 | E31: ЗСУП-002108 | F31: 45807.457 | G31: 1 | H31: 0 | I31: Реализация | J31: null | K31: 9e38a44e-b7d0-11e7-a547-f6d178db6df1 | L31: Реализовано | M31: 05f2ed7a-4034-11ef-8110-00155d000d00 | N31: fc4ae344-ad9b-11eb-ab4c-0cc47af964e9 | O31: fc4ae347-ad9b-11eb-ab4c-0cc47af964e9 | P31: aee0dded-e7be-11ef-ab6a-0cc47af964e9 | Q31: 061dcbcf-02e8-11eb-ab46-0cc47af964e9 | R31: 55c87efc-b566-11e7-a547-f6d178db6df1 | S31: 194970a4-6577-11ed-ab59-0cc47af964e9 | T31: лист | U31: м2 | V31: fa6fadf3-b578-11e7-a547-f6d178db6df1 | W31: Склад упаковки готовой продукции (ЗСП) | X31: 11 | Y31: 13 585,00 | Z31: 44.355 | AA31: 3.743 | AB31: Слопласт | AD31: 0 | AE31: 1 235,00 | AF31: Мебель | AG31: c236b5ca-1e1d-11f1-99bb-00155dde6a00 | AH31: e1cib/data/Документ.РеализацияТоваровУслуг?ref=ab6b0cc47af964e911f03d2bbeb54391 | AI31: 1f3d71c3-2019-11f0-ab6a-0cc47af964e9194970a4-6577-11ed-ab59-0cc47af964e9 | AJ31: УП-00080436
A32: ERP | B32: 45999.843 | C32: d2e6baea-41fe-11f0-ab6b-0cc47af964e9 | D32: Реализация товаров и услуг ЗСУП-002195 от 05.06.2025 14:18:38 | E32: ЗСУП-002195 | F32: 45813.596 | G32: 1 | H32: 0 | I32: Реализация | J32: null | K32: 9e38a44e-b7d0-11e7-a547-f6d178db6df1 | L32: Реализовано | M32: 01d4de8c-6aaf-11ef-8110-00155d000d00 | N32: e534587a-e964-11e7-80e4-00155d000d00 | O32: ada5d5f6-f367-11e8-9fe3-d000e1470f5d | P32: d79896b0-11a7-11ed-ab55-0cc47af964e9 | Q32: 4bba30ca-29d6-11ed-ab55-0cc47af964e9 | R32: 609d494f-b566-11e7-a547-f6d178db6df1 | S32: 194970a4-6577-11ed-ab59-0cc47af964e9 | T32: лист | U32: м2 | V32: fa6fadf3-b578-11e7-a547-f6d178db6df1 | W32: Склад упаковки готовой продукции (ЗСП) | X32: 56 | Y32: 78 792,00 | Z32: 225.806 | AA32: 19.054 | AB32: Слопласт | AD32: 13 132,00 | AE32: 1 407,00 | AF32: Мебель | AG32: c236b5ca-1e1d-11f1-99bb-00155dde6a00 | AH32: e1cib/data/Документ.РеализацияТоваровУслуг?ref=ab6b0cc47af964e911f041fed2e6baea | AI32: 7f35cb9d-36f0-11f0-ab6b-0cc47af964e9194970a4-6577-11ed-ab59-0cc47af964e9 | AJ32: УП-00080436
A33: ERP | B33: 45999.843 | C33: 557eff22-5c95-11f0-ab6b-0cc47af964e9 | D33: Реализация товаров и услуг ЗСУП-002612 от 09.07.2025 10:21:32 | E33: ЗСУП-002612 | F33: 45847.432 | G33: 1 | H33: 0 | I33: Реализация | J33: null | K33: 9e38a44e-b7d0-11e7-a547-f6d178db6df1 | L33: Реализовано | M33: 01d4de8c-6aaf-11ef-8110-00155d000d00 | N33: 78d73f12-f36a-11e8-9fe3-d000e1470f5d | O33: 78d73f13-f36a-11e8-9fe3-d000e1470f5d | P33: 132ad76f-5aaa-11ed-ab58-0cc47af964e9 | Q33: 8c0ae592-d13a-11ec-ab51-0cc47af964e9 | R33: 609d494f-b566-11e7-a547-f6d178db6df1 | S33: 194970a4-6577-11ed-ab59-0cc47af964e9 | T33: лист | U33: м2 | V33: fa6fadf3-b578-11e7-a547-f6d178db6df1 | W33: Склад упаковки готовой продукции (ЗСП) | X33: 59 | Y33: 87 379,00 | Z33: 237.903 | AA33: 20.075 | AB33: Слопласт | AD33: 14 563,17 | AE33: 1 481,00 | AF33: Мебель | AG33: c6d95ff4-2269-11f1-99bb-00155dde6a00 | AH33: e1cib/data/Документ.РеализацияТоваровУслуг?ref=ab6b0cc47af964e911f05c95557eff22 | AI33: f9faff2d-5359-11f0-ab6b-0cc47af964e9194970a4-6577-11ed-ab59-0cc47af964e9 | AJ33: УП-00080436
A34: ERP | B34: 45999.843 | C34: 30fb33f1-6631-11f0-ab6b-0cc47af964e9 | D34: Реализация товаров и услуг ЗСУП-002762 от 21.07.2025 15:49:53 | E34: ЗСУП-002762 | F34: 45859.66 | G34: 1 | H34: 0 | I34: Реализация | J34: null | K34: 9e38a44e-b7d0-11e7-a547-f6d178db6df1 | L34: Реализовано | M34: 01d4de8c-6aaf-11ef-8110-00155d000d00 | N34: e534587a-e964-11e7-80e4-00155d000d00 | O34: ada5d5f6-f367-11e8-9fe3-d000e1470f5d | P34: d79896b0-11a7-11ed-ab55-0cc47af964e9 | Q34: 4bba30ca-29d6-11ed-ab55-0cc47af964e9 | R34: 609d494f-b566-11e7-a547-f6d178db6df1 | S34: 194970a4-6577-11ed-ab59-0cc47af964e9 | T34: лист | U34: м2 | V34: fa6fadf3-b578-11e7-a547-f6d178db6df1 | W34: Склад упаковки готовой продукции (ЗСП) | X34: 38 | Y34: 53 466,00 | Z34: 153.226 | AA34: 12.93 | AB34: Слопласт | AD34: 8 911,00 | AE34: 1 407,00 | AF34: Мебель | AG34: c6d95ff4-2269-11f1-99bb-00155dde6a00 | AH34: e1cib/data/Документ.РеализацияТоваровУслуг?ref=ab6b0cc47af964e911f0663130fb33f1 | AI34: 13ba3dfa-6182-11f0-ab6b-0cc47af964e9194970a4-6577-11ed-ab59-0cc47af964e9 | AJ34: УП-00080436
A35: ERP | B35: 45999.843 | C35: aaef353e-6857-11f0-ab6b-0cc47af964e9 | D35: Реализация товаров и услуг ЗСУП-002812 от 24.07.2025 9:30:21 | E35: ЗСУП-002812 | F35: 45862.396 | G35: 1 | H35: 0 | I35: Реализация | J35: null | K35: 9e38a44e-b7d0-11e7-a547-f6d178db6df1 | L35: Реализовано | M35: 01d4de8c-6aaf-11ef-8110-00155d000d00 | N35: 31844b91-355e-11de-8227-0015171241a4 | O35: 107108ee-f367-11e8-9fe3-d000e1470f5d | P35: 43488cf5-8bcf-11ef-ab68-0cc47af964e9 | Q35: 2f3364f4-226a-11ea-ab44-0cc47af964e9 | R35: 609d494f-b566-11e7-a547-f6d178db6df1 | S35: 194970a4-6577-11ed-ab59-0cc47af964e9 | T35: лист | U35: м2 | V35: fa6fadf3-b578-11e7-a547-f6d178db6df1 | W35: Склад упаковки готовой продукции (ЗСП) | X35: 12 | Y35: 17 772,00 | Z35: 48.387 | AA35: 4.083 | AB35: Слопласт | AD35: 2 962,00 | AE35: 1 481,00 | AF35: Мебель | AG35: c6d95ff4-2269-11f1-99bb-00155dde6a00 | AH35: e1cib/data/Документ.РеализацияТоваровУслуг?ref=ab6b0cc47af964e911f06857aaef353e | AI35: 400c6031-5b3e-11f0-ab6b-0cc47af964e9194970a4-6577-11ed-ab59-0cc47af964e9 | AJ35: УП-00080436
A36: ERP | B36: 45999.843 | C36: cbccf8f9-6926-11f0-ab6b-0cc47af964e9 | D36: Реализация товаров и услуг ЗСУП-002840 от 25.07.2025 10:13:03 | E36: ЗСУП-002840 | F36: 45863.426 | G36: 1 | H36: 0 | I36: Реализация | J36: null | K36: 9e38a44e-b7d0-11e7-a547-f6d178db6df1 | L36: Реализовано | M36: 05f2ed7a-4034-11ef-8110-00155d000d00 | N36: 043fe15a-a8fe-11e3-a2e4-0015171241a4 | O36: 04e19795-f36b-11e8-9fe3-d000e1470f5d | P36: f8e09145-5001-11ef-ab64-0cc47af964e9 | Q36: 0d1dd908-1fa2-11ed-ab55-0cc47af964e9 | R36: 609d494f-b566-11e7-a547-f6d178db6df1 | S36: 194970a4-6577-11ed-ab59-0cc47af964e9 | T36: лист | U36: м2 | V36: fa6fadf3-b578-11e7-a547-f6d178db6df1 | W36: Склад упаковки готовой продукции (ЗСП) | X36: 96 | Y36: 124 320,00 | Z36: 387.097 | AA36: 32.664 | AB36: Слопласт | AD36: 20 720,00 | AE36: 1 295,00 | AF36: Мебель | AG36: c6d95ff4-2269-11f1-99bb-00155dde6a00 | AH36: e1cib/data/Документ.РеализацияТоваровУслуг?ref=ab6b0cc47af964e911f06926cbccf8f9 | AI36: d5f19222-5ccd-11f0-ab6b-0cc47af964e9194970a4-6577-11ed-ab59-0cc47af964e9 | AJ36: УП-00080436
A37: ERP | B37: 45999.843 | C37: 46a58f90-7102-11f0-ab6c-0cc47af964e9 | D37: Реализация товаров и услуг ЗСУП-002990 от 04.08.2025 10:11:44 | E37: ЗСУП-002990 | F37: 45873.425 | G37: 1 | H37: 0 | I37: Реализация | J37: null | K37: 9e38a44e-b7d0-11e7-a547-f6d178db6df1 | L37: Реализовано | M37: 01d4de8c-6aaf-11ef-8110-00155d000d00 | N37: 31844b91-355e-11de-8227-0015171241a4 | O37: 107108ee-f367-11e8-9fe3-d000e1470f5d | P37: 43488cf5-8bcf-11ef-ab68-0cc47af964e9 | Q37: 2f3364f4-226a-11ea-ab44-0cc47af964e9 | R37: 609d494f-b566-11e7-a547-f6d178db6df1 | S37: 194970a4-6577-11ed-ab59-0cc47af964e9 | T37: лист | U37: м2 | V37: fa6fadf3-b578-11e7-a547-f6d178db6df1 | W37: Склад упаковки готовой продукции (ЗСП) | X37: 11 | Y37: 16 291,00 | Z37: 44.355 | AA37: 3.743 | AB37: Слопласт | AD37: 2 715,17 | AE37: 1 481,00 | AF37: Мебель | AG37: c6d95ff4-2269-11f1-99bb-00155dde6a00 | AH37: e1cib/data/Документ.РеализацияТоваровУслуг?ref=ab6c0cc47af964e911f0710246a58f90 | AI37: 1c7fb8a9-60c1-11f0-ab6b-0cc47af964e9194970a4-6577-11ed-ab59-0cc47af964e9 | AJ37: УП-00080436
A38: ERP | B38: 45999.843 | C38: e0a48fc5-7e55-11f0-99b7-00155dde6a00 | D38: Реализация товаров и услуг ЗСУП-003168 от 21.08.2025 9:12:56 | E38: ЗСУП-003168 | F38: 45890.384 | G38: 1 | H38: 0 | I38: Реализация | J38: null | K38: 9e38a44e-b7d0-11e7-a547-f6d178db6df1 | L38: Реализовано | M38: 01d4de8c-6aaf-11ef-8110-00155d000d00 | N38: 31844b91-355e-11de-8227-0015171241a4 | O38: 107108ee-f367-11e8-9fe3-d000e1470f5d | P38: 43488cf5-8bcf-11ef-ab68-0cc47af964e9 | Q38: 2f3364f4-226a-11ea-ab44-0cc47af964e9 | R38: 55c87efc-b566-11e7-a547-f6d178db6df1 | S38: 194970a4-6577-11ed-ab59-0cc47af964e9 | T38: лист | U38: м2 | V38: fa6fadf3-b578-11e7-a547-f6d178db6df1 | W38: Склад упаковки готовой продукции (ЗСП) | X38: 12 | Y38: 17 772,00 | Z38: 48.387 | AA38: 4.083 | AB38: Слопласт | AD38: 2 962,00 | AE38: 1 481,00 | AF38: Мебель | AG38: c6d95ff4-2269-11f1-99bb-00155dde6a00 | AH38: e1cib/data/Документ.РеализацияТоваровУслуг?ref=99b700155dde6a0011f07e55e0a48fc5 | AI38: 4b2f54dc-6c80-11f0-ab6b-0cc47af964e9194970a4-6577-11ed-ab59-0cc47af964e9 | AJ38: УП-00080436
A39: ERP | B39: 45999.843 | C39: 9734e891-7e5b-11f0-99b7-00155dde6a00 | D39: Реализация товаров и услуг ЗСУП-003177 от 22.08.2025 0:00:00 | E39: ЗСУП-003177 | F39: 45891 | G39: 1 | H39: 0 | I39: Реализация | J39: null | K39: 9e38a44e-b7d0-11e7-a547-f6d178db6df1 | L39: Реализовано | M39: 01d4de8c-6aaf-11ef-8110-00155d000d00 | N39: 78d73f12-f36a-11e8-9fe3-d000e1470f5d | O39: 78d73f13-f36a-11e8-9fe3-d000e1470f5d | P39: 132ad76f-5aaa-11ed-ab58-0cc47af964e9 | Q39: 8c0ae592-d13a-11ec-ab51-0cc47af964e9 | R39: 609d494f-b566-11e7-a547-f6d178db6df1 | S39: 194970a4-6577-11ed-ab59-0cc47af964e9 | T39: лист | U39: м2 | V39: fa6fadf3-b578-11e7-a547-f6d178db6df1 | W39: Склад упаковки готовой продукции (ЗСП) | X39: 60 | Y39: 88 860,00 | Z39: 241.935 | AA39: 20.415 | AB39: Слопласт | AD39: 14 810,00 | AE39: 1 481,00 | AF39: Мебель | AG39: d0bbdb8d-1fe5-11f1-99bb-00155dde6a00 | AH39: e1cib/data/Документ.РеализацияТоваровУслуг?ref=99b700155dde6a0011f07e5b9734e891 | AI39: 7355603b-6ea0-11f0-ab6c-0cc47af964e9194970a4-6577-11ed-ab59-0cc47af964e9 | AJ39: УП-00080436
A40: ERP | B40: 45999.843 | C40: 0cdf2aaf-7f21-11f0-99b7-00155dde6a00 | D40: Реализация товаров и услуг ЗСУП-003201 от 22.08.2025 9:27:22 | E40: ЗСУП-003201 | F40: 45891.394 | G40: 1 | H40: 0 | I40: Реализация | J40: null | K40: 9e38a44e-b7d0-11e7-a547-f6d178db6df1 | L40: Реализовано | M40: 05f2ed7a-4034-11ef-8110-00155d000d00 | N40: 043fe15a-a8fe-11e3-a2e4-0015171241a4 | O40: 04e19795-f36b-11e8-9fe3-d000e1470f5d | P40: f8e09145-5001-11ef-ab64-0cc47af964e9 | Q40: 0d1dd908-1fa2-11ed-ab55-0cc47af964e9 | R40: 609d494f-b566-11e7-a547-f6d178db6df1 | S40: 194970a4-6577-11ed-ab59-0cc47af964e9 | T40: лист | U40: м2 | V40: fa6fadf3-b578-11e7-a547-f6d178db6df1 | W40: Склад упаковки готовой продукции (ЗСП) | X40: 104 | Y40: 134 680,00 | Z40: 419.355 | AA40: 35.386 | AB40: Слопласт | AD40: 22 446,67 | AE40: 1 295,00 | AF40: Мебель | AG40: d0bbdb8d-1fe5-11f1-99bb-00155dde6a00 | AH40: e1cib/data/Документ.РеализацияТоваровУслуг?ref=99b700155dde6a0011f07f210cdf2aaf | AI40: 40d300f8-6ba4-11f0-ab6b-0cc47af964e9194970a4-6577-11ed-ab59-0cc47af964e9 | AJ40: УП-00080436
A41: ERP | B41: 45999.843 | C41: 3daecbdf-7f21-11f0-99b7-00155dde6a00 | D41: Реализация товаров и услуг ЗСУП-003202 от 22.08.2025 9:28:40 | E41: ЗСУП-003202 | F41: 45891.395 | G41: 1 | H41: 0 | I41: Реализация | J41: null | K41: 9e38a44e-b7d0-11e7-a547-f6d178db6df1 | L41: Реализовано | M41: 05f2ed7a-4034-11ef-8110-00155d000d00 | N41: 043fe15a-a8fe-11e3-a2e4-0015171241a4 | O41: 04e19795-f36b-11e8-9fe3-d000e1470f5d | P41: f8e09145-5001-11ef-ab64-0cc47af964e9 | Q41: 0d1dd908-1fa2-11ed-ab55-0cc47af964e9 | R41: 609d494f-b566-11e7-a547-f6d178db6df1 | S41: 194970a4-6577-11ed-ab59-0cc47af964e9 | T41: лист | U41: м2 | V41: fa6fadf3-b578-11e7-a547-f6d178db6df1 | W41: Склад упаковки готовой продукции (ЗСП) | X41: 30 | Y41: 38 850,00 | Z41: 120.968 | AA41: 10.208 | AB41: Слопласт | AD41: 6 475,00 | AE41: 1 295,00 | AF41: Мебель | AG41: d0bbdb8d-1fe5-11f1-99bb-00155dde6a00 | AH41: e1cib/data/Документ.РеализацияТоваровУслуг?ref=99b700155dde6a0011f07f213daecbdf | AI41: acfeab31-6d2a-11f0-ab6b-0cc47af964e9194970a4-6577-11ed-ab59-0cc47af964e9 | AJ41: УП-00080436
A42: ERP | B42: 45999.843 | C42: 2e3bdff3-8a23-11f0-99b7-00155dde6a00 | D42: Реализация товаров и услуг ЗСУП-003389 от 05.09.2025 9:40:17 | E42: ЗСУП-003389 | F42: 45905.403 | G42: 1 | H42: 0 | I42: Реализация | J42: null | K42: 9e38a44e-b7d0-11e7-a547-f6d178db6df1 | L42: Реализовано | M42: 05f2ed7a-4034-11ef-8110-00155d000d00 | N42: 043fe15a-a8fe-11e3-a2e4-0015171241a4 | O42: 04e19795-f36b-11e8-9fe3-d000e1470f5d | P42: f8e09145-5001-11ef-ab64-0cc47af964e9 | Q42: 0d1dd908-1fa2-11ed-ab55-0cc47af964e9 | R42: 609d494f-b566-11e7-a547-f6d178db6df1 | S42: 194970a4-6577-11ed-ab59-0cc47af964e9 | T42: лист | U42: м2 | V42: fa6fadf3-b578-11e7-a547-f6d178db6df1 | W42: Склад упаковки готовой продукции (ЗСП) | X42: 46 | Y42: 59 570,00 | Z42: 185.484 | AA42: 15.652 | AB42: Слопласт | AD42: 9 928,33 | AE42: 1 295,00 | AF42: Мебель | AG42: d0bbdb8d-1fe5-11f1-99bb-00155dde6a00 | AH42: e1cib/data/Документ.РеализацияТоваровУслуг?ref=99b700155dde6a0011f08a232e3bdff3 | AI42: 40d300f8-6ba4-11f0-ab6b-0cc47af964e9194970a4-6577-11ed-ab59-0cc47af964e9 | AJ42: УП-00080436
A43: ERP | B43: 45999.843 | C43: 04019bca-8fac-11f0-99b7-00155dde6a00 | D43: Реализация товаров и услуг ЗСУП-003423 от 12.09.2025 10:42:22 | E43: ЗСУП-003423 | F43: 45912.446 | G43: 1 | H43: 0 | I43: Реализация | J43: null | K43: 9e38a44e-b7d0-11e7-a547-f6d178db6df1 | L43: Реализовано | M43: 01d4de8c-6aaf-11ef-8110-00155d000d00 | N43: e534587a-e964-11e7-80e4-00155d000d00 | O43: ada5d5f6-f367-11e8-9fe3-d000e1470f5d | P43: d79896b0-11a7-11ed-ab55-0cc47af964e9 | Q43: 4bba30ca-29d6-11ed-ab55-0cc47af964e9 | R43: 609d494f-b566-11e7-a547-f6d178db6df1 | S43: 194970a4-6577-11ed-ab59-0cc47af964e9 | T43: лист | U43: м2 | V43: fa6fadf3-b578-11e7-a547-f6d178db6df1 | W43: Склад упаковки готовой продукции (ЗСП) | X43: 24 | Y43: 33 768,00 | Z43: 96.774 | AA43: 8.166 | AB43: Слопласт | AD43: 5 628,00 | AE43: 1 407,00 | AF43: Мебель | AG43: d0bbdb8d-1fe5-11f1-99bb-00155dde6a00 | AH43: e1cib/data/Документ.РеализацияТоваровУслуг?ref=99b700155dde6a0011f08fac04019bca | AI43: afffc6ca-84b4-11f0-99b7-00155dde6a00194970a4-6577-11ed-ab59-0cc47af964e9 | AJ43: УП-00080436
... A48: ERP | B48: 45999.843 | C48: 73f06c0d-9911-11f0-99b7-00155dde6a00 | D48: Реализация товаров и услуг ЗСУП-003555 от 24.09.2025 9:41:10 | E48: ЗСУП-003555 | F48: 45924.404 | G48: 1 | H48: 0 | I48: Реализация | J48: null | K48: 9e38a44e-b7d0-11e7-a547-f6d178db6df1 | L48: Реализовано | M48: 01d4de8c-6aaf-11ef-8110-00155d000d00 | N48: 78d73f12-f36a-11e8-9fe3-d000e1470f5d | O48: 78d73f13-f36a-11e8-9fe3-d000e1470f5d | P48: 132ad76f-5aaa-11ed-ab58-0cc47af964e9 | Q48: 8c0ae592-d13a-11ec-ab51-0cc47af964e9 | R48: 609d494f-b566-11e7-a547-f6d178db6df1 | S48: 194970a4-6577-11ed-ab59-0cc47af964e9 | T48: лист | U48: м2 | V48: fa6fadf3-b578-11e7-a547-f6d178db6df1 | W48: Склад упаковки готовой продукции (ЗСП) | X48: 10 | Y48: 14 810,00 | Z48: 40.323 | AA48: 3.403 | AB48: Слопласт | AD48: 2 468,33 | AE48: 1 481,00 | AF48: Мебель | AG48: 3a7e6a32-1f4f-11f1-99bb-00155dde6a00 | AH48: e1cib/data/Документ.РеализацияТоваровУслуг?ref=99b700155dde6a0011f0991173f06c0d | AI48: 7355603b-6ea0-11f0-ab6c-0cc47af964e9194970a4-6577-11ed-ab59-0cc47af964e9 | AJ48: УП-00080436
A49: ERP | B49: 45999.843 | C49: c003ff3b-9cfe-11f0-99b7-00155dde6a00 | D49: Реализация товаров и услуг ЗСУП-003629 от 29.09.2025 9:37:21 | E49: ЗСУП-003629 | F49: 45929.401 | G49: 1 | H49: 0 | I49: Реализация | J49: null | K49: 9e38a44e-b7d0-11e7-a547-f6d178db6df1 | L49: Реализовано | M49: 05f2ed7a-4034-11ef-8110-00155d000d00 | N49: fc4ae344-ad9b-11eb-ab4c-0cc47af964e9 | O49: fc4ae347-ad9b-11eb-ab4c-0cc47af964e9 | P49: aee0dded-e7be-11ef-ab6a-0cc47af964e9 | Q49: 54206bf8-fefd-11ea-ab46-0cc47af964e9 | R49: 55c87efc-b566-11e7-a547-f6d178db6df1 | S49: 194970a4-6577-11ed-ab59-0cc47af964e9 | T49: лист | U49: м2 | V49: fa6fadf3-b578-11e7-a547-f6d178db6df1 | W49: Склад упаковки готовой продукции (ЗСП) | X49: 12 | Y49: 14 820,00 | Z49: 48.387 | AA49: 4.083 | AB49: Слопласт | AD49: 0 | AE49: 1 235,00 | AF49: Мебель | AG49: 3a7e6a32-1f4f-11f1-99bb-00155dde6a00 | AH49: e1cib/data/Документ.РеализацияТоваровУслуг?ref=99b700155dde6a0011f09cfec003ff3b | AI49: 0544f2f0-78e8-11f0-99b7-00155dde6a00194970a4-6577-11ed-ab59-0cc47af964e9 | AJ49: УП-00080436
A50: ERP | B50: 45999.843 | C50: a70c0d36-a5ab-11f0-99b7-00155dde6a00 | D50: Реализация товаров и услуг ЗСУП-003867 от 10.10.2025 10:35:11 | E50: ЗСУП-003867 | F50: 45940.441 | G50: 1 | H50: 0 | I50: Реализация | J50: null | K50: 9e38a44e-b7d0-11e7-a547-f6d178db6df1 | L50: Реализовано | M50: 01d4de8c-6aaf-11ef-8110-00155d000d00 | N50: e534587a-e964-11e7-80e4-00155d000d00 | O50: ada5d5f6-f367-11e8-9fe3-d000e1470f5d | P50: d79896b0-11a7-11ed-ab55-0cc47af964e9 | Q50: 4bba30ca-29d6-11ed-ab55-0cc47af964e9 | R50: 609d494f-b566-11e7-a547-f6d178db6df1 | S50: 194970a4-6577-11ed-ab59-0cc47af964e9 | T50: лист | U50: м2 | V50: fa6fadf3-b578-11e7-a547-f6d178db6df1 | W50: Склад упаковки готовой продукции (ЗСП) | X50: 24 | Y50: 33 768,00 | Z50: 96.774 | AA50: 8.166 | AB50: Слопласт | AC50: Дилер_РФ | AD50: 5 628,00 | AE50: 1 407,00 | AF50: Мебель | AG50: 3a7e6a32-1f4f-11f1-99bb-00155dde6a00 | AH50: e1cib/data/Документ.РеализацияТоваровУслуг?ref=99b700155dde6a0011f0a5aba70c0d36 | AI50: 8b7e2c29-8fe7-11f0-99b7-00155dde6a00194970a4-6577-11ed-ab59-0cc47af964e9 | AJ50: УП-00080436
A51: ERP | B51: 45999.843 | C51: 971e93f6-a5ad-11f0-99b7-00155dde6a00 | D51: Реализация товаров и услуг ЗСУП-003869 от 10.10.2025 10:49:10 | E51: ЗСУП-003869 | F51: 45940.451 | G51: 1 | H51: 0 | I51: Реализация | J51: null | K51: 9e38a44e-b7d0-11e7-a547-f6d178db6df1 | L51: Реализовано | M51: 01d4de8c-6aaf-11ef-8110-00155d000d00 | N51: e534587a-e964-11e7-80e4-00155d000d00 | O51: ada5d5f6-f367-11e8-9fe3-d000e1470f5d | P51: d79896b0-11a7-11ed-ab55-0cc47af964e9 | Q51: 4bba30ca-29d6-11ed-ab55-0cc47af964e9 | R51: 609d494f-b566-11e7-a547-f6d178db6df1 | S51: 194970a4-6577-11ed-ab59-0cc47af964e9 | T51: лист | U51: м2 | V51: fa6fadf3-b578-11e7-a547-f6d178db6df1 | W51: Склад упаковки готовой продукции (ЗСП) | X51: 12 | Y51: 16 884,00 | Z51: 48.387 | AA51: 4.083 | AB51: Слопласт | AC51: Дилер_РФ | AD51: 2 814,00 | AE51: 1 407,00 | AF51: Мебель | AG51: 3a7e6a32-1f4f-11f1-99bb-00155dde6a00 | AH51: e1cib/data/Документ.РеализацияТоваровУслуг?ref=99b700155dde6a0011f0a5ad971e93f6 | AI51: 34507be7-949a-11f0-99b7-00155dde6a00194970a4-6577-11ed-ab59-0cc47af964e9 | AJ51: УП-00080436
A52: ERP | B52: 45999.843 | C52: b2d7265d-a5ae-11f0-99b7-00155dde6a00 | D52: Реализация товаров и услуг ЗСУП-003873 от 10.10.2025 10:57:07 | E52: ЗСУП-003873 | F52: 45940.456 | G52: 1 | H52: 0 | I52: Реализация | J52: null | K52: 9e38a44e-b7d0-11e7-a547-f6d178db6df1 | L52: Реализовано | M52: 01d4de8c-6aaf-11ef-8110-00155d000d00 | N52: e534587a-e964-11e7-80e4-00155d000d00 | O52: ada5d5f6-f367-11e8-9fe3-d000e1470f5d | P52: d79896b0-11a7-11ed-ab55-0cc47af964e9 | Q52: 4bba30ca-29d6-11ed-ab55-0cc47af964e9 | R52: 609d494f-b566-11e7-a547-f6d178db6df1 | S52: 194970a4-6577-11ed-ab59-0cc47af964e9 | T52: лист | U52: м2 | V52: fa6fadf3-b578-11e7-a547-f6d178db6df1 | W52: Склад упаковки готовой продукции (ЗСП) | X52: 36 | Y52: 50 652,00 | Z52: 145.161 | AA52: 12.249 | AB52: Слопласт | AC52: Дилер_РФ | AD52: 8 442,00 | AE52: 1 407,00 | AF52: Мебель | AG52: 3a7e6a32-1f4f-11f1-99bb-00155dde6a00 | AH52: e1cib/data/Документ.РеализацияТоваровУслуг?ref=99b700155dde6a0011f0a5aeb2d7265d | AI52: e3e79d75-a389-11f0-99b7-00155dde6a00194970a4-6577-11ed-ab59-0cc47af964e9 | AJ52: УП-00080436
A53: ERP | B53: 45999.843 | C53: cfd48840-c38b-11f0-99b9-00155dde6a00 | D53: Реализация товаров и услуг ЗСУП-004544 от 17.11.2025 11:02:55 | E53: ЗСУП-004544 | F53: 45978.46 | G53: 1 | H53: 0 | I53: Реализация | J53: null | K53: 9e38a44e-b7d0-11e7-a547-f6d178db6df1 | L53: Реализовано | M53: 01d4de8c-6aaf-11ef-8110-00155d000d00 | N53: e534587a-e964-11e7-80e4-00155d000d00 | O53: ada5d5f6-f367-11e8-9fe3-d000e1470f5d | P53: d79896b0-11a7-11ed-ab55-0cc47af964e9 | Q53: 4bba30ca-29d6-11ed-ab55-0cc47af964e9 | R53: 609d494f-b566-11e7-a547-f6d178db6df1 | S53: 194970a4-6577-11ed-ab59-0cc47af964e9 | T53: лист | U53: м2 | V53: fa6fadf3-b578-11e7-a547-f6d178db6df1 | W53: Склад упаковки готовой продукции (ЗСП) | X53: 24 | Y53: 33 768,00 | Z53: 96.774 | AA53: 8.166 | AB53: Слопласт | AC53: Дилер_РФ | AD53: 5 628,00 | AE53: 1 407,00 | AF53: Мебель | AG53: 14fdc30b-1d31-11f1-99bb-00155dde6a00 | AH53: e1cib/data/Документ.РеализацияТоваровУслуг?ref=99b900155dde6a0011f0c38bcfd48840 | AI53: 6ff6e5cb-b71c-11f0-99b8-00155dde6a00194970a4-6577-11ed-ab59-0cc47af964e9 | AJ53: УП-00080436
A54: ERP | B54: 45999.843 | C54: 13d8000a-c551-11f0-99b9-00155dde6a00 | D54: Реализация товаров и услуг ЗСУП-004613 от 21.11.2025 0:00:00 | E54: ЗСУП-004613 | F54: 45982 | G54: 1 | H54: 0 | I54: Реализация | J54: null | K54: 9e38a44e-b7d0-11e7-a547-f6d178db6df1 | L54: Реализовано | M54: 05f2ed7a-4034-11ef-8110-00155d000d00 | N54: 043fe15a-a8fe-11e3-a2e4-0015171241a4 | O54: 04e19795-f36b-11e8-9fe3-d000e1470f5d | P54: f8e09145-5001-11ef-ab64-0cc47af964e9 | Q54: 0d1dd908-1fa2-11ed-ab55-0cc47af964e9 | R54: 609d494f-b566-11e7-a547-f6d178db6df1 | S54: 194970a4-6577-11ed-ab59-0cc47af964e9 | T54: лист | U54: м2 | V54: fa6fadf3-b578-11e7-a547-f6d178db6df1 | W54: Склад упаковки готовой продукции (ЗСП) | X54: 4 | Y54: 5 180,00 | Z54: 16.129 | AA54: 1.361 | AB54: Слопласт | AD54: 863.33 | AE54: 1 295,00 | AF54: Мебель | AG54: 14fdc30b-1d31-11f1-99bb-00155dde6a00 | AH54: e1cib/data/Документ.РеализацияТоваровУслуг?ref=99b900155dde6a0011f0c55113d8000a | AI54: d5f19222-5ccd-11f0-ab6b-0cc47af964e9194970a4-6577-11ed-ab59-0cc47af964e9 | AJ54: УП-00080436
A55: ERP | B55: 45999.843 | C55: d7331df5-ca01-11f0-99b9-00155dde6a00 | D55: Реализация товаров и услуг ЗСУП-004717 от 25.11.2025 16:22:56 | E55: ЗСУП-004717 | F55: 45986.683 | G55: 1 | H55: 0 | I55: Реализация | J55: null | K55: 9e38a44e-b7d0-11e7-a547-f6d178db6df1 | L55: Реализовано | M55: 05f2ed7a-4034-11ef-8110-00155d000d00 | N55: 3fa69b08-b7a5-11e2-ae63-0015171241a4 | O55: 35ad1025-f36b-11e8-9fe3-d000e1470f5d | P55: 98eb8223-4986-11ef-ab64-0cc47af964e9 | Q55: 52094fa9-769a-11eb-ab4c-0cc47af964e9 | R55: 55c87efc-b566-11e7-a547-f6d178db6df1 | S55: 194970a4-6577-11ed-ab59-0cc47af964e9 | T55: лист | U55: м2 | V55: fa6fadf3-b578-11e7-a547-f6d178db6df1 | W55: Склад упаковки готовой продукции (ЗСП) | X55: 12 | Y55: 17 772,00 | Z55: 48.387 | AA55: 4.083 | AB55: Слопласт | AC55: С4 | AD55: 2 962,00 | AE55: 1 481,00 | AF55: Мебель | AG55: 14fdc30b-1d31-11f1-99bb-00155dde6a00 | AH55: e1cib/data/Документ.РеализацияТоваровУслуг?ref=99b900155dde6a0011f0ca01d7331df5 | AI55: b66fb43c-bf01-11f0-99b9-00155dde6a00194970a4-6577-11ed-ab59-0cc47af964e9 | AJ55: УП-00080436
A56: ERP | B56: 45999.843 | C56: ade4104a-cb82-11f0-99b9-00155dde6a00 | D56: Реализация товаров и услуг ЗСУП-004759 от 27.11.2025 14:17:38 | E56: ЗСУП-004759 | F56: 45988.596 | G56: 1 | H56: 0 | I56: Реализация | J56: null | K56: 9e38a44e-b7d0-11e7-a547-f6d178db6df1 | L56: Реализовано | M56: ca842095-b338-11e8-80e7-00155d000d00 | N56: 78d73f12-f36a-11e8-9fe3-d000e1470f5d | O56: 78d73f13-f36a-11e8-9fe3-d000e1470f5d | P56: 071e6556-c5f7-11f0-99b9-00155dde6a00 | Q56: 8c0ae592-d13a-11ec-ab51-0cc47af964e9 | R56: 609d494f-b566-11e7-a547-f6d178db6df1 | S56: 194970a4-6577-11ed-ab59-0cc47af964e9 | T56: лист | U56: м2 | V56: fa6fadf3-b578-11e7-a547-f6d178db6df1 | W56: Склад упаковки готовой продукции (ЗСП) | X56: 69 | Y56: 102 189,00 | Z56: 278.226 | AA56: 23.477 | AB56: Слопласт | AC56: С4 | AD56: 17 031,50 | AE56: 1 481,00 | AF56: Мебель | AG56: 14fdc30b-1d31-11f1-99bb-00155dde6a00 | AH56: e1cib/data/Документ.РеализацияТоваровУслуг?ref=99b900155dde6a0011f0cb82ade4104a | AI56: bf6b651c-c47f-11f0-99b9-00155dde6a00194970a4-6577-11ed-ab59-0cc47af964e9 | AJ56: УП-00080436
A57: ERP | B57: 45999.843 | C57: 02bd606e-cc4e-11f0-99b9-00155dde6a00 | D57: Реализация товаров и услуг ЗСУП-004810 от 28.11.2025 14:33:08 | E57: ЗСУП-004810 | F57: 45989.606 | G57: 1 | H57: 0 | I57: Реализация | J57: null | K57: 9e38a44e-b7d0-11e7-a547-f6d178db6df1 | L57: Реализовано | M57: 05f2ed7a-4034-11ef-8110-00155d000d00 | N57: 043fe15a-a8fe-11e3-a2e4-0015171241a4 | O57: 04e19795-f36b-11e8-9fe3-d000e1470f5d | P57: f8e09145-5001-11ef-ab64-0cc47af964e9 | Q57: 0d1dd908-1fa2-11ed-ab55-0cc47af964e9 | R57: 609d494f-b566-11e7-a547-f6d178db6df1 | S57: 194970a4-6577-11ed-ab59-0cc47af964e9 | T57: лист | U57: м2 | V57: fa6fadf3-b578-11e7-a547-f6d178db6df1 | W57: Склад упаковки готовой продукции (ЗСП) | X57: 120 | Y57: 155 400,00 | Z57: 483.871 | AA57: 40.83 | AB57: Слопласт | AD57: 25 900,00 | AE57: 1 295,00 | AF57: Мебель | AG57: 14fdc30b-1d31-11f1-99bb-00155dde6a00 | AH57: e1cib/data/Документ.РеализацияТоваровУслуг?ref=99b900155dde6a0011f0cc4e02bd606e | AI57: acfeab31-6d2a-11f0-ab6b-0cc47af964e9194970a4-6577-11ed-ab59-0cc47af964e9 | AJ57: УП-00080436
A58: ERP | B58: 45999.843 | C58: 75bd8135-cc50-11f0-99b9-00155dde6a00 | D58: Реализация товаров и услуг ЗСУП-004812 от 28.11.2025 14:50:48 | E58: ЗСУП-004812 | F58: 45989.619 | G58: 1 | H58: 0 | I58: Реализация | J58: null | K58: 9e38a44e-b7d0-11e7-a547-f6d178db6df1 | L58: Реализовано | M58: 01d4de8c-6aaf-11ef-8110-00155d000d00 | N58: 31844b91-355e-11de-8227-0015171241a4 | O58: 107108ee-f367-11e8-9fe3-d000e1470f5d | P58: 43488cf5-8bcf-11ef-ab68-0cc47af964e9 | Q58: 2f3364f4-226a-11ea-ab44-0cc47af964e9 | R58: 609d494f-b566-11e7-a547-f6d178db6df1 | S58: 194970a4-6577-11ed-ab59-0cc47af964e9 | T58: лист | U58: м2 | V58: fa6fadf3-b578-11e7-a547-f6d178db6df1 | W58: Склад упаковки готовой продукции (ЗСП) | X58: 12 | Y58: 17 772,00 | Z58: 48.387 | AA58: 4.083 | AB58: Слопласт | AC58: С4 | AD58: 2 962,00 | AE58: 1 481,00 | AF58: Мебель | AG58: 14fdc30b-1d31-11f1-99bb-00155dde6a00 | AH58: e1cib/data/Документ.РеализацияТоваровУслуг?ref=99b900155dde6a0011f0cc5075bd8135 | AI58: 317ae1f0-9d02-11f0-99b7-00155dde6a00194970a4-6577-11ed-ab59-0cc47af964e9 | AJ58: УП-00080436
A59: ERP | B59: 46066.481 | C59: 80526e22-08a7-11f1-99b9-00155dde6a00 | D59: Реализация товаров и услуг ЗСУП-000370 от 13.02.2026 9:45:03 | E59: ЗСУП-000370 | F59: 46066.406 | G59: 1 | H59: 0 | I59: Реализация | J59: null | K59: 9e38a44e-b7d0-11e7-a547-f6d178db6df1 | L59: Реализовано | M59: 05f2ed7a-4034-11ef-8110-00155d000d00 | N59: 043fe15a-a8fe-11e3-a2e4-0015171241a4 | O59: 04e19795-f36b-11e8-9fe3-d000e1470f5d | P59: f8e09145-5001-11ef-ab64-0cc47af964e9 | Q59: 0d1dd908-1fa2-11ed-ab55-0cc47af964e9 | R59: 609d494f-b566-11e7-a547-f6d178db6df1 | S59: 194970a4-6577-11ed-ab59-0cc47af964e9 | T59: лист | U59: м2 | V59: fa6fadf3-b578-11e7-a547-f6d178db6df1 | W59: Склад упаковки готовой продукции (ЗСП) | X59: 113 | Y59: 148 821,00 | Z59: 455.645 | AA59: 38.448 | AB59: Слопласт | AD59: 26 836,58 | AE59: 1 317,00 | AF59: Мебель | AG59: 14fdc30b-1d31-11f1-99bb-00155dde6a00 | AH59: e1cib/data/Документ.РеализацияТоваровУслуг?ref=99b900155dde6a0011f108a780526e22 | AI59: 81ad9454-0009-11f1-99b9-00155dde6a00194970a4-6577-11ed-ab59-0cc47af964e9 | AJ59: УП-00080436
A60: ERP | B60: 46000.64 | C60: 5295f40a-d4f8-11f0-99b9-00155dde6a00 | D60: Реализация товаров и услуг ЗСУП-004962 от 09.12.2025 15:12:27 | E60: ЗСУП-004962 | F60: 46000.634 | G60: 1 | H60: 0 | I60: Реализация | J60: null | K60: 9e38a44e-b7d0-11e7-a547-f6d178db6df1 | L60: Реализовано | M60: 01d4de8c-6aaf-11ef-8110-00155d000d00 | N60: 9a673e3c-e968-11e7-80e4-00155d000d00 | O60: 63c14d00-f368-11e8-9fe3-d000e1470f5d | P60: e75a859d-7b4c-11ef-ab68-0cc47af964e9 | Q60: 7fe1a657-2268-11ea-ab44-0cc47af964e9 | R60: 609d494f-b566-11e7-a547-f6d178db6df1 | S60: 0893a63f-048c-11ef-ab64-0cc47af964e9 | T60: лист | U60: м2 | V60: fa6fadf3-b578-11e7-a547-f6d178db6df1 | W60: Склад упаковки готовой продукции (ЗСП) | X60: 11 | Y60: 16 819,00 | Z60: 44.355 | AA60: 3.743 | AB60: Слопласт | AD60: 2 803,17 | AE60: 1 529,00 | AF60: Мебель | AG60: d30b1e43-164d-11f1-99b9-00155dde6a00 | AH60: e1cib/data/Документ.РеализацияТоваровУслуг?ref=99b900155dde6a0011f0d4f85295f40a | AI60: 97446354-c919-11f0-99b9-00155dde6a000893a63f-048c-11ef-ab64-0cc47af964e9 | AJ60: УП-00099753
A61: ERP | B61: 46010.537 | C61: 882e8e68-dcb0-11f0-99b9-00155dde6a00 | D61: Реализация товаров и услуг ЗСУП-005148 от 19.12.2025 10:58:46 | E61: ЗСУП-005148 | F61: 46010.457 | G61: 1 | H61: 0 | I61: Реализация | J61: null | K61: 9e38a44e-b7d0-11e7-a547-f6d178db6df1 | L61: Реализовано | M61: 01d4de8c-6aaf-11ef-8110-00155d000d00 | N61: e534587a-e964-11e7-80e4-00155d000d00 | O61: ada5d5f6-f367-11e8-9fe3-d000e1470f5d | P61: d79896b0-11a7-11ed-ab55-0cc47af964e9 | Q61: 4bba30ca-29d6-11ed-ab55-0cc47af964e9 | R61: 609d494f-b566-11e7-a547-f6d178db6df1 | S61: 0893a63f-048c-11ef-ab64-0cc47af964e9 | T61: лист | U61: м2 | V61: fa6fadf3-b578-11e7-a547-f6d178db6df1 | W61: Склад упаковки готовой продукции (ЗСП) | X61: 23 | Y61: 32 200,00 | Z61: 92.742 | AA61: 7.826 | AB61: Слопласт | AD61: 5 366,67 | AE61: 1 400,00 | AF61: Мебель | AG61: d30b1e43-164d-11f1-99b9-00155dde6a00 | AH61: e1cib/data/Документ.РеализацияТоваровУслуг?ref=99b900155dde6a0011f0dcb0882e8e68 | AI61: e5cd9aca-cf8e-11f0-99b9-00155dde6a000893a63f-048c-11ef-ab64-0cc47af964e9 | AJ61: УП-00099753
A62: ERP | B62: 46015.413 | C62: fb08c21e-df2f-11f0-99b9-00155dde6a00 | D62: Реализация товаров и услуг ЗСУП-005212 от 24.12.2025 0:00:00 | E62: ЗСУП-005212 | F62: 46015 | G62: 1 | H62: 0 | I62: Реализация | J62: null | K62: 9e38a44e-b7d0-11e7-a547-f6d178db6df1 | L62: Реализовано | M62: 01d4de8c-6aaf-11ef-8110-00155d000d00 | N62: e057ce73-f36b-11e8-9fe3-d000e1470f5d | O62: e057ce74-f36b-11e8-9fe3-d000e1470f5d | P62: d3fb935e-45ec-11f0-ab6b-0cc47af964e9 | Q62: 4850fc4c-226d-11ea-ab44-0cc47af964e9 | R62: 55c87efc-b566-11e7-a547-f6d178db6df1 | S62: 0893a63f-048c-11ef-ab64-0cc47af964e9 | T62: лист | U62: м2 | V62: fa6fadf3-b578-11e7-a547-f6d178db6df1 | W62: Склад упаковки готовой продукции (ЗСП) | X62: 24 | Y62: 43 008,00 | Z62: 96.774 | AA62: 8.166 | AB62: Слопласт | AC62: С3 | AD62: 7 168,00 | AE62: 1 792,00 | AF62: Мебель | AG62: d30b1e43-164d-11f1-99b9-00155dde6a00 | AH62: e1cib/data/Документ.РеализацияТоваровУслуг?ref=99b900155dde6a0011f0df2ffb08c21e | AI62: 0d31837c-c9e4-11f0-99b9-00155dde6a000893a63f-048c-11ef-ab64-0cc47af964e9 | AJ62: УП-00099753
A63: ERP | B63: 46038.47 | C63: 5dc8e724-e562-11f0-99b9-00155dde6a00 | D63: Реализация товаров и услуг ЗСУП-005357 от 30.12.2025 12:31:59 | E63: ЗСУП-005357 | F63: 46021.522 | G63: 1 | H63: 0 | I63: Реализация | J63: null | K63: 9e38a44e-b7d0-11e7-a547-f6d178db6df1 | L63: Реализовано | M63: 01d4de8c-6aaf-11ef-8110-00155d000d00 | N63: e534587a-e964-11e7-80e4-00155d000d00 | O63: ada5d5f6-f367-11e8-9fe3-d000e1470f5d | P63: d79896b0-11a7-11ed-ab55-0cc47af964e9 | Q63: 4bba30ca-29d6-11ed-ab55-0cc47af964e9 | R63: 609d494f-b566-11e7-a547-f6d178db6df1 | S63: 0893a63f-048c-11ef-ab64-0cc47af964e9 | T63: лист | U63: м2 | V63: fa6fadf3-b578-11e7-a547-f6d178db6df1 | W63: Склад упаковки готовой продукции (ЗСП) | X63: 22 | Y63: 30 800,00 | Z63: 88.71 | AA63: 7.486 | AB63: Слопласт | AD63: 5 133,33 | AE63: 1 400,00 | AF63: Мебель | AG63: d30b1e43-164d-11f1-99b9-00155dde6a00 | AH63: e1cib/data/Документ.РеализацияТоваровУслуг?ref=99b900155dde6a0011f0e5625dc8e724 | AI63: 321e5a0f-d697-11f0-99b9-00155dde6a000893a63f-048c-11ef-ab64-0cc47af964e9 | AJ63: УП-00099753
A64: ERP | B64: 46034.549 | C64: eaaf3f59-e571-11f0-99b9-00155dde6a00 | D64: Реализация товаров и услуг ЗСУП-005369 от 30.12.2025 14:23:12 | E64: ЗСУП-005369 | F64: 46021.599 | G64: 1 | H64: 0 | I64: Реализация | J64: null | K64: 9e38a44e-b7d0-11e7-a547-f6d178db6df1 | L64: Реализовано | M64: 05f2ed7a-4034-11ef-8110-00155d000d00 | N64: 3fa69b08-b7a5-11e2-ae63-0015171241a4 | O64: 35ad1025-f36b-11e8-9fe3-d000e1470f5d | P64: 98eb8223-4986-11ef-ab64-0cc47af964e9 | Q64: 52094fa9-769a-11eb-ab4c-0cc47af964e9 | R64: 55c87efc-b566-11e7-a547-f6d178db6df1 | S64: 0893a63f-048c-11ef-ab64-0cc47af964e9 | T64: лист | U64: м2 | V64: fa6fadf3-b578-11e7-a547-f6d178db6df1 | W64: Склад упаковки готовой продукции (ЗСП) | X64: 119 | Y64: 181 832,00 | Z64: 479.839 | AA64: 40.49 | AB64: Слопласт | AC64: С4 | AD64: 30 305,33 | AE64: 1 528,00 | AF64: Мебель | AG64: d30b1e43-164d-11f1-99b9-00155dde6a00 | AH64: e1cib/data/Документ.РеализацияТоваровУслуг?ref=99b900155dde6a0011f0e571eaaf3f59 | AI64: 7868bf60-dc21-11f0-99b9-00155dde6a000893a63f-048c-11ef-ab64-0cc47af964e9 | AJ64: УП-00099753
A65: ERP | B65: 45999.843 | C65: 4fb3bebb-ce7c-11ef-ab69-0cc47af964e9 | D65: Реализация товаров и услуг ЗСУП-000005 от 09.01.2025 14:24:38 | E65: ЗСУП-000005 | F65: 45666.6 | G65: 1 | H65: 0 | I65: Реализация | J65: null | K65: 9e38a44e-b7d0-11e7-a547-f6d178db6df1 | L65: Реализовано | M65: f422c0a3-be06-11e6-80dc-00155d000d00 | N65: 043fe15a-a8fe-11e3-a2e4-0015171241a4 | O65: 04e19795-f36b-11e8-9fe3-d000e1470f5d | P65: 144db961-4be7-11ef-ab64-0cc47af964e9 | Q65: 0d1dd908-1fa2-11ed-ab55-0cc47af964e9 | R65: 609d494f-b566-11e7-a547-f6d178db6df1 | S65: 0893a63f-048c-11ef-ab64-0cc47af964e9 | T65: лист | U65: м2 | V65: fa6fadf3-b578-11e7-a547-f6d178db6df1 | W65: Склад упаковки готовой продукции (ЗСП) | X65: 22 | Y65: 33 616,00 | Z65: 88.71 | AA65: 7.486 | AB65: Слопласт | AD65: 5 602,67 | AE65: 1 528,00 | AF65: Мебель | AG65: d30b1e43-164d-11f1-99b9-00155dde6a00 | AH65: e1cib/data/Документ.РеализацияТоваровУслуг?ref=ab690cc47af964e911efce7c4fb3bebb | AI65: 0904f735-b313-11ef-ab69-0cc47af964e90893a63f-048c-11ef-ab64-0cc47af964e9 | AJ65: УП-00099753
A66: ERP | B66: 45999.843 | C66: 235b6a6e-d1a2-11ef-ab69-0cc47af964e9 | D66: Реализация товаров и услуг ЗСУП-000049 от 13.01.2025 14:33:07 | E66: ЗСУП-000049 | F66: 45670.606 | G66: 1 | H66: 0 | I66: Реализация | J66: null | K66: 9e38a44e-b7d0-11e7-a547-f6d178db6df1 | L66: Реализовано | M66: f422c0a3-be06-11e6-80dc-00155d000d00 | N66: 9a673e3c-e968-11e7-80e4-00155d000d00 | O66: 63c14d00-f368-11e8-9fe3-d000e1470f5d | P66: e75a859d-7b4c-11ef-ab68-0cc47af964e9 | Q66: 7fe1a657-2268-11ea-ab44-0cc47af964e9 | R66: 609d494f-b566-11e7-a547-f6d178db6df1 | S66: 0893a63f-048c-11ef-ab64-0cc47af964e9 | T66: лист | U66: м2 | V66: fa6fadf3-b578-11e7-a547-f6d178db6df1 | W66: Склад упаковки готовой продукции (ЗСП) | X66: 22 | Y66: 33 616,00 | Z66: 88.71 | AA66: 7.486 | AB66: Слопласт | AD66: 5 602,67 | AE66: 1 528,00 | AF66: Мебель | AG66: d30b1e43-164d-11f1-99b9-00155dde6a00 | AH66: e1cib/data/Документ.РеализацияТоваровУслуг?ref=ab690cc47af964e911efd1a2235b6a6e | AI66: 39698272-bc4d-11ef-ab69-0cc47af964e90893a63f-048c-11ef-ab64-0cc47af964e9 | AJ66: УП-00099753
A67: ERP | B67: 45999.843 | C67: 583e1542-d414-11ef-ab69-0cc47af964e9 | D67: Реализация товаров и услуг ЗСУП-000137 от 16.01.2025 17:15:35 | E67: ЗСУП-000137 | F67: 45673.719 | G67: 1 | H67: 0 | I67: Реализация | J67: null | K67: 9e38a44e-b7d0-11e7-a547-f6d178db6df1 | L67: Реализовано | M67: bd5b30ac-573c-11eb-ab4b-0cc47af964e9 | N67: e534587a-e964-11e7-80e4-00155d000d00 | O67: ada5d5f6-f367-11e8-9fe3-d000e1470f5d | P67: d79896b0-11a7-11ed-ab55-0cc47af964e9 | Q67: 4bba30ca-29d6-11ed-ab55-0cc47af964e9 | R67: 609d494f-b566-11e7-a547-f6d178db6df1 | S67: 0893a63f-048c-11ef-ab64-0cc47af964e9 | T67: лист | U67: м2 | V67: fa6fadf3-b578-11e7-a547-f6d178db6df1 | W67: Склад упаковки готовой продукции (ЗСП) | X67: 36 | Y67: 52 272,00 | Z67: 145.161 | AA67: 12.249 | AB67: Слопласт | AD67: 8 712,00 | AE67: 1 452,00 | AF67: Мебель | AG67: d30b1e43-164d-11f1-99b9-00155dde6a00 | AH67: e1cib/data/Документ.РеализацияТоваровУслуг?ref=ab690cc47af964e911efd414583e1542 | AI67: e33e33f3-ad8f-11ef-ab69-0cc47af964e90893a63f-048c-11ef-ab64-0cc47af964e9 | AJ67: УП-00099753
A68: ERP | B68: 45999.843 | C68: 5528c09f-da2f-11ef-ab69-0cc47af964e9 | D68: Реализация товаров и услуг ЗСУП-000322 от 24.01.2025 11:43:52 | E68: ЗСУП-000322 | F68: 45681.489 | G68: 1 | H68: 0 | I68: Реализация | J68: null | K68: 9e38a44e-b7d0-11e7-a547-f6d178db6df1 | L68: Реализовано | M68: bafef812-be80-11ee-ab64-0cc47af964e9 | N68: 3fa69b08-b7a5-11e2-ae63-0015171241a4 | O68: 35ad1025-f36b-11e8-9fe3-d000e1470f5d | P68: 98eb8223-4986-11ef-ab64-0cc47af964e9 | Q68: 52094fa9-769a-11eb-ab4c-0cc47af964e9 | R68: 609d494f-b566-11e7-a547-f6d178db6df1 | S68: 0893a63f-048c-11ef-ab64-0cc47af964e9 | T68: лист | U68: м2 | V68: fa6fadf3-b578-11e7-a547-f6d178db6df1 | W68: Склад упаковки готовой продукции (ЗСП) | X68: 198 | Y68: 302 544,00 | Z68: 798.387 | AA68: 67.37 | AB68: Слопласт | AD68: 50 424,00 | AE68: 1 528,00 | AF68: Мебель | AG68: d30b1e43-164d-11f1-99b9-00155dde6a00 | AH68: e1cib/data/Документ.РеализацияТоваровУслуг?ref=ab690cc47af964e911efda2f5528c09f | AI68: aa40444f-b08f-11ef-ab69-0cc47af964e90893a63f-048c-11ef-ab64-0cc47af964e9 | AJ68: УП-00099753
A69: ERP | B69: 45999.843 | C69: a14f1b7e-f5ca-11ef-ab6a-0cc47af964e9 | D69: Реализация товаров и услуг ЗСУП-000919 от 28.02.2025 14:53:34 | E69: ЗСУП-000919 | F69: 45716.621 | G69: 1 | H69: 0 | I69: Реализация | J69: null | K69: 9e38a44e-b7d0-11e7-a547-f6d178db6df1 | L69: Реализовано | M69: bd5b30ac-573c-11eb-ab4b-0cc47af964e9 | N69: e534587a-e964-11e7-80e4-00155d000d00 | O69: ada5d5f6-f367-11e8-9fe3-d000e1470f5d | P69: d79896b0-11a7-11ed-ab55-0cc47af964e9 | Q69: 4bba30ca-29d6-11ed-ab55-0cc47af964e9 | R69: 609d494f-b566-11e7-a547-f6d178db6df1 | S69: 0893a63f-048c-11ef-ab64-0cc47af964e9 | T69: лист | U69: м2 | V69: fa6fadf3-b578-11e7-a547-f6d178db6df1 | W69: Склад упаковки готовой продукции (ЗСП) | X69: 95 | Y69: 137 940,00 | Z69: 383.065 | AA69: 32.324 | AB69: Слопласт | AD69: 22 990,00 | AE69: 1 452,00 | AF69: Мебель | AG69: e2e7dc1d-0bbd-11f1-99b9-00155dde6a00 | AH69: e1cib/data/Документ.РеализацияТоваровУслуг?ref=ab6a0cc47af964e911eff5caa14f1b7e | AI69: df87f30d-e3c8-11ef-ab6a-0cc47af964e90893a63f-048c-11ef-ab64-0cc47af964e9 | AJ69: УП-00099753
A70: ERP | B70: 45999.843 | C70: 8e2ad068-f5cb-11ef-ab6a-0cc47af964e9 | D70: Реализация товаров и услуг ЗСУП-000924 от 28.02.2025 15:00:16 | E70: ЗСУП-000924 | F70: 45716.625 | G70: 1 | H70: 0 | I70: Реализация | J70: null | K70: 9e38a44e-b7d0-11e7-a547-f6d178db6df1 | L70: Реализовано | M70: bd5b30ac-573c-11eb-ab4b-0cc47af964e9 | N70: e534587a-e964-11e7-80e4-00155d000d00 | O70: ada5d5f6-f367-11e8-9fe3-d000e1470f5d | P70: d79896b0-11a7-11ed-ab55-0cc47af964e9 | Q70: 4bba30ca-29d6-11ed-ab55-0cc47af964e9 | R70: 609d494f-b566-11e7-a547-f6d178db6df1 | S70: 0893a63f-048c-11ef-ab64-0cc47af964e9 | T70: лист | U70: м2 | V70: fa6fadf3-b578-11e7-a547-f6d178db6df1 | W70: Склад упаковки готовой продукции (ЗСП) | X70: 81 | Y70: 117 612,00 | Z70: 326.613 | AA70: 27.56 | AB70: Слопласт | AD70: 19 602,00 | AE70: 1 452,00 | AF70: Мебель | AG70: e2e7dc1d-0bbd-11f1-99b9-00155dde6a00 | AH70: e1cib/data/Документ.РеализацияТоваровУслуг?ref=ab6a0cc47af964e911eff5cb8e2ad068 | AI70: dd0c893c-f02a-11ef-ab6a-0cc47af964e90893a63f-048c-11ef-ab64-0cc47af964e9 | AJ70: УП-00099753
A71: ERP | B71: 45999.843 | C71: d4d33e6e-f5d9-11ef-ab6a-0cc47af964e9 | D71: Реализация товаров и услуг ЗСУП-000929 от 28.02.2025 16:42:20 | E71: ЗСУП-000929 | F71: 45716.696 | G71: 1 | H71: 0 | I71: Реализация | J71: null | K71: 9e38a44e-b7d0-11e7-a547-f6d178db6df1 | L71: Реализовано | M71: f422c0a3-be06-11e6-80dc-00155d000d00 | N71: 043fe15a-a8fe-11e3-a2e4-0015171241a4 | O71: 04e19795-f36b-11e8-9fe3-d000e1470f5d | P71: f8e09145-5001-11ef-ab64-0cc47af964e9 | Q71: 0d1dd908-1fa2-11ed-ab55-0cc47af964e9 | R71: 609d494f-b566-11e7-a547-f6d178db6df1 | S71: 0893a63f-048c-11ef-ab64-0cc47af964e9 | T71: лист | U71: м2 | V71: fa6fadf3-b578-11e7-a547-f6d178db6df1 | W71: Склад упаковки готовой продукции (ЗСП) | X71: 12 | Y71: 18 336,00 | Z71: 48.387 | AA71: 4.083 | AB71: Слопласт | AD71: 3 056,00 | AE71: 1 528,00 | AF71: Мебель | AG71: e2e7dc1d-0bbd-11f1-99b9-00155dde6a00 | AH71: e1cib/data/Документ.РеализацияТоваровУслуг?ref=ab6a0cc47af964e911eff5d9d4d33e6e | AI71: 5f5ac4cb-ed33-11ef-ab6a-0cc47af964e90893a63f-048c-11ef-ab64-0cc47af964e9 | AJ71: УП-00099753
A72: ERP | B72: 45999.843 | C72: eda18edb-0e0d-11f0-ab6a-0cc47af964e9 | D72: Реализация товаров и услуг ЗСУП-001397 от 31.03.2025 11:55:52 | E72: ЗСУП-001397 | F72: 45747.497 | G72: 1 | H72: 0 | I72: Реализация | J72: null | K72: 9e38a44e-b7d0-11e7-a547-f6d178db6df1 | L72: Реализовано | M72: 05f2ed7a-4034-11ef-8110-00155d000d00 | N72: e057ce73-f36b-11e8-9fe3-d000e1470f5d | O72: e057ce74-f36b-11e8-9fe3-d000e1470f5d | P72: 3c80ed09-1193-11ed-ab55-0cc47af964e9 | Q72: 4850fc4c-226d-11ea-ab44-0cc47af964e9 | R72: 55c87efc-b566-11e7-a547-f6d178db6df1 | S72: 0893a63f-048c-11ef-ab64-0cc47af964e9 | T72: лист | U72: м2 | V72: fa6fadf3-b578-11e7-a547-f6d178db6df1 | W72: Склад упаковки готовой продукции (ЗСП) | X72: 24 | Y72: 43 008,00 | Z72: 96.774 | AA72: 8.166 | AB72: Слопласт | AD72: 7 168,00 | AE72: 1 792,00 | AF72: Мебель | AG72: e2e7dc1d-0bbd-11f1-99b9-00155dde6a00 | AH72: e1cib/data/Документ.РеализацияТоваровУслуг?ref=ab6a0cc47af964e911f00e0deda18edb | AI72: 50328b63-04c2-11f0-ab6a-0cc47af964e90893a63f-048c-11ef-ab64-0cc47af964e9 | AJ72: УП-00099753
A73: ERP | B73: 45999.843 | C73: 4135be23-0e3f-11f0-ab6a-0cc47af964e9 | D73: Реализация товаров и услуг ЗСУП-001430 от 31.03.2025 17:48:49 | E73: ЗСУП-001430 | F73: 45747.742 | G73: 1 | H73: 0 | I73: Реализация | J73: null | K73: 9e38a44e-b7d0-11e7-a547-f6d178db6df1 | L73: Реализовано | M73: 05f2ed7a-4034-11ef-8110-00155d000d00 | N73: e534587a-e964-11e7-80e4-00155d000d00 | O73: ada5d5f6-f367-11e8-9fe3-d000e1470f5d | P73: d79896b0-11a7-11ed-ab55-0cc47af964e9 | Q73: 4bba30ca-29d6-11ed-ab55-0cc47af964e9 | R73: 609d494f-b566-11e7-a547-f6d178db6df1 | S73: 0893a63f-048c-11ef-ab64-0cc47af964e9 | T73: лист | U73: м2 | V73: fa6fadf3-b578-11e7-a547-f6d178db6df1 | W73: Склад упаковки готовой продукции (ЗСП) | X73: 104 | Y73: 151 008,00 | Z73: 419.355 | AA73: 35.386 | AB73: Слопласт | AD73: 25 168,00 | AE73: 1 452,00 | AF73: Мебель | AG73: e2e7dc1d-0bbd-11f1-99b9-00155dde6a00 | AH73: e1cib/data/Документ.РеализацияТоваровУслуг?ref=ab6a0cc47af964e911f00e3f4135be23 | AI73: 70556176-0659-11f0-ab6a-0cc47af964e90893a63f-048c-11ef-ab64-0cc47af964e9 | AJ73: УП-00099753
A74: ERP | B74: 45999.843 | C74: 02d9936a-1c37-11f0-ab6a-0cc47af964e9 | D74: Реализация товаров и услуг ЗСУП-001642 от 18.04.2025 12:25:05 | E74: ЗСУП-001642 | F74: 45765.517 | G74: 1 | H74: 0 | I74: Реализация | J74: null | K74: 9e38a44e-b7d0-11e7-a547-f6d178db6df1 | L74: Реализовано | M74: 01d4de8c-6aaf-11ef-8110-00155d000d00 | N74: 9a673e3c-e968-11e7-80e4-00155d000d00 | O74: 63c14d00-f368-11e8-9fe3-d000e1470f5d | P74: e75a859d-7b4c-11ef-ab68-0cc47af964e9 | Q74: 7fe1a657-2268-11ea-ab44-0cc47af964e9 | R74: 609d494f-b566-11e7-a547-f6d178db6df1 | S74: 0893a63f-048c-11ef-ab64-0cc47af964e9 | T74: лист | U74: м2 | V74: fa6fadf3-b578-11e7-a547-f6d178db6df1 | W74: Склад упаковки готовой продукции (ЗСП) | X74: 24 | Y74: 36 672,00 | Z74: 96.774 | AA74: 8.166 | AB74: Слопласт | AD74: 6 112,00 | AE74: 1 528,00 | AF74: Мебель | AG74: e2e7dc1d-0bbd-11f1-99b9-00155dde6a00 | AH74: e1cib/data/Документ.РеализацияТоваровУслуг?ref=ab6a0cc47af964e911f01c3702d9936a | AI74: a50cb6e5-1161-11f0-ab6a-0cc47af964e90893a63f-048c-11ef-ab64-0cc47af964e9 | AJ74: УП-00099753
A75: ERP | B75: 45999.843 | C75: faff8f37-25cd-11f0-ab6a-0cc47af964e9 | D75: Реализация товаров и услуг ЗСУП-001830 от 30.04.2025 17:18:30 | E75: ЗСУП-001830 | F75: 45777.721 | G75: 1 | H75: 0 | I75: Реализация | J75: null | K75: 9e38a44e-b7d0-11e7-a547-f6d178db6df1 | L75: Реализовано | M75: 05f2ed7a-4034-11ef-8110-00155d000d00 | N75: 3fa69b08-b7a5-11e2-ae63-0015171241a4 | O75: 35ad1025-f36b-11e8-9fe3-d000e1470f5d | P75: 98eb8223-4986-11ef-ab64-0cc47af964e9 | Q75: 52094fa9-769a-11eb-ab4c-0cc47af964e9 | R75: 55c87efc-b566-11e7-a547-f6d178db6df1 | S75: 0893a63f-048c-11ef-ab64-0cc47af964e9 | T75: лист | U75: м2 | V75: fa6fadf3-b578-11e7-a547-f6d178db6df1 | W75: Склад упаковки готовой продукции (ЗСП) | X75: 194 | Y75: 296 432,00 | Z75: 782.258 | AA75: 66.009 | AB75: Слопласт | AD75: 49 405,33 | AE75: 1 528,00 | AF75: Мебель | AG75: ed25a087-212c-11f1-99bb-00155dde6a00 | AH75: e1cib/data/Документ.РеализацияТоваровУслуг?ref=ab6a0cc47af964e911f025cdfaff8f37 | AI75: 3ee47088-25a1-11f0-ab6a-0cc47af964e90893a63f-048c-11ef-ab64-0cc47af964e9 | AJ75: УП-00099753
A76: ERP | B76: 45999.843 | C76: cb6f317e-36ee-11f0-ab6b-0cc47af964e9 | D76: Реализация товаров и услуг ЗСУП-001990 от 22.05.2025 12:26:12 | E76: ЗСУП-001990 | F76: 45799.518 | G76: 1 | H76: 0 | I76: Реализация | J76: null | K76: 9e38a44e-b7d0-11e7-a547-f6d178db6df1 | L76: Реализовано | M76: 01d4de8c-6aaf-11ef-8110-00155d000d00 | N76: e534587a-e964-11e7-80e4-00155d000d00 | O76: ada5d5f6-f367-11e8-9fe3-d000e1470f5d | P76: d79896b0-11a7-11ed-ab55-0cc47af964e9 | Q76: 4bba30ca-29d6-11ed-ab55-0cc47af964e9 | R76: 609d494f-b566-11e7-a547-f6d178db6df1 | S76: 0893a63f-048c-11ef-ab64-0cc47af964e9 | T76: лист | U76: м2 | V76: fa6fadf3-b578-11e7-a547-f6d178db6df1 | W76: Склад упаковки готовой продукции (ЗСП) | X76: 34 | Y76: 49 368,00 | Z76: 137.097 | AA76: 11.569 | AB76: Слопласт | AD76: 8 228,00 | AE76: 1 452,00 | AF76: Мебель | AG76: ed25a087-212c-11f1-99bb-00155dde6a00 | AH76: e1cib/data/Документ.РеализацияТоваровУслуг?ref=ab6b0cc47af964e911f036eecb6f317e | AI76: a938c386-25c3-11f0-ab6a-0cc47af964e90893a63f-048c-11ef-ab64-0cc47af964e9 | AJ76: УП-00099753
... A80: ERP | B80: 45999.843 | C80: 8e17999e-5327-11f0-ab6b-0cc47af964e9 | D80: Реализация товаров и услуг ЗСУП-002453 от 27.06.2025 10:23:03 | E80: ЗСУП-002453 | F80: 45835.433 | G80: 1 | H80: 0 | I80: Реализация | J80: null | K80: 9e38a44e-b7d0-11e7-a547-f6d178db6df1 | L80: Реализовано | M80: 05f2ed7a-4034-11ef-8110-00155d000d00 | N80: 043fe15a-a8fe-11e3-a2e4-0015171241a4 | O80: 04e19795-f36b-11e8-9fe3-d000e1470f5d | P80: 144db961-4be7-11ef-ab64-0cc47af964e9 | Q80: 0d1dd908-1fa2-11ed-ab55-0cc47af964e9 | R80: 609d494f-b566-11e7-a547-f6d178db6df1 | S80: 0893a63f-048c-11ef-ab64-0cc47af964e9 | T80: лист | U80: м2 | V80: fa6fadf3-b578-11e7-a547-f6d178db6df1 | W80: Склад упаковки готовой продукции (ЗСП) | X80: 34 | Y80: 44 132,00 | Z80: 137.097 | AA80: 11.569 | AB80: Слопласт | AD80: 7 355,33 | AE80: 1 298,00 | AF80: Мебель | AG80: ed25a087-212c-11f1-99bb-00155dde6a00 | AH80: e1cib/data/Документ.РеализацияТоваровУслуг?ref=ab6b0cc47af964e911f053278e17999e | AI80: d58f4d92-4602-11f0-ab6b-0cc47af964e90893a63f-048c-11ef-ab64-0cc47af964e9 | AJ80: УП-00099753
A81: ERP | B81: 45999.843 | C81: 559805e6-557e-11f0-ab6b-0cc47af964e9 | D81: Реализация товаров и услуг ЗСУП-002480 от 30.06.2025 9:49:17 | E81: ЗСУП-002480 | F81: 45838.409 | G81: 1 | H81: 0 | I81: Реализация | J81: null | K81: 9e38a44e-b7d0-11e7-a547-f6d178db6df1 | L81: Реализовано | M81: 05f2ed7a-4034-11ef-8110-00155d000d00 | N81: fc4ae344-ad9b-11eb-ab4c-0cc47af964e9 | O81: fc4ae347-ad9b-11eb-ab4c-0cc47af964e9 | P81: aee0dded-e7be-11ef-ab6a-0cc47af964e9 | Q81: 54206bf8-fefd-11ea-ab46-0cc47af964e9 | R81: 55c87efc-b566-11e7-a547-f6d178db6df1 | S81: 0893a63f-048c-11ef-ab64-0cc47af964e9 | T81: лист | U81: м2 | V81: fa6fadf3-b578-11e7-a547-f6d178db6df1 | W81: Склад упаковки готовой продукции (ЗСП) | X81: 12 | Y81: 15 288,00 | Z81: 48.387 | AA81: 4.083 | AB81: Слопласт | AD81: 0 | AE81: 1 274,00 | AF81: Мебель | AG81: ed25a087-212c-11f1-99bb-00155dde6a00 | AH81: e1cib/data/Документ.РеализацияТоваровУслуг?ref=ab6b0cc47af964e911f0557e559805e6 | AI81: 3d1aabfe-4609-11f0-ab6b-0cc47af964e90893a63f-048c-11ef-ab64-0cc47af964e9 | AJ81: УП-00099753
A82: ERP | B82: 45999.843 | C82: a4567eb7-55b9-11f0-ab6b-0cc47af964e9 | D82: Реализация товаров и услуг ЗСУП-002508 от 30.06.2025 16:53:48 | E82: ЗСУП-002508 | F82: 45838.704 | G82: 1 | H82: 0 | I82: Реализация | J82: null | K82: 9e38a44e-b7d0-11e7-a547-f6d178db6df1 | L82: Реализовано | M82: 01d4de8c-6aaf-11ef-8110-00155d000d00 | N82: e534587a-e964-11e7-80e4-00155d000d00 | O82: ada5d5f6-f367-11e8-9fe3-d000e1470f5d | P82: d79896b0-11a7-11ed-ab55-0cc47af964e9 | Q82: 4bba30ca-29d6-11ed-ab55-0cc47af964e9 | R82: 609d494f-b566-11e7-a547-f6d178db6df1 | S82: 0893a63f-048c-11ef-ab64-0cc47af964e9 | T82: лист | U82: м2 | V82: fa6fadf3-b578-11e7-a547-f6d178db6df1 | W82: Склад упаковки готовой продукции (ЗСП) | X82: 35 | Y82: 50 820,00 | Z82: 141.129 | AA82: 11.909 | AB82: Слопласт | AD82: 8 470,00 | AE82: 1 452,00 | AF82: Мебель | AG82: cc3a40a9-1ee5-11f1-99bb-00155dde6a00 | AH82: e1cib/data/Документ.РеализацияТоваровУслуг?ref=ab6b0cc47af964e911f055b9a4567eb7 | AI82: cb5fb174-4aab-11f0-ab6b-0cc47af964e90893a63f-048c-11ef-ab64-0cc47af964e9 | AJ82: УП-00099753
A83: ERP | B83: 45999.843 | C83: 375c8e46-55be-11f0-ab6b-0cc47af964e9 | D83: Реализация товаров и услуг ЗСУП-002513 от 30.06.2025 17:26:32 | E83: ЗСУП-002513 | F83: 45838.727 | G83: 1 | H83: 0 | I83: Реализация | J83: null | K83: 9e38a44e-b7d0-11e7-a547-f6d178db6df1 | L83: Реализовано | M83: 01d4de8c-6aaf-11ef-8110-00155d000d00 | N83: e534587a-e964-11e7-80e4-00155d000d00 | O83: ada5d5f6-f367-11e8-9fe3-d000e1470f5d | P83: d79896b0-11a7-11ed-ab55-0cc47af964e9 | Q83: 4bba30ca-29d6-11ed-ab55-0cc47af964e9 | R83: 609d494f-b566-11e7-a547-f6d178db6df1 | S83: 0893a63f-048c-11ef-ab64-0cc47af964e9 | T83: лист | U83: м2 | V83: fa6fadf3-b578-11e7-a547-f6d178db6df1 | W83: Склад упаковки готовой продукции (ЗСП) | X83: 59 | Y83: 85 668,00 | Z83: 237.903 | AA83: 20.075 | AB83: Слопласт | AD83: 14 278,00 | AE83: 1 452,00 | AF83: Мебель | AG83: cc3a40a9-1ee5-11f1-99bb-00155dde6a00 | AH83: e1cib/data/Документ.РеализацияТоваровУслуг?ref=ab6b0cc47af964e911f055be375c8e46 | AI83: c51e7757-50d7-11f0-ab6b-0cc47af964e90893a63f-048c-11ef-ab64-0cc47af964e9 | AJ83: УП-00099753
A84: ERP | B84: 45999.843 | C84: 914fe8db-5b08-11f0-ab6b-0cc47af964e9 | D84: Реализация товаров и услуг ЗСУП-002580 от 07.07.2025 11:01:22 | E84: ЗСУП-002580 | F84: 45845.459 | G84: 1 | H84: 0 | I84: Реализация | J84: null | K84: 9e38a44e-b7d0-11e7-a547-f6d178db6df1 | L84: Реализовано | M84: 01d4de8c-6aaf-11ef-8110-00155d000d00 | N84: 9a673e3c-e968-11e7-80e4-00155d000d00 | O84: 63c14d00-f368-11e8-9fe3-d000e1470f5d | P84: e75a859d-7b4c-11ef-ab68-0cc47af964e9 | Q84: 7fe1a657-2268-11ea-ab44-0cc47af964e9 | R84: 609d494f-b566-11e7-a547-f6d178db6df1 | S84: 0893a63f-048c-11ef-ab64-0cc47af964e9 | T84: лист | U84: м2 | V84: fa6fadf3-b578-11e7-a547-f6d178db6df1 | W84: Склад упаковки готовой продукции (ЗСП) | X84: 12 | Y84: 18 336,00 | Z84: 48.387 | AA84: 4.083 | AB84: Слопласт | AD84: 3 056,00 | AE84: 1 528,00 | AF84: Мебель | AG84: cc3a40a9-1ee5-11f1-99bb-00155dde6a00 | AH84: e1cib/data/Документ.РеализацияТоваровУслуг?ref=ab6b0cc47af964e911f05b08914fe8db | AI84: f7d6f2e5-5027-11f0-ab6b-0cc47af964e90893a63f-048c-11ef-ab64-0cc47af964e9 | AJ84: УП-00099753
A85: ERP | B85: 45999.843 | C85: b5149668-5e24-11f0-ab6b-0cc47af964e9 | D85: Реализация товаров и услуг ЗСУП-002651 от 14.07.2025 0:00:00 | E85: ЗСУП-002651 | F85: 45852 | G85: 1 | H85: 0 | I85: Реализация | J85: null | K85: 9e38a44e-b7d0-11e7-a547-f6d178db6df1 | L85: Реализовано | M85: 01d4de8c-6aaf-11ef-8110-00155d000d00 | N85: e057ce73-f36b-11e8-9fe3-d000e1470f5d | O85: e057ce74-f36b-11e8-9fe3-d000e1470f5d | P85: d3fb935e-45ec-11f0-ab6b-0cc47af964e9 | Q85: 4850fc4c-226d-11ea-ab44-0cc47af964e9 | R85: 55c87efc-b566-11e7-a547-f6d178db6df1 | S85: 0893a63f-048c-11ef-ab64-0cc47af964e9 | T85: лист | U85: м2 | V85: fa6fadf3-b578-11e7-a547-f6d178db6df1 | W85: Склад упаковки готовой продукции (ЗСП) | X85: 12 | Y85: 21 504,00 | Z85: 48.387 | AA85: 4.083 | AB85: Слопласт | AD85: 3 584,00 | AE85: 1 792,00 | AF85: Мебель | AG85: cc3a40a9-1ee5-11f1-99bb-00155dde6a00 | AH85: e1cib/data/Документ.РеализацияТоваровУслуг?ref=ab6b0cc47af964e911f05e24b5149668 | AI85: 2d29b56f-45ec-11f0-ab6b-0cc47af964e90893a63f-048c-11ef-ab64-0cc47af964e9 | AJ85: УП-00099753
A86: ERP | B86: 45999.843 | C86: cbccf8f9-6926-11f0-ab6b-0cc47af964e9 | D86: Реализация товаров и услуг ЗСУП-002840 от 25.07.2025 10:13:03 | E86: ЗСУП-002840 | F86: 45863.426 | G86: 1 | H86: 0 | I86: Реализация | J86: null | K86: 9e38a44e-b7d0-11e7-a547-f6d178db6df1 | L86: Реализовано | M86: 05f2ed7a-4034-11ef-8110-00155d000d00 | N86: 043fe15a-a8fe-11e3-a2e4-0015171241a4 | O86: 04e19795-f36b-11e8-9fe3-d000e1470f5d | P86: f8e09145-5001-11ef-ab64-0cc47af964e9 | Q86: 0d1dd908-1fa2-11ed-ab55-0cc47af964e9 | R86: 609d494f-b566-11e7-a547-f6d178db6df1 | S86: 0893a63f-048c-11ef-ab64-0cc47af964e9 | T86: лист | U86: м2 | V86: fa6fadf3-b578-11e7-a547-f6d178db6df1 | W86: Склад упаковки готовой продукции (ЗСП) | X86: 23 | Y86: 29 854,00 | Z86: 92.742 | AA86: 7.826 | AB86: Слопласт | AD86: 4 975,67 | AE86: 1 298,00 | AF86: Мебель | AG86: cc3a40a9-1ee5-11f1-99bb-00155dde6a00 | AH86: e1cib/data/Документ.РеализацияТоваровУслуг?ref=ab6b0cc47af964e911f06926cbccf8f9 | AI86: d5f19222-5ccd-11f0-ab6b-0cc47af964e90893a63f-048c-11ef-ab64-0cc47af964e9 | AJ86: УП-00099753
A87: ERP | B87: 45999.843 | C87: 6194b3b8-6b88-11f0-ab6b-0cc47af964e9 | D87: Реализация товаров и услуг ЗСУП-002862 от 28.07.2025 10:56:35 | E87: ЗСУП-002862 | F87: 45866.456 | G87: 1 | H87: 0 | I87: Реализация | J87: null | K87: 9e38a44e-b7d0-11e7-a547-f6d178db6df1 | L87: Реализовано | M87: 01d4de8c-6aaf-11ef-8110-00155d000d00 | N87: 9a673e3c-e968-11e7-80e4-00155d000d00 | O87: 63c14d00-f368-11e8-9fe3-d000e1470f5d | P87: e75a859d-7b4c-11ef-ab68-0cc47af964e9 | Q87: 7fe1a657-2268-11ea-ab44-0cc47af964e9 | R87: 609d494f-b566-11e7-a547-f6d178db6df1 | S87: 0893a63f-048c-11ef-ab64-0cc47af964e9 | T87: лист | U87: м2 | V87: fa6fadf3-b578-11e7-a547-f6d178db6df1 | W87: Склад упаковки готовой продукции (ЗСП) | X87: 12 | Y87: 18 336,00 | Z87: 48.387 | AA87: 4.083 | AB87: Слопласт | AD87: 3 056,00 | AE87: 1 528,00 | AF87: Мебель | AG87: 45b6d95f-fc4c-11f0-99b9-00155dde6a00 | AH87: e1cib/data/Документ.РеализацияТоваровУслуг?ref=ab6b0cc47af964e911f06b886194b3b8 | AI87: 4bce1267-5c04-11f0-ab6b-0cc47af964e90893a63f-048c-11ef-ab64-0cc47af964e9 | AJ87: УП-00099753
A88: ERP | B88: 45999.843 | C88: ec745707-6c5a-11f0-ab6b-0cc47af964e9 | D88: Реализация товаров и услуг ЗСУП-002875 от 29.07.2025 12:03:43 | E88: ЗСУП-002875 | F88: 45867.503 | G88: 1 | H88: 0 | I88: Реализация | J88: null | K88: 9e38a44e-b7d0-11e7-a547-f6d178db6df1 | L88: Реализовано | M88: 05f2ed7a-4034-11ef-8110-00155d000d00 | N88: 3fa69b08-b7a5-11e2-ae63-0015171241a4 | O88: 35ad1025-f36b-11e8-9fe3-d000e1470f5d | P88: 98eb8223-4986-11ef-ab64-0cc47af964e9 | Q88: 52094fa9-769a-11eb-ab4c-0cc47af964e9 | R88: 55c87efc-b566-11e7-a547-f6d178db6df1 | S88: 0893a63f-048c-11ef-ab64-0cc47af964e9 | T88: лист | U88: м2 | V88: fa6fadf3-b578-11e7-a547-f6d178db6df1 | W88: Склад упаковки готовой продукции (ЗСП) | X88: 106 | Y88: 161 968,00 | Z88: 427.419 | AA88: 36.067 | AB88: Слопласт | AD88: 26 994,67 | AE88: 1 528,00 | AF88: Мебель | AG88: 45b6d95f-fc4c-11f0-99b9-00155dde6a00 | AH88: e1cib/data/Документ.РеализацияТоваровУслуг?ref=ab6b0cc47af964e911f06c5aec745707 | AI88: bf436c7b-519f-11f0-ab6b-0cc47af964e90893a63f-048c-11ef-ab64-0cc47af964e9 | AJ88: УП-00099753
A89: ERP | B89: 45999.843 | C89: 9adfbb6e-79a8-11f0-99b7-00155dde6a00 | D89: Реализация товаров и услуг ЗСУП-003093 от 15.08.2025 10:22:31 | E89: ЗСУП-003093 | F89: 45884.432 | G89: 1 | H89: 0 | I89: Реализация | J89: null | K89: 9e38a44e-b7d0-11e7-a547-f6d178db6df1 | L89: Реализовано | M89: 01d4de8c-6aaf-11ef-8110-00155d000d00 | N89: e534587a-e964-11e7-80e4-00155d000d00 | O89: ada5d5f6-f367-11e8-9fe3-d000e1470f5d | P89: d79896b0-11a7-11ed-ab55-0cc47af964e9 | Q89: 4bba30ca-29d6-11ed-ab55-0cc47af964e9 | R89: 609d494f-b566-11e7-a547-f6d178db6df1 | S89: 0893a63f-048c-11ef-ab64-0cc47af964e9 | T89: лист | U89: м2 | V89: fa6fadf3-b578-11e7-a547-f6d178db6df1 | W89: Склад упаковки готовой продукции (ЗСП) | X89: 60 | Y89: 84 000,00 | Z89: 241.935 | AA89: 20.415 | AB89: Слопласт | AD89: 14 000,00 | AE89: 1 400,00 | AF89: Мебель | AG89: 45b6d95f-fc4c-11f0-99b9-00155dde6a00 | AH89: e1cib/data/Документ.РеализацияТоваровУслуг?ref=99b700155dde6a0011f079a89adfbb6e | AI89: 17f928b2-67cd-11f0-ab6b-0cc47af964e90893a63f-048c-11ef-ab64-0cc47af964e9 | AJ89: УП-00099753
A90: ERP | B90: 45999.843 | C90: 727e8b43-79a9-11f0-99b7-00155dde6a00 | D90: Реализация товаров и услуг ЗСУП-003095 от 15.08.2025 10:28:33 | E90: ЗСУП-003095 | F90: 45884.436 | G90: 1 | H90: 0 | I90: Реализация | J90: null | K90: 9e38a44e-b7d0-11e7-a547-f6d178db6df1 | L90: Реализовано | M90: 01d4de8c-6aaf-11ef-8110-00155d000d00 | N90: e534587a-e964-11e7-80e4-00155d000d00 | O90: ada5d5f6-f367-11e8-9fe3-d000e1470f5d | P90: d79896b0-11a7-11ed-ab55-0cc47af964e9 | Q90: 4bba30ca-29d6-11ed-ab55-0cc47af964e9 | R90: 609d494f-b566-11e7-a547-f6d178db6df1 | S90: 0893a63f-048c-11ef-ab64-0cc47af964e9 | T90: лист | U90: м2 | V90: fa6fadf3-b578-11e7-a547-f6d178db6df1 | W90: Склад упаковки готовой продукции (ЗСП) | X90: 36 | Y90: 50 400,00 | Z90: 145.161 | AA90: 12.249 | AB90: Слопласт | AD90: 8 400,00 | AE90: 1 400,00 | AF90: Мебель | AG90: 45b6d95f-fc4c-11f0-99b9-00155dde6a00 | AH90: e1cib/data/Документ.РеализацияТоваровУслуг?ref=99b700155dde6a0011f079a9727e8b43 | AI90: a413654c-6948-11f0-ab6b-0cc47af964e90893a63f-048c-11ef-ab64-0cc47af964e9 | AJ90: УП-00099753
A91: ERP | B91: 45999.843 | C91: 45c43427-7c09-11f0-99b7-00155dde6a00 | D91: Реализация товаров и услуг ЗСУП-003116 от 18.08.2025 10:59:32 | E91: ЗСУП-003116 | F91: 45887.458 | G91: 1 | H91: 0 | I91: Реализация | J91: null | K91: 9e38a44e-b7d0-11e7-a547-f6d178db6df1 | L91: Реализовано | M91: 01d4de8c-6aaf-11ef-8110-00155d000d00 | N91: 9a673e3c-e968-11e7-80e4-00155d000d00 | O91: 63c14d00-f368-11e8-9fe3-d000e1470f5d | P91: e75a859d-7b4c-11ef-ab68-0cc47af964e9 | Q91: 7fe1a657-2268-11ea-ab44-0cc47af964e9 | R91: 609d494f-b566-11e7-a547-f6d178db6df1 | S91: 0893a63f-048c-11ef-ab64-0cc47af964e9 | T91: лист | U91: м2 | V91: fa6fadf3-b578-11e7-a547-f6d178db6df1 | W91: Склад упаковки готовой продукции (ЗСП) | X91: 9 | Y91: 13 752,00 | Z91: 36.29 | AA91: 3.062 | AB91: Слопласт | AD91: 2 292,00 | AE91: 1 528,00 | AF91: Мебель | AG91: 45b6d95f-fc4c-11f0-99b9-00155dde6a00 | AH91: e1cib/data/Документ.РеализацияТоваровУслуг?ref=99b700155dde6a0011f07c0945c43427 | AI91: c0a6183f-6c52-11f0-ab6b-0cc47af964e90893a63f-048c-11ef-ab64-0cc47af964e9 | AJ91: УП-00099753
A92: ERP | B92: 45999.843 | C92: 08ffdc10-84d2-11f0-99b7-00155dde6a00 | D92: Реализация товаров и услуг ЗСУП-003345 от 29.08.2025 15:16:48 | E92: ЗСУП-003345 | F92: 45898.637 | G92: 1 | H92: 0 | I92: Реализация | J92: null | K92: 9e38a44e-b7d0-11e7-a547-f6d178db6df1 | L92: Реализовано | M92: 01d4de8c-6aaf-11ef-8110-00155d000d00 | N92: e534587a-e964-11e7-80e4-00155d000d00 | O92: ada5d5f6-f367-11e8-9fe3-d000e1470f5d | P92: d79896b0-11a7-11ed-ab55-0cc47af964e9 | Q92: 4bba30ca-29d6-11ed-ab55-0cc47af964e9 | R92: 609d494f-b566-11e7-a547-f6d178db6df1 | S92: 0893a63f-048c-11ef-ab64-0cc47af964e9 | T92: лист | U92: м2 | V92: fa6fadf3-b578-11e7-a547-f6d178db6df1 | W92: Склад упаковки готовой продукции (ЗСП) | X92: 87 | Y92: 121 800,00 | Z92: 350.806 | AA92: 29.602 | AB92: Слопласт | AD92: 20 300,00 | AE92: 1 400,00 | AF92: Мебель | AG92: 45b6d95f-fc4c-11f0-99b9-00155dde6a00 | AH92: e1cib/data/Документ.РеализацияТоваровУслуг?ref=99b700155dde6a0011f084d208ffdc10 | AI92: 6fb64f4a-6e0e-11f0-ab6c-0cc47af964e90893a63f-048c-11ef-ab64-0cc47af964e9 | AJ92: УП-00099753
A93: ERP | B93: 45999.843 | C93: 760dcc45-8a23-11f0-99b7-00155dde6a00 | D93: Реализация товаров и услуг ЗСУП-003390 от 05.09.2025 9:42:21 | E93: ЗСУП-003390 | F93: 45905.404 | G93: 1 | H93: 0 | I93: Реализация | J93: null | K93: 9e38a44e-b7d0-11e7-a547-f6d178db6df1 | L93: Реализовано | M93: 05f2ed7a-4034-11ef-8110-00155d000d00 | N93: 043fe15a-a8fe-11e3-a2e4-0015171241a4 | O93: 04e19795-f36b-11e8-9fe3-d000e1470f5d | P93: f8e09145-5001-11ef-ab64-0cc47af964e9 | Q93: 0d1dd908-1fa2-11ed-ab55-0cc47af964e9 | R93: 609d494f-b566-11e7-a547-f6d178db6df1 | S93: 0893a63f-048c-11ef-ab64-0cc47af964e9 | T93: лист | U93: м2 | V93: fa6fadf3-b578-11e7-a547-f6d178db6df1 | W93: Склад упаковки готовой продукции (ЗСП) | X93: 23 | Y93: 29 854,00 | Z93: 92.742 | AA93: 7.826 | AB93: Слопласт | AD93: 4 975,66 | AE93: 1 298,00 | AF93: Мебель | AG93: 45b6d95f-fc4c-11f0-99b9-00155dde6a00 | AH93: e1cib/data/Документ.РеализацияТоваровУслуг?ref=99b700155dde6a0011f08a23760dcc45 | AI93: acfeab31-6d2a-11f0-ab6b-0cc47af964e90893a63f-048c-11ef-ab64-0cc47af964e9 | AJ93: УП-00099753
... A102: ERP | B102: 45999.843 | C102: 2b3df927-b32b-11f0-99b8-00155dde6a00 | D102: Реализация товаров и услуг ЗСУП-004139 от 27.10.2025 14:50:44 | E102: ЗСУП-004139 | F102: 45957.619 | G102: 1 | H102: 0 | I102: Реализация | J102: null | K102: 9e38a44e-b7d0-11e7-a547-f6d178db6df1 | L102: Реализовано | M102: 01d4de8c-6aaf-11ef-8110-00155d000d00 | N102: 9a673e3c-e968-11e7-80e4-00155d000d00 | O102: 63c14d00-f368-11e8-9fe3-d000e1470f5d | P102: e75a859d-7b4c-11ef-ab68-0cc47af964e9 | Q102: 7fe1a657-2268-11ea-ab44-0cc47af964e9 | R102: 609d494f-b566-11e7-a547-f6d178db6df1 | S102: 0893a63f-048c-11ef-ab64-0cc47af964e9 | T102: лист | U102: м2 | V102: fa6fadf3-b578-11e7-a547-f6d178db6df1 | W102: Склад упаковки готовой продукции (ЗСП) | X102: 35 | Y102: 53 515,00 | Z102: 141.129 | AA102: 11.909 | AB102: Слопласт | AD102: 8 919,17 | AE102: 1 529,00 | AF102: Мебель | AG102: 886a2158-0bd4-11f1-99b9-00155dde6a00 | AH102: e1cib/data/Документ.РеализацияТоваровУслуг?ref=99b800155dde6a0011f0b32b2b3df927 | AI102: 6062c7de-9d3e-11f0-99b7-00155dde6a000893a63f-048c-11ef-ab64-0cc47af964e9 | AJ102: УП-00099753
A103: ERP | B103: 45999.843 | C103: 8cd87938-b3d1-11f0-99b8-00155dde6a00 | D103: Реализация товаров и услуг ЗСУП-004160 от 28.10.2025 10:41:44 | E103: ЗСУП-004160 | F103: 45958.446 | G103: 1 | H103: 0 | I103: Реализация | J103: null | K103: 9e38a44e-b7d0-11e7-a547-f6d178db6df1 | L103: Реализовано | M103: 05f2ed7a-4034-11ef-8110-00155d000d00 | N103: 3fa69b08-b7a5-11e2-ae63-0015171241a4 | O103: 35ad1025-f36b-11e8-9fe3-d000e1470f5d | P103: 98eb8223-4986-11ef-ab64-0cc47af964e9 | Q103: 52094fa9-769a-11eb-ab4c-0cc47af964e9 | R103: 55c87efc-b566-11e7-a547-f6d178db6df1 | S103: 0893a63f-048c-11ef-ab64-0cc47af964e9 | T103: лист | U103: м2 | V103: fa6fadf3-b578-11e7-a547-f6d178db6df1 | W103: Склад упаковки готовой продукции (ЗСП) | X103: 107 | Y103: 163 496,00 | Z103: 431.452 | AA103: 36.407 | AB103: Слопласт | AC103: С4 | AD103: 27 249,33 | AE103: 1 528,00 | AF103: Мебель | AG103: 886a2158-0bd4-11f1-99b9-00155dde6a00 | AH103: e1cib/data/Документ.РеализацияТоваровУслуг?ref=99b800155dde6a0011f0b3d18cd87938 | AI103: 3f4d9646-a441-11f0-99b7-00155dde6a000893a63f-048c-11ef-ab64-0cc47af964e9 | AJ103: УП-00099753
A104: ERP | B104: 45999.843 | C104: 7665967c-b4af-11f0-99b8-00155dde6a00 | D104: Реализация товаров и услуг ЗСУП-004200 от 29.10.2025 13:10:15 | E104: ЗСУП-004200 | F104: 45959.549 | G104: 1 | H104: 0 | I104: Реализация | J104: null | K104: 9e38a44e-b7d0-11e7-a547-f6d178db6df1 | L104: Реализовано | M104: 01d4de8c-6aaf-11ef-8110-00155d000d00 | N104: e057ce73-f36b-11e8-9fe3-d000e1470f5d | O104: e057ce74-f36b-11e8-9fe3-d000e1470f5d | P104: d3fb935e-45ec-11f0-ab6b-0cc47af964e9 | Q104: 4850fc4c-226d-11ea-ab44-0cc47af964e9 | R104: 55c87efc-b566-11e7-a547-f6d178db6df1 | S104: 0893a63f-048c-11ef-ab64-0cc47af964e9 | T104: лист | U104: м2 | V104: fa6fadf3-b578-11e7-a547-f6d178db6df1 | W104: Склад упаковки готовой продукции (ЗСП) | X104: 12 | Y104: 21 504,00 | Z104: 48.387 | AA104: 4.083 | AB104: Слопласт | AC104: С3 | AD104: 3 584,00 | AE104: 1 792,00 | AF104: Мебель | AG104: 886a2158-0bd4-11f1-99b9-00155dde6a00 | AH104: e1cib/data/Документ.РеализацияТоваровУслуг?ref=99b800155dde6a0011f0b4af7665967c | AI104: b3889823-93bd-11f0-99b7-00155dde6a000893a63f-048c-11ef-ab64-0cc47af964e9 | AJ104: УП-00099753
A105: ERP | B105: 45999.843 | C105: cfd48840-c38b-11f0-99b9-00155dde6a00 | D105: Реализация товаров и услуг ЗСУП-004544 от 17.11.2025 11:02:55 | E105: ЗСУП-004544 | F105: 45978.46 | G105: 1 | H105: 0 | I105: Реализация | J105: null | K105: 9e38a44e-b7d0-11e7-a547-f6d178db6df1 | L105: Реализовано | M105: 01d4de8c-6aaf-11ef-8110-00155d000d00 | N105: e534587a-e964-11e7-80e4-00155d000d00 | O105: ada5d5f6-f367-11e8-9fe3-d000e1470f5d | P105: d79896b0-11a7-11ed-ab55-0cc47af964e9 | Q105: 4bba30ca-29d6-11ed-ab55-0cc47af964e9 | R105: 609d494f-b566-11e7-a547-f6d178db6df1 | S105: 0893a63f-048c-11ef-ab64-0cc47af964e9 | T105: лист | U105: м2 | V105: fa6fadf3-b578-11e7-a547-f6d178db6df1 | W105: Склад упаковки готовой продукции (ЗСП) | X105: 104 | Y105: 151 008,00 | Z105: 419.355 | AA105: 35.386 | AB105: Слопласт | AD105: 25 168,00 | AE105: 1 452,00 | AF105: Мебель | AG105: 886a2158-0bd4-11f1-99b9-00155dde6a00 | AH105: e1cib/data/Документ.РеализацияТоваровУслуг?ref=99b900155dde6a0011f0c38bcfd48840 | AI105: 6ff6e5cb-b71c-11f0-99b8-00155dde6a000893a63f-048c-11ef-ab64-0cc47af964e9 | AJ105: УП-00099753
A106: ERP | B106: 46013.537 | C106: 1d075919-c552-11f0-99b9-00155dde6a00 | D106: Реализация товаров и услуг ЗСУП-004614 от 21.11.2025 0:00:00 | E106: ЗСУП-004614 | F106: 45982 | G106: 1 | H106: 0 | I106: Реализация | J106: null | K106: 9e38a44e-b7d0-11e7-a547-f6d178db6df1 | L106: Реализовано | M106: 05f2ed7a-4034-11ef-8110-00155d000d00 | N106: 043fe15a-a8fe-11e3-a2e4-0015171241a4 | O106: 04e19795-f36b-11e8-9fe3-d000e1470f5d | P106: f8e09145-5001-11ef-ab64-0cc47af964e9 | Q106: 0d1dd908-1fa2-11ed-ab55-0cc47af964e9 | R106: 609d494f-b566-11e7-a547-f6d178db6df1 | S106: 0893a63f-048c-11ef-ab64-0cc47af964e9 | T106: лист | U106: м2 | V106: fa6fadf3-b578-11e7-a547-f6d178db6df1 | W106: Склад упаковки готовой продукции (ЗСП) | X106: 25 | Y106: 32 450,00 | Z106: 100.806 | AA106: 8.506 | AB106: Слопласт | AD106: 5 408,33 | AE106: 1 298,00 | AF106: Мебель | AG106: 886a2158-0bd4-11f1-99b9-00155dde6a00 | AH106: e1cib/data/Документ.РеализацияТоваровУслуг?ref=99b900155dde6a0011f0c5521d075919 | AI106: 40d300f8-6ba4-11f0-ab6b-0cc47af964e90893a63f-048c-11ef-ab64-0cc47af964e9 | AJ106: УП-00099753
A107: ERP | B107: 46083.601 | C107: 053abe95-13be-11f1-99b9-00155dde6a00 | D107: Реализация товаров и услуг ЗСУП-000592 от 27.02.2026 12:23:49 | E107: ЗСУП-000592 | F107: 46080.517 | G107: 1 | H107: 0 | I107: Реализация | J107: null | K107: 9e38a44e-b7d0-11e7-a547-f6d178db6df1 | L107: Реализовано | M107: 01d4de8c-6aaf-11ef-8110-00155d000d00 | N107: 3fa69b08-b7a5-11e2-ae63-0015171241a4 | O107: 35ad1025-f36b-11e8-9fe3-d000e1470f5d | P107: 3ab8e4b6-0108-11f1-99b9-00155dde6a00 | Q107: 52094fa9-769a-11eb-ab4c-0cc47af964e9 | R107: 55c87efc-b566-11e7-a547-f6d178db6df1 | S107: 0893a63f-048c-11ef-ab64-0cc47af964e9 | T107: лист | U107: м2 | V107: fa6fadf3-b578-11e7-a547-f6d178db6df1 | W107: Склад упаковки готовой продукции (ЗСП) | X107: 58 | Y107: 90 364,00 | Z107: 233.871 | AA107: 170.462 | AB107: Слопласт | AD107: 16 295,15 | AE107: 1 558,00 | AF107: Мебель | AG107: 882b5916-116f-11f1-99b9-00155dde6a00 | AH107: e1cib/data/Документ.РеализацияТоваровУслуг?ref=99b900155dde6a0011f113be053abe95 | AI107: 670cadbb-0105-11f1-99b9-00155dde6a000893a63f-048c-11ef-ab64-0cc47af964e9 | AJ107: УП-00099753
A108: ERP | B108: 46084.684 | C108: 23fb3e93-13e1-11f1-99b9-00155dde6a00 | D108: Реализация товаров и услуг ЗСУП-000606 от 27.02.2026 16:35:16 | E108: ЗСУП-000606 | F108: 46080.691 | G108: 1 | H108: 0 | I108: Реализация | J108: null | K108: 9e38a44e-b7d0-11e7-a547-f6d178db6df1 | L108: Реализовано | M108: 01d4de8c-6aaf-11ef-8110-00155d000d00 | N108: e534587a-e964-11e7-80e4-00155d000d00 | O108: ada5d5f6-f367-11e8-9fe3-d000e1470f5d | P108: b7d087c7-e096-11f0-99b9-00155dde6a00 | Q108: 4bba30ca-29d6-11ed-ab55-0cc47af964e9 | R108: 609d494f-b566-11e7-a547-f6d178db6df1 | S108: 0893a63f-048c-11ef-ab64-0cc47af964e9 | T108: лист | U108: м2 | V108: fa6fadf3-b578-11e7-a547-f6d178db6df1 | W108: Склад упаковки готовой продукции (ЗСП) | X108: 43 | Y108: 60 200,00 | Z108: 173.387 | AA108: 126.377 | AB108: Слопласт | AD108: 10 855,74 | AE108: 1 400,00 | AF108: Мебель | AG108: 882b5916-116f-11f1-99b9-00155dde6a00 | AH108: e1cib/data/Документ.РеализацияТоваровУслуг?ref=99b900155dde6a0011f113e123fb3e93 | AI108: deac622f-010d-11f1-99b9-00155dde6a000893a63f-048c-11ef-ab64-0cc47af964e9 | AJ108: УП-00099753
A109: ERP | B109: 46084.684 | C109: b915e716-13e1-11f1-99b9-00155dde6a00 | D109: Реализация товаров и услуг ЗСУП-000608 от 27.02.2026 16:39:24 | E109: ЗСУП-000608 | F109: 46080.694 | G109: 1 | H109: 0 | I109: Реализация | J109: null | K109: 9e38a44e-b7d0-11e7-a547-f6d178db6df1 | L109: Реализовано | M109: 01d4de8c-6aaf-11ef-8110-00155d000d00 | N109: e534587a-e964-11e7-80e4-00155d000d00 | O109: ada5d5f6-f367-11e8-9fe3-d000e1470f5d | P109: b7d087c7-e096-11f0-99b9-00155dde6a00 | Q109: 4bba30ca-29d6-11ed-ab55-0cc47af964e9 | R109: 609d494f-b566-11e7-a547-f6d178db6df1 | S109: 0893a63f-048c-11ef-ab64-0cc47af964e9 | T109: лист | U109: м2 | V109: fa6fadf3-b578-11e7-a547-f6d178db6df1 | W109: Склад упаковки готовой продукции (ЗСП) | X109: 79 | Y109: 110 600,00 | Z109: 318.548 | AA109: 232.181 | AB109: Слопласт | AD109: 19 944,26 | AE109: 1 400,00 | AF109: Мебель | AG109: 882b5916-116f-11f1-99b9-00155dde6a00 | AH109: e1cib/data/Документ.РеализацияТоваровУслуг?ref=99b900155dde6a0011f113e1b915e716 | AI109: 6a5f63c4-f6a7-11f0-99b9-00155dde6a000893a63f-048c-11ef-ab64-0cc47af964e9 | AJ109: УП-00099753
A110: ERP | B110: 45999.843 | C110: 8440ed46-30a5-11f0-ab6b-0cc47af964e9 | D110: Реализация товаров и услуг ЗСУП-001928 от 14.05.2025 12:26:32 | E110: ЗСУП-001928 | F110: 45791.518 | G110: 1 | H110: 0 | I110: Реализация | J110: null | K110: 9e38a44e-b7d0-11e7-a547-f6d178db6df1 | L110: Реализовано | M110: 5e8bee44-e660-11e7-80e4-00155d000d00 | N110: 96f83f7d-0c87-11e9-ab3f-0cc47af964e9 | O110: 71f30c81-0c86-11e9-ab3f-0cc47af964e9 | P110: 39ef7673-0c94-11e9-ab3f-0cc47af964e9 | Q110: 72cbdb73-82ec-11ee-ab63-0cc47af964e9 | R110: 898e199b-b566-11e7-a547-f6d178db6df1 | S110: 000a1b10-c8be-11ed-ab59-0cc47af964e9 | T110: лист | U110: м2 | V110: 25dd4bf1-ec7b-11e7-80e4-00155d000d00 | W110: Склад сырья и материалов (брак) | X110: 156 | Y110: 56 948,38 | Z110: 647.303 | AA110: 0 | AB110: Декоративная бумага (пропитанная переработка) | AD110: 9 491,40 | AE110: 365.05 | AF110: Прочие материалы | AG110: 882b5916-116f-11f1-99b9-00155dde6a00 | AH110: e1cib/data/Документ.РеализацияТоваровУслуг?ref=ab6b0cc47af964e911f030a58440ed46 | AI110: 45e201e1-3093-11f0-ab6b-0cc47af964e9000a1b10-c8be-11ed-ab59-0cc47af964e9 | AJ110: УП-00085358
A111: ERP | B111: 46000.64 | C111: 3a78ecbb-cc65-11f0-99b9-00155dde6a00 | D111: Реализация товаров и услуг ЗСУП-004833 от 28.11.2025 17:19:20 | E111: ЗСУП-004833 | F111: 45989.722 | G111: 1 | H111: 0 | I111: Реализация | J111: null | K111: 9e38a44e-b7d0-11e7-a547-f6d178db6df1 | L111: Реализовано | M111: 01d4de8c-6aaf-11ef-8110-00155d000d00 | N111: e534587a-e964-11e7-80e4-00155d000d00 | O111: ada5d5f6-f367-11e8-9fe3-d000e1470f5d | P111: d79896b0-11a7-11ed-ab55-0cc47af964e9 | Q111: 4bba30ca-29d6-11ed-ab55-0cc47af964e9 | R111: 609d494f-b566-11e7-a547-f6d178db6df1 | S111: 11577069-090f-11ef-ab64-0cc47af964e9 | T111: лист | U111: м2 | V111: fa6fadf3-b578-11e7-a547-f6d178db6df1 | W111: Склад упаковки готовой продукции (ЗСП) | X111: 57 | Y111: 104 595,00 | Z111: 229.839 | AA111: 19.394 | AB111: Слопласт | AC111: Дилер_РФ | AD111: 17 432,50 | AE111: 1 835,00 | AF111: Мебель | AG111: 882b5916-116f-11f1-99b9-00155dde6a00 | AH111: e1cib/data/Документ.РеализацияТоваровУслуг?ref=99b900155dde6a0011f0cc653a78ecbb | AI111: 6ff6e5cb-b71c-11f0-99b8-00155dde6a0011577069-090f-11ef-ab64-0cc47af964e9 | AJ111: УП-00099854
A112: ERP | B112: 46010.537 | C112: 26185780-dcb0-11f0-99b9-00155dde6a00 | D112: Реализация товаров и услуг ЗСУП-005146 от 19.12.2025 10:56:03 | E112: ЗСУП-005146 | F112: 46010.456 | G112: 1 | H112: 0 | I112: Реализация | J112: null | K112: 9e38a44e-b7d0-11e7-a547-f6d178db6df1 | L112: Реализовано | M112: 01d4de8c-6aaf-11ef-8110-00155d000d00 | N112: e534587a-e964-11e7-80e4-00155d000d00 | O112: ada5d5f6-f367-11e8-9fe3-d000e1470f5d | P112: d79896b0-11a7-11ed-ab55-0cc47af964e9 | Q112: 4bba30ca-29d6-11ed-ab55-0cc47af964e9 | R112: 609d494f-b566-11e7-a547-f6d178db6df1 | S112: 11577069-090f-11ef-ab64-0cc47af964e9 | T112: лист | U112: м2 | V112: fa6fadf3-b578-11e7-a547-f6d178db6df1 | W112: Склад упаковки готовой продукции (ЗСП) | X112: 32 | Y112: 58 432,00 | Z112: 129.032 | AA112: 10.888 | AB112: Слопласт | AD112: 9 738,67 | AE112: 1 826,00 | AF112: Мебель | AG112: 882b5916-116f-11f1-99b9-00155dde6a00 | AH112: e1cib/data/Документ.РеализацияТоваровУслуг?ref=99b900155dde6a0011f0dcb026185780 | AI112: 0778be3f-c61c-11f0-99b9-00155dde6a0011577069-090f-11ef-ab64-0cc47af964e9 | AJ112: УП-00099854
A113: ERP | B113: 46038.47 | C113: 0d0d5979-e562-11f0-99b9-00155dde6a00 | D113: Реализация товаров и услуг ЗСУП-005355 от 30.12.2025 12:29:34 | E113: ЗСУП-005355 | F113: 46021.521 | G113: 1 | H113: 0 | I113: Реализация | J113: null | K113: 9e38a44e-b7d0-11e7-a547-f6d178db6df1 | L113: Реализовано | M113: 01d4de8c-6aaf-11ef-8110-00155d000d00 | N113: e534587a-e964-11e7-80e4-00155d000d00 | O113: ada5d5f6-f367-11e8-9fe3-d000e1470f5d | P113: d79896b0-11a7-11ed-ab55-0cc47af964e9 | Q113: 4bba30ca-29d6-11ed-ab55-0cc47af964e9 | R113: 609d494f-b566-11e7-a547-f6d178db6df1 | S113: 11577069-090f-11ef-ab64-0cc47af964e9 | T113: лист | U113: м2 | V113: fa6fadf3-b578-11e7-a547-f6d178db6df1 | W113: Склад упаковки готовой продукции (ЗСП) | X113: 3 | Y113: 5 478,00 | Z113: 12.097 | AA113: 1.021 | AB113: Слопласт | AD113: 913 | AE113: 1 826,00 | AF113: Мебель | AG113: 882b5916-116f-11f1-99b9-00155dde6a00 | AH113: e1cib/data/Документ.РеализацияТоваровУслуг?ref=99b900155dde6a0011f0e5620d0d5979 | AI113: 0778be3f-c61c-11f0-99b9-00155dde6a0011577069-090f-11ef-ab64-0cc47af964e9 | AJ113: УП-00099854
A114: ERP | B114: 46084.684 | C114: 23fb3e93-13e1-11f1-99b9-00155dde6a00 | D114: Реализация товаров и услуг ЗСУП-000606 от 27.02.2026 16:35:16 | E114: ЗСУП-000606 | F114: 46080.691 | G114: 1 | H114: 0 | I114: Реализация | J114: null | K114: 9e38a44e-b7d0-11e7-a547-f6d178db6df1 | L114: Реализовано | M114: 01d4de8c-6aaf-11ef-8110-00155d000d00 | N114: e534587a-e964-11e7-80e4-00155d000d00 | O114: ada5d5f6-f367-11e8-9fe3-d000e1470f5d | P114: b7d087c7-e096-11f0-99b9-00155dde6a00 | Q114: 4bba30ca-29d6-11ed-ab55-0cc47af964e9 | R114: 609d494f-b566-11e7-a547-f6d178db6df1 | S114: 11577069-090f-11ef-ab64-0cc47af964e9 | T114: лист | U114: м2 | V114: fa6fadf3-b578-11e7-a547-f6d178db6df1 | W114: Склад упаковки готовой продукции (ЗСП) | X114: 86 | Y114: 159 788,00 | Z114: 346.774 | AA114: 252.754 | AB114: Слопласт | AD114: 28 814,23 | AE114: 1 858,00 | AF114: Мебель | AG114: 882b5916-116f-11f1-99b9-00155dde6a00 | AH114: e1cib/data/Документ.РеализацияТоваровУслуг?ref=99b900155dde6a0011f113e123fb3e93 | AI114: deac622f-010d-11f1-99b9-00155dde6a0011577069-090f-11ef-ab64-0cc47af964e9 | AJ114: УП-00099854
A115: ERP | B115: 45999.843 | C115: 53c9dc80-93bc-11f0-99b7-00155dde6a00 | D115: Реализация товаров и услуг ЗСУП-003463 от 17.09.2025 14:49:17 | E115: ЗСУП-003463 | F115: 45917.618 | G115: 1 | H115: 0 | I115: Реализация | J115: null | K115: 9e38a44e-b7d0-11e7-a547-f6d178db6df1 | L115: Реализовано | M115: 8870b4a7-f73b-11e6-80de-00155d000d00 | N115: c64f81c5-f924-11ed-ab5f-0cc47af964e9 | O115: c64f81fe-f924-11ed-ab5f-0cc47af964e9 | P115: 69626225-8a26-11f0-99b7-00155dde6a00 | Q115: ab4b5364-f576-11ee-ab64-0cc47af964e9 | R115: 55c87efc-b566-11e7-a547-f6d178db6df1 | S115: 0013d1cd-3a4f-11e8-ab3d-0cc47af964e9 | T115: шт | U115: шт | V115: fa6fadf3-b578-11e7-a547-f6d178db6df1 | W115: Склад упаковки готовой продукции (ЗСП) | X115: 31 | Y115: 30 318,00 | Z115: 31 | AA115: 0 | AB115: Материалы прочее | AD115: 5 053,00 | AE115: 978 | AF115: Стройка | AG115: f38645b5-1d2d-11f1-99bb-00155dde6a00 | AH115: e1cib/data/Документ.РеализацияТоваровУслуг?ref=99b700155dde6a0011f093bc53c9dc80 | AI115: 7a584416-8a26-11f0-99b7-00155dde6a000013d1cd-3a4f-11e8-ab3d-0cc47af964e9 | AJ115: УП-00025923
...

Sheet spr_partners
B2: берем из Googlesheets
B4: https://docs.google.com/spreadsheets/d/e/2PACX-1vSBDkJMDuogKZmMW9zyKX9nEWSim1FqZWvib6JgMuTQHa8vmptQUss1Zu2RDZIVovRt26q1aIWg3rum/pub?output=xlsx
